Workbook
Name Metal: #REF!
Name Pop: #REF!
Name Jazz: #REF!
Name Electronic: #REF!
Name Classical: #REF!
Name International: #REF!
Name Hip_Hop: #REF!
Name R_B: #REF!
Name Rap: #REF!
Name Parent_Genre: #REF!
Name Other: #REF!
Name Rock: #REF!
Name Country: #REF!

Sheet Da Rules
A1: The Constitution of Music Book Club
A5: Bill of Rights | G5: Rules
A6: 1 | B6: Right to vote | G6: 1 | H6: The user shall post a song every Mon, Wed, Fri
A7: 2 | B7: Right to post any song | G7: 2 | H7: The user shall listen to each song until the song ends or for at least 6 minutes, whichever comes first
A8: 3 | G8: 3 | H8: The user shall be truthful with the votes
A9: 4 | G9: 4 | H9: The user shall not repeat a song
A10: 5 | G10: 5 | H10: Non-Proliferation Treaty
A11: 6 | G11: 6
A12: 7 | G12: 7
A13: 8 | G13: 8
A14: 9 | G14: 9
A15: 10 | G15: 10
A16: Rosey Faces | G16: Proposed Rules | M16: Logan | N16: Parker | O16: Giacomo | P16: Rosey | Q16: TTAC | R16: Weston | S16: Jake
A17: 1 | G17: 1 | H17: Lil TJay is banished to the shadow realm | M17: Y | N17: faggot | O17: W | R17: ?
A18: 2 | G18: 2 | H18: No Tinkering of Votes | M18: Y | N18: fag | O18: Tink By Smino | R18: 1 | S18: 🚁
A19: 3 | G19: 3 | H19: Amendment's only need 6/7 votes to pass :) | M19: Y | N19: fag | O19: 😡 | R19: 1 | S19: 🚁
A20: 4 | G20: 4 | H20: TTAC Daily 7 | N20: fag | P20: O/ | | R20: 1 | S20: 🛶
A21: 5 | G21: 5 | H21: Removal of all photos/gifs | O21: Inshallah | R21: 1 | S21: 🚁
A22: 6 | G22: 6 | H22: add flocco | O22: 🦉 | R22: 1
A23: 7 | G23: 7
A24: 8 | G24: 8
A25: 9 | G25: 9
A26: 10 | G26: 10
A27: 11 | G27: 11
A28: 12 | G28: 12
A29: 13 | G29: 13
A30: 14 | G30: 14
A31: 15 | G31: 15
G32: If rules have been proposed, votes will be cast in this document. If the rule was proposed before noon, a vote will be held and a ruling will be made by the end of the same work day. Otherwise, a vote and ruling will be held the following work day. A unanimous vote is needed to pass.

Sheet Rankings
A1: Date | B1: Album Art | C1: Winner of the day | D1: Date | E1: Poster | F1: Average | G1: STDEV | H1: Peer Rank | I1: Song Title | J1: Artist | K1: Logan | L1: Parker | M1: Giacomo | N1: Rosey | O1: TTAC | P1: Weston | Q1: Flocco | R1: Jake | S1: Day Rank | T1: W Rank | U1: Winner | V1: Score | W1: Notes
A2: 45908 | C2: {=INDEX(Rankings!$E$2:$E$8, MATCH(1, (Rankings!$D$2:$D$8=A2)*(Rankings!$U$2:$U$8=TRUE()), 0))} -> Parker | D2: =A2 -> 45908 | E2: =$K$1 -> Logan | F2: =IFERROR(AVERAGE(Rankings!$K2:$R2), "TBD") -> 4.4285714 | G2: =IFERROR(_xlfn.STDEV.P(Rankings!$K2:$R2), "TBD") -> 2.1285235 | H2: =IFERROR(AVERAGE(Rankings!$L2:$R2), "TBD") -> 4.8333333 | I2: Earthquake | J2: Ferdous | K2: 2 | L2: 7 | M2: 7 | N2: 5 | O2: 5 | P2: 4 | R2: 1 | S2: =IF(SUM(Rankings!$K2:$R2)>0, COUNTIFS(Rankings!$D$2:$D$987, Rankings!$D2, Rankings!$F$2:$F$987, "<"&Rankings!$F2) + COUNTIFS(Rankings!$D$2:$D$987, Rankings!$D2, Rankings!$F$2:$F$987, Rankings!$F2, Rankings!$G$2:$G$987, "<"&Rankings!$G2)+1, "TBD") -> 5 | T2: 1 | U2: =Rankings!$S2=Rankings!$T2 -> FALSE
D3: =D2 -> 45908 | E3: =$L$1 -> Parker | F3: =IFERROR(AVERAGE(Rankings!$K3:$R3), "TBD") -> 2.1428571 | G3: =IFERROR(_xlfn.STDEV.P(Rankings!$K3:$R3), "TBD") -> 0.63887657 | H3: =IFERROR(AVERAGE(Rankings!$K3, Rankings!$M3:$R3), "TBD") -> 2.1666667 | I3: Send it Back | J3: Don West | K3: 3 | L3: 2 | M3: 2 | N3: 3 | O3: 2 | P3: 1 | R3: 2 | S3: =IF(SUM(Rankings!$K3:$R3)>0, COUNTIFS(Rankings!$D$2:$D$987, Rankings!$D3, Rankings!$F$2:$F$987, "<"&Rankings!$F3) + COUNTIFS(Rankings!$D$2:$D$987, Rankings!$D3, Rankings!$F$2:$F$987, Rankings!$F3, Rankings!$G$2:$G$987, "<"&Rankings!$G3)+1, "TBD") -> 1 | T3: 1 | U3: =Rankings!$S3=Rankings!$T3 -> TRUE
D4: =D2 -> 45908 | E4: =$M$1 -> Giacomo | F4: =IFERROR(AVERAGE(Rankings!$K4:$R4), "TBD") -> 4.1428571 | G4: =IFERROR(_xlfn.STDEV.P(Rankings!$K4:$R4), "TBD") -> 1.9587585 | H4: =IFERROR(AVERAGE(Rankings!$K4:$L4, Rankings!$N4:$R4), "TBD") -> 4.6666667 | I4: FOCUS | J4: _BY.ALEXANDER | K4: 4 | L4: 4 | M4: 1 | N4: 2 | O4: 7 | P4: 5 | R4: 6 | S4: =IF(SUM(Rankings!$K4:$R4)>0, COUNTIFS(Rankings!$D$2:$D$987, Rankings!$D4, Rankings!$F$2:$F$987, "<"&Rankings!$F4) + COUNTIFS(Rankings!$D$2:$D$987, Rankings!$D4, Rankings!$F$2:$F$987, Rankings!$F4, Rankings!$G$2:$G$987, "<"&Rankings!$G4)+1, "TBD") -> 3 | T4: 1 | U4: =Rankings!$S4=Rankings!$T4 -> FALSE
D5: =D2 -> 45908 | E5: =$N$1 -> Rosey | F5: =IFERROR(AVERAGE(Rankings!$K5:$R5), "TBD") -> 4.8571429 | G5: =IFERROR(_xlfn.STDEV.P(Rankings!$K5:$R5), "TBD") -> 1.8070158 | H5: =IFERROR(AVERAGE(Rankings!$K5:$M5, Rankings!$O5:$R5), "TBD") -> 5.5 | I5: Aloe Lite | J5: Good Kid | K5: 5 | L5: 6 | M5: 6 | N5: 1 | O5: 4 | P5: 7 | R5: 5 | S5: =IF(SUM(Rankings!$K5:$R5)>0, COUNTIFS(Rankings!$D$2:$D$987, Rankings!$D5, Rankings!$F$2:$F$987, "<"&Rankings!$F5) + COUNTIFS(Rankings!$D$2:$D$987, Rankings!$D5, Rankings!$F$2:$F$987, Rankings!$F5, Rankings!$G$2:$G$987, "<"&Rankings!$G5)+1, "TBD") -> 6 | T5: 1 | U5: =Rankings!$S5=Rankings!$T5 -> FALSE
D6: =D2 -> 45908 | E6: =$O$1 -> TTAC | F6: =IFERROR(AVERAGE(Rankings!$K6:$R6), "TBD") -> 5 | G6: =IFERROR(_xlfn.STDEV.P(Rankings!$K6:$R6), "TBD") -> 2.0701967 | H6: =IFERROR(AVERAGE(Rankings!$K6:$N6, Rankings!$P6:$R6), "TBD") -> 5.6666667 | I6: Buttercup | J6: Hippo Campus | K6: 7 | L6: 5 | M6: 3 | N6: 6 | O6: 1 | P6: 6 | R6: 7 | S6: =IF(SUM(Rankings!$K6:$R6)>0, COUNTIFS(Rankings!$D$2:$D$987, Rankings!$D6, Rankings!$F$2:$F$987, "<"&Rankings!$F6) + COUNTIFS(Rankings!$D$2:$D$987, Rankings!$D6, Rankings!$F$2:$F$987, Rankings!$F6, Rankings!$G$2:$G$987, "<"&Rankings!$G6)+1, "TBD") -> 7 | T6: 1 | U6: =Rankings!$S6=Rankings!$T6 -> FALSE
D7: =D3 -> 45908 | E7: =$P$1 -> Weston | F7: =IFERROR(AVERAGE(Rankings!$K7:$R7), "TBD") -> 3.1428571 | G7: =IFERROR(_xlfn.STDEV.P(Rankings!$K7:$R7), "TBD") -> 1.7261494 | H7: =IFERROR(AVERAGE(Rankings!$K7:$O7, Rankings!$R7), "TBD") -> 3.3333333 | I7: Snap my Finger | J7: Kaytranada | K7: 1 | L7: 1 | M7: 4 | N7: 4 | O7: 6 | P7: 2 | R7: 4 | S7: =IF(SUM(Rankings!$K7:$R7)>0, COUNTIFS(Rankings!$D$2:$D$987, Rankings!$D7, Rankings!$F$2:$F$987, "<"&Rankings!$F7) + COUNTIFS(Rankings!$D$2:$D$987, Rankings!$D7, Rankings!$F$2:$F$987, Rankings!$F7, Rankings!$G$2:$G$987, "<"&Rankings!$G7)+1, "TBD") -> 2 | T7: 1 | U7: =Rankings!$S7=Rankings!$T7 -> FALSE
D8: =D4 -> 45908 | E8: =$R$1 -> Jake | F8: =IFERROR(AVERAGE(Rankings!$K8:$R8), "TBD") -> 4.2857143 | G8: =IFERROR(_xlfn.STDEV.P(Rankings!$K8:$R8), "TBD") -> 1.5779087 | H8: =IFERROR(AVERAGE(Rankings!$K8:$P8), "TBD") -> 4.5 | I8: Help Is On It's Way | J8: Little River Band | K8: 6 | L8: 3 | M8: 5 | N8: 7 | O8: 3 | P8: 3 | R8: 3 | S8: =IF(SUM(Rankings!$K8:$R8)>0, COUNTIFS(Rankings!$D$2:$D$987, Rankings!$D8, Rankings!$F$2:$F$987, "<"&Rankings!$F8) + COUNTIFS(Rankings!$D$2:$D$987, Rankings!$D8, Rankings!$F$2:$F$987, Rankings!$F8, Rankings!$G$2:$G$987, "<"&Rankings!$G8)+1, "TBD") -> 4 | T8: 1 | U8: =Rankings!$S8=Rankings!$T8 -> FALSE
A9: 45910 | C9: {=INDEX(Rankings!$E$9:$E$15, MATCH(1, (Rankings!$D$9:$D$15=A9)*(Rankings!$U$9:$U$15=TRUE()), 0))} -> Giacomo | D9: =A9 -> 45910 | E9: =$K$1 -> Logan | F9: =IFERROR(AVERAGE(Rankings!$K9:$R9), "TBD") -> 4 | G9: =IFERROR(_xlfn.STDEV.P(Rankings!$K9:$R9), "TBD") -> 2.2038927 | H9: =IFERROR(AVERAGE(Rankings!$L9:$R9), "TBD") -> 4.3333333 | I9: Top 10 staTues tHat CriEd bloOd | J9: Bring Me The Horizon | K9: 2 | L9: 2 | M9: 7 | N9: 1 | O9: 6 | P9: 4 | R9: 6 | S9: =IF(SUM(Rankings!$K9:$R9)>0, COUNTIFS(Rankings!$D$2:$D$987, Rankings!$D9, Rankings!$F$2:$F$987, "<"&Rankings!$F9) + COUNTIFS(Rankings!$D$2:$D$987, Rankings!$D9, Rankings!$F$2:$F$987, Rankings!$F9, Rankings!$G$2:$G$987, "<"&Rankings!$G9)+1, "TBD") -> 4 | T9: 1 | U9: =Rankings!$S9=Rankings!$T9 -> FALSE
D10: =D9 -> 45910 | E10: =$L$1 -> Parker | F10: =IFERROR(AVERAGE(Rankings!$K10:$R10), "TBD") -> 2.7142857 | G10: =IFERROR(_xlfn.STDEV.P(Rankings!$K10:$R10), "TBD") -> 1.2777531 | H10: =IFERROR(AVERAGE(Rankings!$K10, Rankings!$M10:$R10), "TBD") -> 3 | I10: AURORA | J10: Mora, De La Rose | K10: 4 | L10: 1 | M10: 2 | N10: 4 | O10: 4 | P10: 3 | R10: 1 | S10: =IF(SUM(Rankings!$K10:$R10)>0, COUNTIFS(Rankings!$D$2:$D$987, Rankings!$D10, Rankings!$F$2:$F$987, "<"&Rankings!$F10) + COUNTIFS(Rankings!$D$2:$D$987, Rankings!$D10, Rankings!$F$2:$F$987, Rankings!$F10, Rankings!$G$2:$G$987, "<"&Rankings!$G10)+1, "TBD") -> 2 | T10: 1 | U10: =Rankings!$S10=Rankings!$T10 -> FALSE
D11: =D9 -> 45910 | E11: =$M$1 -> Giacomo | F11: =IFERROR(AVERAGE(Rankings!$K11:$R11), "TBD") -> 1.8571429 | G11: =IFERROR(_xlfn.STDEV.P(Rankings!$K11:$R11), "TBD") -> 0.83299313 | H11: =IFERROR(AVERAGE(Rankings!$K11:$L11, Rankings!$N11:$R11), "TBD") -> 2 | I11: SEE U DANCE | J11: Joey Valence & Brae, Rebecca Black | K11: 1 | L11: 3 | M11: 1 | N11: 3 | O11: 1 | P11: 2 | R11: 2 | S11: =IF(SUM(Rankings!$K11:$R11)>0, COUNTIFS(Rankings!$D$2:$D$987, Rankings!$D11, Rankings!$F$2:$F$987, "<"&Rankings!$F11) + COUNTIFS(Rankings!$D$2:$D$987, Rankings!$D11, Rankings!$F$2:$F$987, Rankings!$F11, Rankings!$G$2:$G$987, "<"&Rankings!$G11)+1, "TBD") -> 1 | T11: 1 | U11: =Rankings!$S11=Rankings!$T11 -> TRUE
D12: =D9 -> 45910 | E12: =$N$1 -> Rosey | F12: =IFERROR(AVERAGE(Rankings!$K12:$R12), "TBD") -> 5.1428571 | G12: =IFERROR(_xlfn.STDEV.P(Rankings!$K12:$R12), "TBD") -> 1.8070158 | H12: =IFERROR(AVERAGE(Rankings!$K12:$M12, Rankings!$O12:$R12), "TBD") -> 5.6666667 | I12: Tree | J12: Chance the Rapper, Smino, Lil Wayne | K12: 3 | L12: 6 | M12: 6 | N12: 2 | O12: 7 | P12: 7 | R12: 5 | S12: =IF(SUM(Rankings!$K12:$R12)>0, COUNTIFS(Rankings!$D$2:$D$987, Rankings!$D12, Rankings!$F$2:$F$987, "<"&Rankings!$F12) + COUNTIFS(Rankings!$D$2:$D$987, Rankings!$D12, Rankings!$F$2:$F$987, Rankings!$F12, Rankings!$G$2:$G$987, "<"&Rankings!$G12)+1, "TBD") -> 6 | T12: 1 | U12: =Rankings!$S12=Rankings!$T12 -> FALSE
D13: =D9 -> 45910 | E13: =$O$1 -> TTAC | F13: =IFERROR(AVERAGE(Rankings!$K13:$R13), "TBD") -> 6.2857143 | G13: =IFERROR(_xlfn.STDEV.P(Rankings!$K13:$R13), "TBD") -> 0.88063057 | H13: =IFERROR(AVERAGE(Rankings!$K13:$N13, Rankings!$P13:$R13), "TBD") -> 6.5 | I13: La Mamá de la Mamá | J13: El Alfa, Chael Produciendo, CJ | K13: 7 | L13: 7 | M13: 5 | N13: 7 | O13: 5 | P13: 6 | R13: 7 | S13: =IF(SUM(Rankings!$K13:$R13)>0, COUNTIFS(Rankings!$D$2:$D$987, Rankings!$D13, Rankings!$F$2:$F$987, "<"&Rankings!$F13) + COUNTIFS(Rankings!$D$2:$D$987, Rankings!$D13, Rankings!$F$2:$F$987, Rankings!$F13, Rankings!$G$2:$G$987, "<"&Rankings!$G13)+1, "TBD") -> 7 | T13: 1 | U13: =Rankings!$S13=Rankings!$T13 -> FALSE
D14: =D10 -> 45910 | E14: =$P$1 -> Weston | F14: =IFERROR(AVERAGE(Rankings!$K14:$R14), "TBD") -> 3.8571429 | G14: =IFERROR(_xlfn.STDEV.P(Rankings!$K14:$R14), "TBD") -> 1.7261494 | H14: =IFERROR(AVERAGE(Rankings!$K14:$O14, Rankings!$R14), "TBD") -> 4.3333333 | I14: The Artist in the Ambulance | J14: Thrice | K14: 6 | L14: 4 | M14: 4 | N14: 6 | O14: 2 | P14: 1 | R14: 4 | S14: =IF(SUM(Rankings!$K14:$R14)>0, COUNTIFS(Rankings!$D$2:$D$987, Rankings!$D14, Rankings!$F$2:$F$987, "<"&Rankings!$F14) + COUNTIFS(Rankings!$D$2:$D$987, Rankings!$D14, Rankings!$F$2:$F$987, Rankings!$F14, Rankings!$G$2:$G$987, "<"&Rankings!$G14)+1, "TBD") -> 3 | T14: 1 | U14: =Rankings!$S14=Rankings!$T14 -> FALSE
D15: =D11 -> 45910 | E15: =$R$1 -> Jake | F15: =IFERROR(AVERAGE(Rankings!$K15:$R15), "TBD") -> 4.1428571 | G15: =IFERROR(_xlfn.STDEV.P(Rankings!$K15:$R15), "TBD") -> 0.98974332 | H15: =IFERROR(AVERAGE(Rankings!$K15:$P15), "TBD") -> 4.3333333 | I15: Indigo | J15: Magnolian | K15: 5 | L15: 5 | M15: 3 | N15: 5 | O15: 3 | P15: 5 | R15: 3 | S15: =IF(SUM(Rankings!$K15:$R15)>0, COUNTIFS(Rankings!$D$2:$D$987, Rankings!$D15, Rankings!$F$2:$F$987, "<"&Rankings!$F15) + COUNTIFS(Rankings!$D$2:$D$987, Rankings!$D15, Rankings!$F$2:$F$987, Rankings!$F15, Rankings!$G$2:$G$987, "<"&Rankings!$G15)+1, "TBD") -> 5 | T15: 1 | U15: =Rankings!$S15=Rankings!$T15 -> FALSE
A16: 45912 | C16: {=INDEX(Rankings!$E$16:$E$22, MATCH(1, (Rankings!$D$16:$D$22=A16)*(Rankings!$U$16:$U$22=TRUE()), 0))} -> Rosey | D16: =A16 -> 45912 | E16: =$K$1 -> Logan | F16: =IFERROR(AVERAGE(Rankings!$K16:$R16), "TBD") -> 3.2857143 | G16: =IFERROR(_xlfn.STDEV.P(Rankings!$K16:$R16), "TBD") -> 1.905952 | H16: =IFERROR(AVERAGE(Rankings!$L16:$R16), "TBD") -> 3.6666667 | I16: Candle Flame | J16: Jungle, Erick the Architect | K16: 1 | L16: 4 | M16: 3 | N16: 3 | O16: 7 | P16: 4 | R16: 1 | S16: =IF(SUM(Rankings!$K16:$R16)>0, COUNTIFS(Rankings!$D$2:$D$987, Rankings!$D16, Rankings!$F$2:$F$987, "<"&Rankings!$F16) + COUNTIFS(Rankings!$D$2:$D$987, Rankings!$D16, Rankings!$F$2:$F$987, Rankings!$F16, Rankings!$G$2:$G$987, "<"&Rankings!$G16)+1, "TBD") -> 2 | T16: 1 | U16: =Rankings!$S16=Rankings!$T16 -> FALSE
D17: =D16 -> 45912 | E17: =$L$1 -> Parker | F17: =IFERROR(AVERAGE(Rankings!$K17:$R17), "TBD") -> 4 | G17: =IFERROR(_xlfn.STDEV.P(Rankings!$K17:$R17), "TBD") -> 1.9272482 | H17: =IFERROR(AVERAGE(Rankings!$K17, Rankings!$M17:$R17), "TBD") -> 4.5 | I17: Bros | J17: Wolf Alice | K17: 6 | L17: 1 | M17: 4 | N17: 6 | O17: 2 | P17: 3 | R17: 6 | S17: =IF(SUM(Rankings!$K17:$R17)>0, COUNTIFS(Rankings!$D$2:$D$987, Rankings!$D17, Rankings!$F$2:$F$987, "<"&Rankings!$F17) + COUNTIFS(Rankings!$D$2:$D$987, Rankings!$D17, Rankings!$F$2:$F$987, Rankings!$F17, Rankings!$G$2:$G$987, "<"&Rankings!$G17)+1, "TBD") -> 3 | T17: 1 | U17: =Rankings!$S17=Rankings!$T17 -> FALSE
D18: =D16 -> 45912 | E18: =$M$1 -> Giacomo | F18: =IFERROR(AVERAGE(Rankings!$K18:$R18), "TBD") -> 4.2857143 | G18: =IFERROR(_xlfn.STDEV.P(Rankings!$K18:$R18), "TBD") -> 1.484615 | H18: =IFERROR(AVERAGE(Rankings!$K18:$L18, Rankings!$N18:$R18), "TBD") -> 4.6666667 | I18: move it along | J18: Sasha Keable, Leon Thomas | K18: 5 | L18: 2 | M18: 2 | N18: 5 | O18: 6 | P18: 5 | R18: 5 | S18: =IF(SUM(Rankings!$K18:$R18)>0, COUNTIFS(Rankings!$D$2:$D$987, Rankings!$D18, Rankings!$F$2:$F$987, "<"&Rankings!$F18) + COUNTIFS(Rankings!$D$2:$D$987, Rankings!$D18, Rankings!$F$2:$F$987, Rankings!$F18, Rankings!$G$2:$G$987, "<"&Rankings!$G18)+1, "TBD") -> 4 | T18: 1 | U18: =Rankings!$S18=Rankings!$T18 -> FALSE
D19: =D16 -> 45912 | E19: =$N$1 -> Rosey | F19: =IFERROR(AVERAGE(Rankings!$K19:$R19), "TBD") -> 2.8571429 | G19: =IFERROR(_xlfn.STDEV.P(Rankings!$K19:$R19), "TBD") -> 1.8070158 | H19: =IFERROR(AVERAGE(Rankings!$K19:$M19, Rankings!$O19:$R19), "TBD") -> 3.1666667 | I19: Helena Beat | J19: Foster the People | K19: 2 | L19: 6 | M19: 5 | N19: 1 | O19: 3 | P19: 1 | R19: 2 | S19: =IF(SUM(Rankings!$K19:$R19)>0, COUNTIFS(Rankings!$D$2:$D$987, Rankings!$D19, Rankings!$F$2:$F$987, "<"&Rankings!$F19) + COUNTIFS(Rankings!$D$2:$D$987, Rankings!$D19, Rankings!$F$2:$F$987, Rankings!$F19, Rankings!$G$2:$G$987, "<"&Rankings!$G19)+1, "TBD") -> 1 | T19: 1 | U19: =Rankings!$S19=Rankings!$T19 -> TRUE
D20: =D16 -> 45912 | E20: =$O$1 -> TTAC | F20: =IFERROR(AVERAGE(Rankings!$K20:$R20), "TBD") -> 4.2857143 | G20: =IFERROR(_xlfn.STDEV.P(Rankings!$K20:$R20), "TBD") -> 2.5475078 | H20: =IFERROR(AVERAGE(Rankings!$K20:$N20, Rankings!$P20:$R20), "TBD") -> 4.8333333 | I20: PROM/KING | J20: Saba | K20: 4 | L20: 3 | M20: 1 | N20: 7 | O20: 1 | P20: 7 | R20: 7 | S20: =IF(SUM(Rankings!$K20:$R20)>0, COUNTIFS(Rankings!$D$2:$D$987, Rankings!$D20, Rankings!$F$2:$F$987, "<"&Rankings!$F20) + COUNTIFS(Rankings!$D$2:$D$987, Rankings!$D20, Rankings!$F$2:$F$987, Rankings!$F20, Rankings!$G$2:$G$987, "<"&Rankings!$G20)+1, "TBD") -> 5 | T20: 1 | U20: =Rankings!$S20=Rankings!$T20 -> FALSE
D21: =D17 -> 45912 | E21: =$P$1 -> Weston | F21: =IFERROR(AVERAGE(Rankings!$K21:$R21), "TBD") -> 4.7142857 | G21: =IFERROR(_xlfn.STDEV.P(Rankings!$K21:$R21), "TBD") -> 2.1189139 | H21: =IFERROR(AVERAGE(Rankings!$K21:$O21, Rankings!$R21), "TBD") -> 5.1666667 | I21: The Kiss of Venus (Dominic Fike) | J21: Paul McCartney, Dominic Fike | K21: 7 | L21: 7 | M21: 7 | N21: 2 | O21: 4 | P21: 2 | R21: 4 | S21: =IF(SUM(Rankings!$K21:$R21)>0, COUNTIFS(Rankings!$D$2:$D$987, Rankings!$D21, Rankings!$F$2:$F$987, "<"&Rankings!$F21) + COUNTIFS(Rankings!$D$2:$D$987, Rankings!$D21, Rankings!$F$2:$F$987, Rankings!$F21, Rankings!$G$2:$G$987, "<"&Rankings!$G21)+1, "TBD") -> 7 | T21: 1 | U21: =Rankings!$S21=Rankings!$T21 -> FALSE
D22: =D18 -> 45912 | E22: =$R$1 -> Jake | F22: =IFERROR(AVERAGE(Rankings!$K22:$R22), "TBD") -> 4.5714286 | G22: =IFERROR(_xlfn.STDEV.P(Rankings!$K22:$R22), "TBD") -> 1.1780302 | H22: =IFERROR(AVERAGE(Rankings!$K22:$P22), "TBD") -> 4.8333333 | I22: Pressure | J22: Billy Joel | K22: 3 | L22: 5 | M22: 6 | N22: 4 | O22: 5 | P22: 6 | R22: 3 | S22: =IF(SUM(Rankings!$K22:$R22)>0, COUNTIFS(Rankings!$D$2:$D$987, Rankings!$D22, Rankings!$F$2:$F$987, "<"&Rankings!$F22) + COUNTIFS(Rankings!$D$2:$D$987, Rankings!$D22, Rankings!$F$2:$F$987, Rankings!$F22, Rankings!$G$2:$G$987, "<"&Rankings!$G22)+1, "TBD") -> 6 | T22: 1 | U22: =Rankings!$S22=Rankings!$T22 -> FALSE
A23: 45915 | C23: {=INDEX(Rankings!$E23:$E29, MATCH(1, (Rankings!$D23:$D29=$A23)*(Rankings!$U23:$U29=TRUE()), 0))} -> Rosey | D23: =A23 -> 45915 | E23: =$K$1 -> Logan | F23: =IFERROR(AVERAGE(Rankings!$K23:$R23), "TBD") -> 3.5714286 | G23: =IFERROR(_xlfn.STDEV.P(Rankings!$K23:$R23), "TBD") -> 1.4982984 | H23: =IFERROR(AVERAGE(Rankings!$L23:$R23), "TBD") -> 4 | I23: Politix | J23: Balu Brigada | K23: 1 | L23: 3 | M23: 5 | N23: 6 | O23: 3 | P23: 3 | R23: 4 | S23: =IF(SUM(Rankings!$K23:$R23)>0, COUNTIFS(Rankings!$D$2:$D$987, Rankings!$D23, Rankings!$F$2:$F$987, "<"&Rankings!$F23) + COUNTIFS(Rankings!$D$2:$D$987, Rankings!$D23, Rankings!$F$2:$F$987, Rankings!$F23, Rankings!$G$2:$G$987, "<"&Rankings!$G23)+1, "TBD") -> 2 | T23: 1 | U23: =Rankings!$S23=Rankings!$T23 -> FALSE
D24: =D23 -> 45915 | E24: =$L$1 -> Parker | F24: =IFERROR(AVERAGE(Rankings!$K24:$R24), "TBD") -> 3.7142857 | G24: =IFERROR(_xlfn.STDEV.P(Rankings!$K24:$R24), "TBD") -> 1.7496355 | H24: =IFERROR(AVERAGE(Rankings!$K24, Rankings!$M24:$R24), "TBD") -> 4 | I24: BUBALU | J24: Feid,Rema | K24: 2 | L24: 2 | M24: 3 | N24: 2 | O24: 6 | P24: 6 | R24: 5 | S24: =IF(SUM(Rankings!$K24:$R24)>0, COUNTIFS(Rankings!$D$2:$D$987, Rankings!$D24, Rankings!$F$2:$F$987, "<"&Rankings!$F24) + COUNTIFS(Rankings!$D$2:$D$987, Rankings!$D24, Rankings!$F$2:$F$987, Rankings!$F24, Rankings!$G$2:$G$987, "<"&Rankings!$G24)+1, "TBD") -> 3 | T24: 1 | U24: =Rankings!$S24=Rankings!$T24 -> FALSE
D25: =D23 -> 45915 | E25: =$M$1 -> Giacomo | F25: =IFERROR(AVERAGE(Rankings!$K25:$R25), "TBD") -> 3.8571429 | G25: =IFERROR(_xlfn.STDEV.P(Rankings!$K25:$R25), "TBD") -> 1.5518258 | H25: =IFERROR(AVERAGE(Rankings!$K25:$L25, Rankings!$N25:$R25), "TBD") -> 4.1666667 | I25: mudbone | J25: Paris Texas | K25: 3 | L25: 4 | M25: 2 | N25: 3 | O25: 7 | P25: 5 | R25: 3 | S25: =IF(SUM(Rankings!$K25:$R25)>0, COUNTIFS(Rankings!$D$2:$D$987, Rankings!$D25, Rankings!$F$2:$F$987, "<"&Rankings!$F25) + COUNTIFS(Rankings!$D$2:$D$987, Rankings!$D25, Rankings!$F$2:$F$987, Rankings!$F25, Rankings!$G$2:$G$987, "<"&Rankings!$G25)+1, "TBD") -> 4 | T25: 1 | U25: =Rankings!$S25=Rankings!$T25 -> FALSE
D26: =D23 -> 45915 | E26: =$N$1 -> Rosey | F26: =IFERROR(AVERAGE(Rankings!$K26:$R26), "TBD") -> 2.4285714 | G26: =IFERROR(_xlfn.STDEV.P(Rankings!$K26:$R26), "TBD") -> 2.1285235 | H26: =IFERROR(AVERAGE(Rankings!$K26:$M26, Rankings!$O26:$R26), "TBD") -> 2.6666667 | I26: On My Own | J26: Jaden, Kid Cudi | K26: 4 | L26: 1 | M26: 7 | N26: 1 | O26: 2 | P26: 1 | R26: 1 | S26: =IF(SUM(Rankings!$K26:$R26)>0, COUNTIFS(Rankings!$D$2:$D$987, Rankings!$D26, Rankings!$F$2:$F$987, "<"&Rankings!$F26) + COUNTIFS(Rankings!$D$2:$D$987, Rankings!$D26, Rankings!$F$2:$F$987, Rankings!$F26, Rankings!$G$2:$G$987, "<"&Rankings!$G26)+1, "TBD") -> 1 | T26: 1 | U26: =Rankings!$S26=Rankings!$T26 -> TRUE
D27: =D23 -> 45915 | E27: =$O$1 -> TTAC | F27: =IFERROR(AVERAGE(Rankings!$K27:$R27), "TBD") -> 5.4285714 | G27: =IFERROR(_xlfn.STDEV.P(Rankings!$K27:$R27), "TBD") -> 2.060315 | H27: =IFERROR(AVERAGE(Rankings!$K27:$N27, Rankings!$P27:$R27), "TBD") -> 6.1666667 | I27: Brunette | J27: Tucker Wetmore | K27: 6 | L27: 7 | M27: 6 | N27: 4 | O27: 1 | P27: 7 | R27: 7 | S27: =IF(SUM(Rankings!$K27:$R27)>0, COUNTIFS(Rankings!$D$2:$D$987, Rankings!$D27, Rankings!$F$2:$F$987, "<"&Rankings!$F27) + COUNTIFS(Rankings!$D$2:$D$987, Rankings!$D27, Rankings!$F$2:$F$987, Rankings!$F27, Rankings!$G$2:$G$987, "<"&Rankings!$G27)+1, "TBD") -> 7 | T27: 1 | U27: =Rankings!$S27=Rankings!$T27 -> FALSE
D28: =D24 -> 45915 | E28: =$P$1 -> Weston | F28: =IFERROR(AVERAGE(Rankings!$K28:$R28), "TBD") -> 4.7142857 | G28: =IFERROR(_xlfn.STDEV.P(Rankings!$K28:$R28), "TBD") -> 2.2497165 | H28: =IFERROR(AVERAGE(Rankings!$K28:$O28, Rankings!$R28), "TBD") -> 5.1666667 | I28: Sedona | J28: Houndmouth | K28: 7 | L28: 6 | M28: 1 | N28: 7 | O28: 4 | P28: 2 | R28: 6 | S28: =IF(SUM(Rankings!$K28:$R28)>0, COUNTIFS(Rankings!$D$2:$D$987, Rankings!$D28, Rankings!$F$2:$F$987, "<"&Rankings!$F28) + COUNTIFS(Rankings!$D$2:$D$987, Rankings!$D28, Rankings!$F$2:$F$987, Rankings!$F28, Rankings!$G$2:$G$987, "<"&Rankings!$G28)+1, "TBD") -> 6 | T28: 1 | U28: =Rankings!$S28=Rankings!$T28 -> FALSE
D29: =D25 -> 45915 | E29: =$R$1 -> Jake | F29: =IFERROR(AVERAGE(Rankings!$K29:$R29), "TBD") -> 4.2857143 | G29: =IFERROR(_xlfn.STDEV.P(Rankings!$K29:$R29), "TBD") -> 1.0301575 | H29: =IFERROR(AVERAGE(Rankings!$K29:$P29), "TBD") -> 4.6666667 | I29: Heavy | J29: The Marias | K29: 5 | L29: 5 | M29: 4 | N29: 5 | O29: 5 | P29: 4 | R29: 2 | S29: =IF(SUM(Rankings!$K29:$R29)>0, COUNTIFS(Rankings!$D$2:$D$987, Rankings!$D29, Rankings!$F$2:$F$987, "<"&Rankings!$F29) + COUNTIFS(Rankings!$D$2:$D$987, Rankings!$D29, Rankings!$F$2:$F$987, Rankings!$F29, Rankings!$G$2:$G$987, "<"&Rankings!$G29)+1, "TBD") -> 5 | T29: 1 | U29: =Rankings!$S29=Rankings!$T29 -> FALSE
A30: 45917 | C30: {=INDEX(Rankings!$E30:$E36, MATCH(1, (Rankings!$D30:$D36=$A30)*(Rankings!$U30:$U36=TRUE()), 0))} -> Parker | D30: =A30 -> 45917 | E30: =$K$1 -> Logan | F30: =IFERROR(AVERAGE(Rankings!$K30:$R30), "TBD") -> 3.7142857 | G30: =IFERROR(_xlfn.STDEV.P(Rankings!$K30:$R30), "TBD") -> 1.905952 | H30: =IFERROR(AVERAGE(Rankings!$L30:$R30), "TBD") -> 4 | I30: FAMJAM4000 | J30: Jordan Ward | K30: 2 | L30: 5 | M30: 4 | N30: 6 | O30: 6 | P30: 1 | R30: 2 | S30: =IF(SUM(Rankings!$K30:$R30)>0, COUNTIFS(Rankings!$D$2:$D$987, Rankings!$D30, Rankings!$F$2:$F$987, "<"&Rankings!$F30) + COUNTIFS(Rankings!$D$2:$D$987, Rankings!$D30, Rankings!$F$2:$F$987, Rankings!$F30, Rankings!$G$2:$G$987, "<"&Rankings!$G30)+1, "TBD") -> 4 | T30: 1 | U30: =Rankings!$S30=Rankings!$T30 -> FALSE
D31: =D30 -> 45917 | E31: =$L$1 -> Parker | F31: =IFERROR(AVERAGE(Rankings!$K31:$R31), "TBD") -> 2.8571429 | G31: =IFERROR(_xlfn.STDEV.P(Rankings!$K31:$R31), "TBD") -> 1.6413036 | H31: =IFERROR(AVERAGE(Rankings!$K31, Rankings!$M31:$R31), "TBD") -> 3 | I31: Étouffée | J31: Vince Staples | K31: 4 | L31: 2 | M31: 1 | N31: 1 | O31: 3 | P31: 3 | R31: 6 | S31: =IF(SUM(Rankings!$K31:$R31)>0, COUNTIFS(Rankings!$D$2:$D$987, Rankings!$D31, Rankings!$F$2:$F$987, "<"&Rankings!$F31) + COUNTIFS(Rankings!$D$2:$D$987, Rankings!$D31, Rankings!$F$2:$F$987, Rankings!$F31, Rankings!$G$2:$G$987, "<"&Rankings!$G31)+1, "TBD") -> 1 | T31: 1 | U31: =Rankings!$S31=Rankings!$T31 -> TRUE
D32: =D30 -> 45917 | E32: =$M$1 -> Giacomo | F32: =IFERROR(AVERAGE(Rankings!$K32:$R32), "TBD") -> 4 | G32: =IFERROR(_xlfn.STDEV.P(Rankings!$K32:$R32), "TBD") -> 1.7728105 | H32: =IFERROR(AVERAGE(Rankings!$K32:$L32, Rankings!$N32:$R32), "TBD") -> 4.1666667 | I32: How Can I Love Her More? | J32: The Lemon Twigs | K32: 6 | L32: 4 | M32: 3 | N32: 2 | O32: 2 | P32: 7 | R32: 4 | S32: =IF(SUM(Rankings!$K32:$R32)>0, COUNTIFS(Rankings!$D$2:$D$987, Rankings!$D32, Rankings!$F$2:$F$987, "<"&Rankings!$F32) + COUNTIFS(Rankings!$D$2:$D$987, Rankings!$D32, Rankings!$F$2:$F$987, Rankings!$F32, Rankings!$G$2:$G$987, "<"&Rankings!$G32)+1, "TBD") -> 5 | T32: 1 | U32: =Rankings!$S32=Rankings!$T32 -> FALSE
D33: =D30 -> 45917 | E33: =$N$1 -> Rosey | F33: =IFERROR(AVERAGE(Rankings!$K33:$R33), "TBD") -> 5 | G33: =IFERROR(_xlfn.STDEV.P(Rankings!$K33:$R33), "TBD") -> 2.1380899 | H33: =IFERROR(AVERAGE(Rankings!$K33:$M33, Rankings!$O33:$R33), "TBD") -> 5.3333333 | I33: Paradox | J33: Survive Said the Prophet | K33: 1 | L33: 7 | M33: 7 | N33: 3 | O33: 5 | P33: 5 | R33: 7 | S33: =IF(SUM(Rankings!$K33:$R33)>0, COUNTIFS(Rankings!$D$2:$D$987, Rankings!$D33, Rankings!$F$2:$F$987, "<"&Rankings!$F33) + COUNTIFS(Rankings!$D$2:$D$987, Rankings!$D33, Rankings!$F$2:$F$987, Rankings!$F33, Rankings!$G$2:$G$987, "<"&Rankings!$G33)+1, "TBD") -> 6 | T33: 1 | U33: =Rankings!$S33=Rankings!$T33 -> FALSE
D34: =D30 -> 45917 | E34: =$O$1 -> TTAC | F34: =IFERROR(AVERAGE(Rankings!$K34:$R34), "TBD") -> 3.2857143 | G34: =IFERROR(_xlfn.STDEV.P(Rankings!$K34:$R34), "TBD") -> 1.5779087 | H34: =IFERROR(AVERAGE(Rankings!$K34:$N34, Rankings!$P34:$R34), "TBD") -> 3.6666667 | I34: Solsbury Hill | J34: Peter Gabriel | K34: 5 | L34: 3 | M34: 5 | N34: 4 | O34: 1 | P34: 4 | R34: 1 | S34: =IF(SUM(Rankings!$K34:$R34)>0, COUNTIFS(Rankings!$D$2:$D$987, Rankings!$D34, Rankings!$F$2:$F$987, "<"&Rankings!$F34) + COUNTIFS(Rankings!$D$2:$D$987, Rankings!$D34, Rankings!$F$2:$F$987, Rankings!$F34, Rankings!$G$2:$G$987, "<"&Rankings!$G34)+1, "TBD") -> 2 | T34: 1 | U34: =Rankings!$S34=Rankings!$T34 -> FALSE
D35: =D31 -> 45917 | E35: =$P$1 -> Weston | F35: =IFERROR(AVERAGE(Rankings!$K35:$R35), "TBD") -> 3.2857143 | G35: =IFERROR(_xlfn.STDEV.P(Rankings!$K35:$R35), "TBD") -> 1.905952 | H35: =IFERROR(AVERAGE(Rankings!$K35:$O35, Rankings!$R35), "TBD") -> 3.5 | I35: Drugs you should try it | J35: Travis Scott | K35: 3 | L35: 1 | M35: 2 | N35: 5 | O35: 7 | P35: 2 | R35: 3 | S35: =IF(SUM(Rankings!$K35:$R35)>0, COUNTIFS(Rankings!$D$2:$D$987, Rankings!$D35, Rankings!$F$2:$F$987, "<"&Rankings!$F35) + COUNTIFS(Rankings!$D$2:$D$987, Rankings!$D35, Rankings!$F$2:$F$987, Rankings!$F35, Rankings!$G$2:$G$987, "<"&Rankings!$G35)+1, "TBD") -> 3 | T35: 1 | U35: =Rankings!$S35=Rankings!$T35 -> FALSE
D36: =D32 -> 45917 | E36: =$R$1 -> Jake | F36: =IFERROR(AVERAGE(Rankings!$K36:$R36), "TBD") -> 5.8571429 | G36: =IFERROR(_xlfn.STDEV.P(Rankings!$K36:$R36), "TBD") -> 0.98974332 | H36: =IFERROR(AVERAGE(Rankings!$K36:$P36), "TBD") -> 6 | I36: Save Your Soul | J36: Kathleen Edwards | K36: 7 | L36: 6 | M36: 6 | N36: 7 | O36: 4 | P36: 6 | R36: 5 | S36: =IF(SUM(Rankings!$K36:$R36)>0, COUNTIFS(Rankings!$D$2:$D$987, Rankings!$D36, Rankings!$F$2:$F$987, "<"&Rankings!$F36) + COUNTIFS(Rankings!$D$2:$D$987, Rankings!$D36, Rankings!$F$2:$F$987, Rankings!$F36, Rankings!$G$2:$G$987, "<"&Rankings!$G36)+1, "TBD") -> 7 | T36: 1 | U36: =Rankings!$S36=Rankings!$T36 -> FALSE
A37: 45919 | C37: {=INDEX(Rankings!$E37:$E43, MATCH(1, (Rankings!$D37:$D43=$A37)*(Rankings!$U37:$U43=TRUE()), 0))} -> Rosey | D37: =A37 -> 45919 | E37: =$K$1 -> Logan | F37: =IFERROR(AVERAGE(Rankings!$K37:$R37), "TBD") -> 5.1428571 | G37: =IFERROR(_xlfn.STDEV.P(Rankings!$K37:$R37), "TBD") -> 1.8070158 | H37: =IFERROR(AVERAGE(Rankings!$L37:$R37), "TBD") -> 5.6666667 | I37: ROLLER COASTER | J37: legallyrxx | K37: 2 | L37: 4 | M37: 4 | N37: 5 | O37: 7 | P37: 7 | R37: 7 | S37: =IF(SUM(Rankings!$K37:$R37)>0, COUNTIFS(Rankings!$D$2:$D$987, Rankings!$D37, Rankings!$F$2:$F$987, "<"&Rankings!$F37) + COUNTIFS(Rankings!$D$2:$D$987, Rankings!$D37, Rankings!$F$2:$F$987, Rankings!$F37, Rankings!$G$2:$G$987, "<"&Rankings!$G37)+1, "TBD") -> 7 | T37: 1 | U37: =Rankings!$S37=Rankings!$T37 -> FALSE | W37: First sweep, racism test passed :)
D38: =D37 -> 45919 | E38: =$L$1 -> Parker | F38: =IFERROR(AVERAGE(Rankings!$K38:$R38), "TBD") -> 3.5714286 | G38: =IFERROR(_xlfn.STDEV.P(Rankings!$K38:$R38), "TBD") -> 1.2936264 | H38: =IFERROR(AVERAGE(Rankings!$K38, Rankings!$M38:$R38), "TBD") -> 3.8333333 | I38: Kitchen | J38: Kid Cudi | K38: 5 | L38: 2 | M38: 3 | N38: 2 | O38: 5 | P38: 5 | R38: 3 | S38: =IF(SUM(Rankings!$K38:$R38)>0, COUNTIFS(Rankings!$D$2:$D$987, Rankings!$D38, Rankings!$F$2:$F$987, "<"&Rankings!$F38) + COUNTIFS(Rankings!$D$2:$D$987, Rankings!$D38, Rankings!$F$2:$F$987, Rankings!$F38, Rankings!$G$2:$G$987, "<"&Rankings!$G38)+1, "TBD") -> 2 | T38: 1 | U38: =Rankings!$S38=Rankings!$T38 -> FALSE
D39: =D37 -> 45919 | E39: =$M$1 -> Giacomo | F39: =IFERROR(AVERAGE(Rankings!$K39:$R39), "TBD") -> 3.8571429 | G39: =IFERROR(_xlfn.STDEV.P(Rankings!$K39:$R39), "TBD") -> 1.3552619 | H39: =IFERROR(AVERAGE(Rankings!$K39:$L39, Rankings!$N39:$R39), "TBD") -> 4.1666667 | I39: Buenos tiempos | J39: Dillom | K39: 6 | L39: 5 | M39: 2 | N39: 4 | O39: 4 | P39: 4 | R39: 2 | S39: =IF(SUM(Rankings!$K39:$R39)>0, COUNTIFS(Rankings!$D$2:$D$987, Rankings!$D39, Rankings!$F$2:$F$987, "<"&Rankings!$F39) + COUNTIFS(Rankings!$D$2:$D$987, Rankings!$D39, Rankings!$F$2:$F$987, Rankings!$F39, Rankings!$G$2:$G$987, "<"&Rankings!$G39)+1, "TBD") -> 3 | T39: 1 | U39: =Rankings!$S39=Rankings!$T39 -> FALSE
D40: =D37 -> 45919 | E40: =$N$1 -> Rosey | F40: =IFERROR(AVERAGE(Rankings!$K40:$R40), "TBD") -> 1 | G40: =IFERROR(_xlfn.STDEV.P(Rankings!$K40:$R40), "TBD") -> 0 | H40: =IFERROR(AVERAGE(Rankings!$K40:$M40, Rankings!$O40:$R40), "TBD") -> 1 | I40: TEMPTATION | J40: Joey Bada$$ | K40: 1 | L40: 1 | M40: 1 | N40: 1 | O40: 1 | P40: 1 | R40: 1 | S40: =IF(SUM(Rankings!$K40:$R40)>0, COUNTIFS(Rankings!$D$2:$D$987, Rankings!$D40, Rankings!$F$2:$F$987, "<"&Rankings!$F40) + COUNTIFS(Rankings!$D$2:$D$987, Rankings!$D40, Rankings!$F$2:$F$987, Rankings!$F40, Rankings!$G$2:$G$987, "<"&Rankings!$G40)+1, "TBD") -> 1 | T40: 1 | U40: =Rankings!$S40=Rankings!$T40 -> TRUE
D41: =D37 -> 45919 | E41: =$O$1 -> TTAC | F41: =IFERROR(AVERAGE(Rankings!$K41:$R41), "TBD") -> 4.7142857 | G41: =IFERROR(_xlfn.STDEV.P(Rankings!$K41:$R41), "TBD") -> 2.1189139 | H41: =IFERROR(AVERAGE(Rankings!$K41:$N41, Rankings!$P41:$R41), "TBD") -> 5.1666667 | I41: Lazy Afternoon | J41: Rebelution | K41: 4 | L41: 7 | M41: 7 | N41: 7 | O41: 2 | P41: 2 | R41: 4 | S41: =IF(SUM(Rankings!$K41:$R41)>0, COUNTIFS(Rankings!$D$2:$D$987, Rankings!$D41, Rankings!$F$2:$F$987, "<"&Rankings!$F41) + COUNTIFS(Rankings!$D$2:$D$987, Rankings!$D41, Rankings!$F$2:$F$987, Rankings!$F41, Rankings!$G$2:$G$987, "<"&Rankings!$G41)+1, "TBD") -> 5 | T41: 1 | U41: =Rankings!$S41=Rankings!$T41 -> FALSE
D42: =D38 -> 45919 | E42: =$P$1 -> Weston | F42: =IFERROR(AVERAGE(Rankings!$K42:$R42), "TBD") -> 5.1428571 | G42: =IFERROR(_xlfn.STDEV.P(Rankings!$K42:$R42), "TBD") -> 1.3552619 | H42: =IFERROR(AVERAGE(Rankings!$K42:$O42, Rankings!$R42), "TBD") -> 5.5 | I42: Cute without the E | J42: Taking Back Sunday | K42: 3 | L42: 6 | M42: 6 | N42: 6 | O42: 6 | P42: 3 | R42: 6 | S42: =IF(SUM(Rankings!$K42:$R42)>0, COUNTIFS(Rankings!$D$2:$D$987, Rankings!$D42, Rankings!$F$2:$F$987, "<"&Rankings!$F42) + COUNTIFS(Rankings!$D$2:$D$987, Rankings!$D42, Rankings!$F$2:$F$987, Rankings!$F42, Rankings!$G$2:$G$987, "<"&Rankings!$G42)+1, "TBD") -> 6 | T42: 1 | U42: =Rankings!$S42=Rankings!$T42 -> FALSE
D43: =D39 -> 45919 | E43: =$R$1 -> Jake | F43: =IFERROR(AVERAGE(Rankings!$K43:$R43), "TBD") -> 4.5714286 | G43: =IFERROR(_xlfn.STDEV.P(Rankings!$K43:$R43), "TBD") -> 1.4982984 | H43: =IFERROR(AVERAGE(Rankings!$K43:$P43), "TBD") -> 4.5 | I43: Joy | J43: Apollo 100 | K43: 7 | L43: 3 | M43: 5 | N43: 3 | O43: 3 | P43: 6 | R43: 5 | S43: =IF(SUM(Rankings!$K43:$R43)>0, COUNTIFS(Rankings!$D$2:$D$987, Rankings!$D43, Rankings!$F$2:$F$987, "<"&Rankings!$F43) + COUNTIFS(Rankings!$D$2:$D$987, Rankings!$D43, Rankings!$F$2:$F$987, Rankings!$F43, Rankings!$G$2:$G$987, "<"&Rankings!$G43)+1, "TBD") -> 4 | T43: 1 | U43: =Rankings!$S43=Rankings!$T43 -> FALSE
A44: 45922 | C44: {=INDEX(Rankings!$E44:$E50, MATCH(1, (Rankings!$D44:$D50=$A44)*(Rankings!$U44:$U50=TRUE()), 0))} -> Parker | D44: =A44 -> 45922 | E44: =$K$1 -> Logan | F44: =IFERROR(AVERAGE(Rankings!$K44:$R44), "TBD") -> 3.2857143 | G44: =IFERROR(_xlfn.STDEV.P(Rankings!$K44:$R44), "TBD") -> 1.3850514 | H44: =IFERROR(AVERAGE(Rankings!$L44:$R44), "TBD") -> 3.3333333 | I44: robbery | J44: SOLOMON | K44: 3 | L44: 4 | M44: 5 | N44: 1 | O44: 2 | P44: 3 | R44: 5 | S44: =IF(SUM(Rankings!$K44:$R44)>0, COUNTIFS(Rankings!$D$2:$D$987, Rankings!$D44, Rankings!$F$2:$F$987, "<"&Rankings!$F44) + COUNTIFS(Rankings!$D$2:$D$987, Rankings!$D44, Rankings!$F$2:$F$987, Rankings!$F44, Rankings!$G$2:$G$987, "<"&Rankings!$G44)+1, "TBD") -> 3 | T44: 1 | U44: =Rankings!$S44=Rankings!$T44 -> FALSE
D45: =D44 -> 45922 | E45: =$L$1 -> Parker | F45: =IFERROR(AVERAGE(Rankings!$K45:$R45), "TBD") -> 2.7142857 | G45: =IFERROR(_xlfn.STDEV.P(Rankings!$K45:$R45), "TBD") -> 1.1605769 | H45: =IFERROR(AVERAGE(Rankings!$K45, Rankings!$M45:$R45), "TBD") -> 2.6666667 | I45: Image | J45: Magdalena Bay | K45: 2 | L45: 3 | M45: 3 | N45: 2 | O45: 5 | P45: 1 | R45: 3 | S45: =IF(SUM(Rankings!$K45:$R45)>0, COUNTIFS(Rankings!$D$2:$D$987, Rankings!$D45, Rankings!$F$2:$F$987, "<"&Rankings!$F45) + COUNTIFS(Rankings!$D$2:$D$987, Rankings!$D45, Rankings!$F$2:$F$987, Rankings!$F45, Rankings!$G$2:$G$987, "<"&Rankings!$G45)+1, "TBD") -> 1 | T45: 1 | U45: =Rankings!$S45=Rankings!$T45 -> TRUE
D46: =D44 -> 45922 | E46: =$M$1 -> Giacomo | F46: =IFERROR(AVERAGE(Rankings!$K46:$R46), "TBD") -> 4.2857143 | G46: =IFERROR(_xlfn.STDEV.P(Rankings!$K46:$R46), "TBD") -> 1.9794866 | H46: =IFERROR(AVERAGE(Rankings!$K46:$L46, Rankings!$N46:$R46), "TBD") -> 4.6666667 | I46: father | J46: Jim Legxacy | K46: 1 | L46: 5 | M46: 2 | N46: 5 | O46: 4 | P46: 7 | R46: 6 | S46: =IF(SUM(Rankings!$K46:$R46)>0, COUNTIFS(Rankings!$D$2:$D$987, Rankings!$D46, Rankings!$F$2:$F$987, "<"&Rankings!$F46) + COUNTIFS(Rankings!$D$2:$D$987, Rankings!$D46, Rankings!$F$2:$F$987, Rankings!$F46, Rankings!$G$2:$G$987, "<"&Rankings!$G46)+1, "TBD") -> 5 | T46: 1 | U46: =Rankings!$S46=Rankings!$T46 -> FALSE
D47: =D44 -> 45922 | E47: =$N$1 -> Rosey | F47: =IFERROR(AVERAGE(Rankings!$K47:$R47), "TBD") -> 3.8571429 | G47: =IFERROR(_xlfn.STDEV.P(Rankings!$K47:$R47), "TBD") -> 2.0995626 | H47: =IFERROR(AVERAGE(Rankings!$K47:$M47, Rankings!$O47:$R47), "TBD") -> 3.8333333 | I47: Oh Girl | J47: The Chi-Lites | K47: 7 | L47: 1 | M47: 1 | N47: 4 | O47: 6 | P47: 4 | R47: 4 | S47: =IF(SUM(Rankings!$K47:$R47)>0, COUNTIFS(Rankings!$D$2:$D$987, Rankings!$D47, Rankings!$F$2:$F$987, "<"&Rankings!$F47) + COUNTIFS(Rankings!$D$2:$D$987, Rankings!$D47, Rankings!$F$2:$F$987, Rankings!$F47, Rankings!$G$2:$G$987, "<"&Rankings!$G47)+1, "TBD") -> 4 | T47: 1 | U47: =Rankings!$S47=Rankings!$T47 -> FALSE
D48: =D44 -> 45922 | E48: =$O$1 -> TTAC | F48: =IFERROR(AVERAGE(Rankings!$K48:$R48), "TBD") -> 5.8571429 | G48: =IFERROR(_xlfn.STDEV.P(Rankings!$K48:$R48), "TBD") -> 2.0303815 | H48: =IFERROR(AVERAGE(Rankings!$K48:$N48, Rankings!$P48:$R48), "TBD") -> 6.6666667 | I48: Sh-Boom | J48: The Chords | K48: 6 | L48: 7 | M48: 7 | N48: 7 | O48: 1 | P48: 6 | R48: 7 | S48: =IF(SUM(Rankings!$K48:$R48)>0, COUNTIFS(Rankings!$D$2:$D$987, Rankings!$D48, Rankings!$F$2:$F$987, "<"&Rankings!$F48) + COUNTIFS(Rankings!$D$2:$D$987, Rankings!$D48, Rankings!$F$2:$F$987, Rankings!$F48, Rankings!$G$2:$G$987, "<"&Rankings!$G48)+1, "TBD") -> 7 | T48: 1 | U48: =Rankings!$S48=Rankings!$T48 -> FALSE
D49: =D45 -> 45922 | E49: =$P$1 -> Weston | F49: =IFERROR(AVERAGE(Rankings!$K49:$R49), "TBD") -> 3.1428571 | G49: =IFERROR(_xlfn.STDEV.P(Rankings!$K49:$R49), "TBD") -> 1.3552619 | H49: =IFERROR(AVERAGE(Rankings!$K49:$O49, Rankings!$R49), "TBD") -> 3.3333333 | I49: Guilty Conscience | J49: 070 Shake | K49: 4 | L49: 2 | M49: 6 | N49: 3 | O49: 3 | P49: 2 | R49: 2 | S49: =IF(SUM(Rankings!$K49:$R49)>0, COUNTIFS(Rankings!$D$2:$D$987, Rankings!$D49, Rankings!$F$2:$F$987, "<"&Rankings!$F49) + COUNTIFS(Rankings!$D$2:$D$987, Rankings!$D49, Rankings!$F$2:$F$987, Rankings!$F49, Rankings!$G$2:$G$987, "<"&Rankings!$G49)+1, "TBD") -> 2 | T49: 1 | U49: =Rankings!$S49=Rankings!$T49 -> FALSE
D50: =D46 -> 45922 | E50: =$R$1 -> Jake | F50: =IFERROR(AVERAGE(Rankings!$K50:$R50), "TBD") -> 4.8571429 | G50: =IFERROR(_xlfn.STDEV.P(Rankings!$K50:$R50), "TBD") -> 1.8070158 | H50: =IFERROR(AVERAGE(Rankings!$K50:$P50), "TBD") -> 5.5 | I50: Dirty Laundry | J50: Don Henley | K50: 5 | L50: 6 | M50: 4 | N50: 6 | O50: 7 | P50: 5 | R50: 1 | S50: =IF(SUM(Rankings!$K50:$R50)>0, COUNTIFS(Rankings!$D$2:$D$987, Rankings!$D50, Rankings!$F$2:$F$987, "<"&Rankings!$F50) + COUNTIFS(Rankings!$D$2:$D$987, Rankings!$D50, Rankings!$F$2:$F$987, Rankings!$F50, Rankings!$G$2:$G$987, "<"&Rankings!$G50)+1, "TBD") -> 6 | T50: 1 | U50: =Rankings!$S50=Rankings!$T50 -> FALSE
A51: 45924 | C51: {=INDEX(Rankings!$E51:$E57, MATCH(1, (Rankings!$D51:$D57=$A51)*(Rankings!$U51:$U57=TRUE()), 0))} -> Giacomo | D51: =A51 -> 45924 | E51: =$K$1 -> Logan | F51: =IFERROR(AVERAGE(Rankings!$K51:$R51), "TBD") -> 3.5714286 | G51: =IFERROR(_xlfn.STDEV.P(Rankings!$K51:$R51), "TBD") -> 2.4411439 | H51: =IFERROR(AVERAGE(Rankings!$L51:$R51), "TBD") -> 3.8333333 | I51: cloud 11 | J51: thủy | K51: 2 | L51: 2 | M51: 6 | N51: 6 | O51: 1 | P51: 1 | R51: 7 | S51: =IF(SUM(Rankings!$K51:$R51)>0, COUNTIFS(Rankings!$D$2:$D$987, Rankings!$D51, Rankings!$F$2:$F$987, "<"&Rankings!$F51) + COUNTIFS(Rankings!$D$2:$D$987, Rankings!$D51, Rankings!$F$2:$F$987, Rankings!$F51, Rankings!$G$2:$G$987, "<"&Rankings!$G51)+1, "TBD") -> 3 | T51: 1 | U51: =Rankings!$S51=Rankings!$T51 -> FALSE
D52: =D51 -> 45924 | E52: =$L$1 -> Parker | F52: =IFERROR(AVERAGE(Rankings!$K52:$R52), "TBD") -> 4.1428571 | G52: =IFERROR(_xlfn.STDEV.P(Rankings!$K52:$R52), "TBD") -> 1.9587585 | H52: =IFERROR(AVERAGE(Rankings!$K52, Rankings!$M52:$R52), "TBD") -> 4.6666667 | I52: TULUM | J52: Peso Pluma, Grupo Frontera | K52: 5 | L52: 1 | M52: 4 | N52: 2 | O52: 7 | P52: 6 | R52: 4 | S52: =IF(SUM(Rankings!$K52:$R52)>0, COUNTIFS(Rankings!$D$2:$D$987, Rankings!$D52, Rankings!$F$2:$F$987, "<"&Rankings!$F52) + COUNTIFS(Rankings!$D$2:$D$987, Rankings!$D52, Rankings!$F$2:$F$987, Rankings!$F52, Rankings!$G$2:$G$987, "<"&Rankings!$G52)+1, "TBD") -> 5 | T52: 1 | U52: =Rankings!$S52=Rankings!$T52 -> FALSE
D53: =D51 -> 45924 | E53: =$M$1 -> Giacomo | F53: =IFERROR(AVERAGE(Rankings!$K53:$R53), "TBD") -> 3.2857143 | G53: =IFERROR(_xlfn.STDEV.P(Rankings!$K53:$R53), "TBD") -> 1.7496355 | H53: =IFERROR(AVERAGE(Rankings!$K53:$L53, Rankings!$N53:$R53), "TBD") -> 3.6666667 | I53: No Problems | J53: Ginger Root | K53: 1 | L53: 5 | M53: 1 | N53: 5 | O53: 2 | P53: 4 | R53: 5 | S53: =IF(SUM(Rankings!$K53:$R53)>0, COUNTIFS(Rankings!$D$2:$D$987, Rankings!$D53, Rankings!$F$2:$F$987, "<"&Rankings!$F53) + COUNTIFS(Rankings!$D$2:$D$987, Rankings!$D53, Rankings!$F$2:$F$987, Rankings!$F53, Rankings!$G$2:$G$987, "<"&Rankings!$G53)+1, "TBD") -> 1 | T53: 1 | U53: =Rankings!$S53=Rankings!$T53 -> TRUE
D54: =D51 -> 45924 | E54: =$N$1 -> Rosey | F54: =IFERROR(AVERAGE(Rankings!$K54:$R54), "TBD") -> 3.4285714 | G54: =IFERROR(_xlfn.STDEV.P(Rankings!$K54:$R54), "TBD") -> 2.1285235 | H54: =IFERROR(AVERAGE(Rankings!$K54:$M54, Rankings!$O54:$R54), "TBD") -> 3.8333333 | I54: Feet Don't Fail Me Now | J54: Joy Crookes | K54: 7 | L54: 3 | M54: 2 | N54: 1 | O54: 5 | P54: 5 | R54: 1 | S54: =IF(SUM(Rankings!$K54:$R54)>0, COUNTIFS(Rankings!$D$2:$D$987, Rankings!$D54, Rankings!$F$2:$F$987, "<"&Rankings!$F54) + COUNTIFS(Rankings!$D$2:$D$987, Rankings!$D54, Rankings!$F$2:$F$987, Rankings!$F54, Rankings!$G$2:$G$987, "<"&Rankings!$G54)+1, "TBD") -> 2 | T54: 1 | U54: =Rankings!$S54=Rankings!$T54 -> FALSE
D55: =D51 -> 45924 | E55: =$O$1 -> TTAC | F55: =IFERROR(AVERAGE(Rankings!$K55:$R55), "TBD") -> 5.2857143 | G55: =IFERROR(_xlfn.STDEV.P(Rankings!$K55:$R55), "TBD") -> 1.9794866 | H55: =IFERROR(AVERAGE(Rankings!$K55:$N55, Rankings!$P55:$R55), "TBD") -> 5.6666667 | I55: RATATATA | J55: BABYMETAL, Electric Callboy | K55: 3 | L55: 7 | M55: 7 | N55: 7 | O55: 3 | P55: 7 | R55: 3 | S55: =IF(SUM(Rankings!$K55:$R55)>0, COUNTIFS(Rankings!$D$2:$D$987, Rankings!$D55, Rankings!$F$2:$F$987, "<"&Rankings!$F55) + COUNTIFS(Rankings!$D$2:$D$987, Rankings!$D55, Rankings!$F$2:$F$987, Rankings!$F55, Rankings!$G$2:$G$987, "<"&Rankings!$G55)+1, "TBD") -> 7 | T55: 1 | U55: =Rankings!$S55=Rankings!$T55 -> FALSE
D56: =D52 -> 45924 | E56: =$P$1 -> Weston | F56: =IFERROR(AVERAGE(Rankings!$K56:$R56), "TBD") -> 4.2857143 | G56: =IFERROR(_xlfn.STDEV.P(Rankings!$K56:$R56), "TBD") -> 1.3850514 | H56: =IFERROR(AVERAGE(Rankings!$K56:$O56, Rankings!$R56), "TBD") -> 4.6666667 | I56: Cold Cold Cold | J56: Cage The Elephant | K56: 4 | L56: 4 | M56: 5 | N56: 3 | O56: 6 | P56: 2 | R56: 6 | S56: =IF(SUM(Rankings!$K56:$R56)>0, COUNTIFS(Rankings!$D$2:$D$987, Rankings!$D56, Rankings!$F$2:$F$987, "<"&Rankings!$F56) + COUNTIFS(Rankings!$D$2:$D$987, Rankings!$D56, Rankings!$F$2:$F$987, Rankings!$F56, Rankings!$G$2:$G$987, "<"&Rankings!$G56)+1, "TBD") -> 6 | T56: 1 | U56: =Rankings!$S56=Rankings!$T56 -> FALSE
D57: =D53 -> 45924 | E57: =$R$1 -> Jake | F57: =IFERROR(AVERAGE(Rankings!$K57:$R57), "TBD") -> 4 | G57: =IFERROR(_xlfn.STDEV.P(Rankings!$K57:$R57), "TBD") -> 1.4142136 | H57: =IFERROR(AVERAGE(Rankings!$K57:$P57), "TBD") -> 4.3333333 | I57: Don't Let It Bring You Down | J57: Neil Young | K57: 6 | L57: 6 | M57: 3 | N57: 4 | O57: 4 | P57: 3 | R57: 2 | S57: =IF(SUM(Rankings!$K57:$R57)>0, COUNTIFS(Rankings!$D$2:$D$987, Rankings!$D57, Rankings!$F$2:$F$987, "<"&Rankings!$F57) + COUNTIFS(Rankings!$D$2:$D$987, Rankings!$D57, Rankings!$F$2:$F$987, Rankings!$F57, Rankings!$G$2:$G$987, "<"&Rankings!$G57)+1, "TBD") -> 4 | T57: 1 | U57: =Rankings!$S57=Rankings!$T57 -> FALSE
A58: 45926 | C58: {=INDEX(Rankings!$E58:$E64, MATCH(1, (Rankings!$D58:$D64=$A58)*(Rankings!$U58:$U64=TRUE()), 0))} -> Weston | D58: =A58 -> 45926 | E58: =$K$1 -> Logan | F58: =IFERROR(AVERAGE(Rankings!$K58:$R58), "TBD") -> 4.7142857 | G58: =IFERROR(_xlfn.STDEV.P(Rankings!$K58:$R58), "TBD") -> 2.2497165 | H58: =IFERROR(AVERAGE(Rankings!$L58:$R58), "TBD") -> 5 | I58: GUMMY | J58: BROCKHAMPTON | K58: 3 | L58: 7 | M58: 1 | N58: 7 | O58: 7 | P58: 5 | R58: 3 | S58: =IF(SUM(Rankings!$K58:$R58)>0, COUNTIFS(Rankings!$D$2:$D$987, Rankings!$D58, Rankings!$F$2:$F$987, "<"&Rankings!$F58) + COUNTIFS(Rankings!$D$2:$D$987, Rankings!$D58, Rankings!$F$2:$F$987, Rankings!$F58, Rankings!$G$2:$G$987, "<"&Rankings!$G58)+1, "TBD") -> 6 | T58: 1 | U58: =Rankings!$S58=Rankings!$T58 -> FALSE
D59: =D58 -> 45926 | E59: =$L$1 -> Parker | F59: =IFERROR(AVERAGE(Rankings!$K59:$R59), "TBD") -> 4.7142857 | G59: =IFERROR(_xlfn.STDEV.P(Rankings!$K59:$R59), "TBD") -> 0.88063057 | H59: =IFERROR(AVERAGE(Rankings!$K59, Rankings!$M59:$R59), "TBD") -> 4.8333333 | I59: Ninja | J59: Young Thug | K59: 6 | L59: 4 | M59: 5 | N59: 6 | O59: 4 | P59: 4 | R59: 4 | S59: =IF(SUM(Rankings!$K59:$R59)>0, COUNTIFS(Rankings!$D$2:$D$987, Rankings!$D59, Rankings!$F$2:$F$987, "<"&Rankings!$F59) + COUNTIFS(Rankings!$D$2:$D$987, Rankings!$D59, Rankings!$F$2:$F$987, Rankings!$F59, Rankings!$G$2:$G$987, "<"&Rankings!$G59)+1, "TBD") -> 5 | T59: 1 | U59: =Rankings!$S59=Rankings!$T59 -> FALSE
D60: =D58 -> 45926 | E60: =$M$1 -> Giacomo | F60: =IFERROR(AVERAGE(Rankings!$K60:$R60), "TBD") -> 4.8571429 | G60: =IFERROR(_xlfn.STDEV.P(Rankings!$K60:$R60), "TBD") -> 1.6413036 | H60: =IFERROR(AVERAGE(Rankings!$K60:$L60, Rankings!$N60:$R60), "TBD") -> 5.3333333 | I60: BLOW IT DOWN! | J60: JELEEL! | K60: 5 | L60: 5 | M60: 2 | N60: 3 | O60: 6 | P60: 7 | R60: 6 | S60: =IF(SUM(Rankings!$K60:$R60)>0, COUNTIFS(Rankings!$D$2:$D$987, Rankings!$D60, Rankings!$F$2:$F$987, "<"&Rankings!$F60) + COUNTIFS(Rankings!$D$2:$D$987, Rankings!$D60, Rankings!$F$2:$F$987, Rankings!$F60, Rankings!$G$2:$G$987, "<"&Rankings!$G60)+1, "TBD") -> 7 | T60: 1 | U60: =Rankings!$S60=Rankings!$T60 -> FALSE
D61: =D58 -> 45926 | E61: =$N$1 -> Rosey | F61: =IFERROR(AVERAGE(Rankings!$K61:$R61), "TBD") -> 3.2857143 | G61: =IFERROR(_xlfn.STDEV.P(Rankings!$K61:$R61), "TBD") -> 2.2497165 | H61: =IFERROR(AVERAGE(Rankings!$K61:$M61, Rankings!$O61:$R61), "TBD") -> 3.6666667 | I61: Baby I'm Yours | J61: Breakbot, Irfane | K61: 2 | L61: 6 | M61: 4 | N61: 1 | O61: 2 | P61: 1 | R61: 7 | S61: =IF(SUM(Rankings!$K61:$R61)>0, COUNTIFS(Rankings!$D$2:$D$987, Rankings!$D61, Rankings!$F$2:$F$987, "<"&Rankings!$F61) + COUNTIFS(Rankings!$D$2:$D$987, Rankings!$D61, Rankings!$F$2:$F$987, Rankings!$F61, Rankings!$G$2:$G$987, "<"&Rankings!$G61)+1, "TBD") -> 2 | T61: 1 | U61: =Rankings!$S61=Rankings!$T61 -> FALSE
D62: =D58 -> 45926 | E62: =$O$1 -> TTAC | F62: =IFERROR(AVERAGE(Rankings!$K62:$R62), "TBD") -> 4.2857143 | G62: =IFERROR(_xlfn.STDEV.P(Rankings!$K62:$R62), "TBD") -> 1.6659863 | H62: =IFERROR(AVERAGE(Rankings!$K62:$N62, Rankings!$P62:$R62), "TBD") -> 4.5 | I62: Video Killed The Radio Star | J62: The Buggles | K62: 4 | L62: 3 | M62: 7 | N62: 2 | O62: 3 | P62: 6 | R62: 5 | S62: =IF(SUM(Rankings!$K62:$R62)>0, COUNTIFS(Rankings!$D$2:$D$987, Rankings!$D62, Rankings!$F$2:$F$987, "<"&Rankings!$F62) + COUNTIFS(Rankings!$D$2:$D$987, Rankings!$D62, Rankings!$F$2:$F$987, Rankings!$F62, Rankings!$G$2:$G$987, "<"&Rankings!$G62)+1, "TBD") -> 4 | T62: 1 | U62: =Rankings!$S62=Rankings!$T62 -> FALSE
D63: =D59 -> 45926 | E63: =$P$1 -> Weston | F63: =IFERROR(AVERAGE(Rankings!$K63:$R63), "TBD") -> 2.5714286 | G63: =IFERROR(_xlfn.STDEV.P(Rankings!$K63:$R63), "TBD") -> 1.9166297 | H63: =IFERROR(AVERAGE(Rankings!$K63:$O63, Rankings!$R63), "TBD") -> 2.6666667 | I63: Worlds away | J63: Dabin | K63: 1 | L63: 2 | M63: 6 | N63: 5 | O63: 1 | P63: 2 | R63: 1 | S63: =IF(SUM(Rankings!$K63:$R63)>0, COUNTIFS(Rankings!$D$2:$D$987, Rankings!$D63, Rankings!$F$2:$F$987, "<"&Rankings!$F63) + COUNTIFS(Rankings!$D$2:$D$987, Rankings!$D63, Rankings!$F$2:$F$987, Rankings!$F63, Rankings!$G$2:$G$987, "<"&Rankings!$G63)+1, "TBD") -> 1 | T63: 1 | U63: =Rankings!$S63=Rankings!$T63 -> TRUE
D64: =D60 -> 45926 | E64: =$R$1 -> Jake | F64: =IFERROR(AVERAGE(Rankings!$K64:$R64), "TBD") -> 3.5714286 | G64: =IFERROR(_xlfn.STDEV.P(Rankings!$K64:$R64), "TBD") -> 1.8405855 | H64: =IFERROR(AVERAGE(Rankings!$K64:$P64), "TBD") -> 3.8333333 | I64: The Book Lovers | J64: Broadcast | K64: 7 | L64: 1 | M64: 3 | N64: 4 | O64: 5 | P64: 3 | R64: 2 | S64: =IF(SUM(Rankings!$K64:$R64)>0, COUNTIFS(Rankings!$D$2:$D$987, Rankings!$D64, Rankings!$F$2:$F$987, "<"&Rankings!$F64) + COUNTIFS(Rankings!$D$2:$D$987, Rankings!$D64, Rankings!$F$2:$F$987, Rankings!$F64, Rankings!$G$2:$G$987, "<"&Rankings!$G64)+1, "TBD") -> 3 | T64: 1 | U64: =Rankings!$S64=Rankings!$T64 -> FALSE
A65: 45929 | C65: {=INDEX(Rankings!$E65:$E71, MATCH(1, (Rankings!$D65:$D71=$A65)*(Rankings!$U65:$U71=TRUE()), 0))} -> Weston | D65: =A65 -> 45929 | E65: =$K$1 -> Logan | F65: =IFERROR(AVERAGE(Rankings!$K65:$R65), "TBD") -> 3.5714286 | G65: =IFERROR(_xlfn.STDEV.P(Rankings!$K65:$R65), "TBD") -> 2.5555063 | H65: =IFERROR(AVERAGE(Rankings!$L65:$R65), "TBD") -> 4 | I65: FEELING LUCKY | J65: berryblue | K65: 1 | L65: 5 | M65: 7 | N65: 7 | O65: 1 | P65: 3 | R65: 1 | S65: =IF(SUM(Rankings!$K65:$R65)>0, COUNTIFS(Rankings!$D$2:$D$987, Rankings!$D65, Rankings!$F$2:$F$987, "<"&Rankings!$F65) + COUNTIFS(Rankings!$D$2:$D$987, Rankings!$D65, Rankings!$F$2:$F$987, Rankings!$F65, Rankings!$G$2:$G$987, "<"&Rankings!$G65)+1, "TBD") -> 3 | T65: 1 | U65: =Rankings!$S65=Rankings!$T65 -> FALSE | W65: #TinkerGate
D66: =D65 -> 45929 | E66: =$L$1 -> Parker | F66: =IFERROR(AVERAGE(Rankings!$K66:$R66), "TBD") -> 3.7142857 | G66: =IFERROR(_xlfn.STDEV.P(Rankings!$K66:$R66), "TBD") -> 1.9794866 | H66: =IFERROR(AVERAGE(Rankings!$K66, Rankings!$M66:$R66), "TBD") -> 4.1666667 | I66: LACONE | J66: Polima Westcoast, Quevedo, Mora | K66: 3 | L66: 1 | M66: 6 | N66: 2 | O66: 4 | P66: 7 | R66: 3 | S66: =IF(SUM(Rankings!$K66:$R66)>0, COUNTIFS(Rankings!$D$2:$D$987, Rankings!$D66, Rankings!$F$2:$F$987, "<"&Rankings!$F66) + COUNTIFS(Rankings!$D$2:$D$987, Rankings!$D66, Rankings!$F$2:$F$987, Rankings!$F66, Rankings!$G$2:$G$987, "<"&Rankings!$G66)+1, "TBD") -> 4 | T66: 1 | U66: =Rankings!$S66=Rankings!$T66 -> FALSE
D67: =D65 -> 45929 | E67: =$M$1 -> Giacomo | F67: =IFERROR(AVERAGE(Rankings!$K67:$R67), "TBD") -> 3.7142857 | G67: =IFERROR(_xlfn.STDEV.P(Rankings!$K67:$R67), "TBD") -> 2.0503857 | H67: =IFERROR(AVERAGE(Rankings!$K67:$L67, Rankings!$N67:$R67), "TBD") -> 4 | I67: BRUISED | J67: sign crushes motorist, KayCyy | K67: 2 | L67: 4 | M67: 2 | N67: 4 | O67: 7 | P67: 1 | R67: 6 | S67: =IF(SUM(Rankings!$K67:$R67)>0, COUNTIFS(Rankings!$D$2:$D$987, Rankings!$D67, Rankings!$F$2:$F$987, "<"&Rankings!$F67) + COUNTIFS(Rankings!$D$2:$D$987, Rankings!$D67, Rankings!$F$2:$F$987, Rankings!$F67, Rankings!$G$2:$G$987, "<"&Rankings!$G67)+1, "TBD") -> 5 | T67: 1 | U67: =Rankings!$S67=Rankings!$T67 -> FALSE
D68: =D65 -> 45929 | E68: =$N$1 -> Rosey | F68: =IFERROR(AVERAGE(Rankings!$K68:$R68), "TBD") -> 3.4285714 | G68: =IFERROR(_xlfn.STDEV.P(Rankings!$K68:$R68), "TBD") -> 1.7612611 | H68: =IFERROR(AVERAGE(Rankings!$K68:$M68, Rankings!$O68:$R68), "TBD") -> 3.8333333 | I68: Me and Your Mama | J68: Childish Gambino | K68: 4 | L68: 3 | M68: 1 | N68: 1 | O68: 6 | P68: 4 | R68: 5 | S68: =IF(SUM(Rankings!$K68:$R68)>0, COUNTIFS(Rankings!$D$2:$D$987, Rankings!$D68, Rankings!$F$2:$F$987, "<"&Rankings!$F68) + COUNTIFS(Rankings!$D$2:$D$987, Rankings!$D68, Rankings!$F$2:$F$987, Rankings!$F68, Rankings!$G$2:$G$987, "<"&Rankings!$G68)+1, "TBD") -> 2 | T68: 1 | U68: =Rankings!$S68=Rankings!$T68 -> FALSE
D69: =D65 -> 45929 | E69: =$O$1 -> TTAC | F69: =IFERROR(AVERAGE(Rankings!$K69:$R69), "TBD") -> 5.2857143 | G69: =IFERROR(_xlfn.STDEV.P(Rankings!$K69:$R69), "TBD") -> 1.3850514 | H69: =IFERROR(AVERAGE(Rankings!$K69:$N69, Rankings!$P69:$R69), "TBD") -> 5.6666667 | I69: Ankles | J69: Lucy Dacus | K69: 7 | L69: 6 | M69: 4 | N69: 5 | O69: 3 | P69: 5 | R69: 7 | S69: =IF(SUM(Rankings!$K69:$R69)>0, COUNTIFS(Rankings!$D$2:$D$987, Rankings!$D69, Rankings!$F$2:$F$987, "<"&Rankings!$F69) + COUNTIFS(Rankings!$D$2:$D$987, Rankings!$D69, Rankings!$F$2:$F$987, Rankings!$F69, Rankings!$G$2:$G$987, "<"&Rankings!$G69)+1, "TBD") -> 7 | T69: 1 | U69: =Rankings!$S69=Rankings!$T69 -> FALSE
D70: =D66 -> 45929 | E70: =$P$1 -> Weston | F70: =IFERROR(AVERAGE(Rankings!$K70:$R70), "TBD") -> 3.4285714 | G70: =IFERROR(_xlfn.STDEV.P(Rankings!$K70:$R70), "TBD") -> 1.4982984 | H70: =IFERROR(AVERAGE(Rankings!$K70:$O70, Rankings!$R70), "TBD") -> 3.6666667 | I70: Pasadena | J70: Young Mister | K70: 6 | L70: 2 | M70: 5 | N70: 3 | O70: 2 | P70: 2 | R70: 4 | S70: =IF(SUM(Rankings!$K70:$R70)>0, COUNTIFS(Rankings!$D$2:$D$987, Rankings!$D70, Rankings!$F$2:$F$987, "<"&Rankings!$F70) + COUNTIFS(Rankings!$D$2:$D$987, Rankings!$D70, Rankings!$F$2:$F$987, Rankings!$F70, Rankings!$G$2:$G$987, "<"&Rankings!$G70)+1, "TBD") -> 1 | T70: 1 | U70: =Rankings!$S70=Rankings!$T70 -> TRUE
D71: =D67 -> 45929 | E71: =$R$1 -> Jake | F71: =IFERROR(AVERAGE(Rankings!$K71:$R71), "TBD") -> 4.8571429 | G71: =IFERROR(_xlfn.STDEV.P(Rankings!$K71:$R71), "TBD") -> 1.6413036 | H71: =IFERROR(AVERAGE(Rankings!$K71:$P71), "TBD") -> 5.3333333 | I71: Animals | J71: Talking Heads | K71: 5 | L71: 7 | M71: 3 | N71: 6 | O71: 5 | P71: 6 | R71: 2 | S71: =IF(SUM(Rankings!$K71:$R71)>0, COUNTIFS(Rankings!$D$2:$D$987, Rankings!$D71, Rankings!$F$2:$F$987, "<"&Rankings!$F71) + COUNTIFS(Rankings!$D$2:$D$987, Rankings!$D71, Rankings!$F$2:$F$987, Rankings!$F71, Rankings!$G$2:$G$987, "<"&Rankings!$G71)+1, "TBD") -> 6 | T71: 1 | U71: =Rankings!$S71=Rankings!$T71 -> FALSE
A72: 45931 | C72: {=INDEX(Rankings!$E72:$E78, MATCH(1, (Rankings!$D72:$D78=$A72)*(Rankings!$U72:$U78=TRUE()), 0))} -> Rosey | D72: =A72 -> 45931 | E72: =$K$1 -> Logan | F72: =IFERROR(AVERAGE(Rankings!$K72:$R72), "TBD") -> 3 | G72: =IFERROR(_xlfn.STDEV.P(Rankings!$K72:$R72), "TBD") -> 2.0701967 | H72: =IFERROR(AVERAGE(Rankings!$L72:$R72), "TBD") -> 3.3333333 | I72: Life 2 | J72: Majid Jordan | K72: 1 | L72: 1 | M72: 5 | N72: 2 | O72: 6 | P72: 5 | R72: 1 | S72: =IF(SUM(Rankings!$K72:$R72)>0, COUNTIFS(Rankings!$D$2:$D$987, Rankings!$D72, Rankings!$F$2:$F$987, "<"&Rankings!$F72) + COUNTIFS(Rankings!$D$2:$D$987, Rankings!$D72, Rankings!$F$2:$F$987, Rankings!$F72, Rankings!$G$2:$G$987, "<"&Rankings!$G72)+1, "TBD") -> 2 | T72: 1 | U72: =Rankings!$S72=Rankings!$T72 -> FALSE
D73: =D72 -> 45931 | E73: =$L$1 -> Parker | F73: =IFERROR(AVERAGE(Rankings!$K73:$R73), "TBD") -> 3.8571429 | G73: =IFERROR(_xlfn.STDEV.P(Rankings!$K73:$R73), "TBD") -> 1.5518258 | H73: =IFERROR(AVERAGE(Rankings!$K73, Rankings!$M73:$R73), "TBD") -> 4.1666667 | I73: We Come Running | J73: Youngblood Hawke | K73: 2 | L73: 2 | M73: 4 | N73: 4 | O73: 3 | P73: 6 | R73: 6 | S73: =IF(SUM(Rankings!$K73:$R73)>0, COUNTIFS(Rankings!$D$2:$D$987, Rankings!$D73, Rankings!$F$2:$F$987, "<"&Rankings!$F73) + COUNTIFS(Rankings!$D$2:$D$987, Rankings!$D73, Rankings!$F$2:$F$987, Rankings!$F73, Rankings!$G$2:$G$987, "<"&Rankings!$G73)+1, "TBD") -> 4 | T73: 1 | U73: =Rankings!$S73=Rankings!$T73 -> FALSE
D74: =D72 -> 45931 | E74: =$M$1 -> Giacomo | F74: =IFERROR(AVERAGE(Rankings!$K74:$R74), "TBD") -> 5.1428571 | G74: =IFERROR(_xlfn.STDEV.P(Rankings!$K74:$R74), "TBD") -> 2.0995626 | H74: =IFERROR(AVERAGE(Rankings!$K74:$L74, Rankings!$N74:$R74), "TBD") -> 5.8333333 | I74: NOURISH A THUG | J74: Action Bronson | K74: 7 | L74: 6 | M74: 1 | N74: 7 | O74: 4 | P74: 4 | R74: 7 | S74: =IF(SUM(Rankings!$K74:$R74)>0, COUNTIFS(Rankings!$D$2:$D$987, Rankings!$D74, Rankings!$F$2:$F$987, "<"&Rankings!$F74) + COUNTIFS(Rankings!$D$2:$D$987, Rankings!$D74, Rankings!$F$2:$F$987, Rankings!$F74, Rankings!$G$2:$G$987, "<"&Rankings!$G74)+1, "TBD") -> 6 | T74: 1 | U74: =Rankings!$S74=Rankings!$T74 -> FALSE
D75: =D72 -> 45931 | E75: =$N$1 -> Rosey | F75: =IFERROR(AVERAGE(Rankings!$K75:$R75), "TBD") -> 2.7142857 | G75: =IFERROR(_xlfn.STDEV.P(Rankings!$K75:$R75), "TBD") -> 1.3850514 | H75: =IFERROR(AVERAGE(Rankings!$K75:$M75, Rankings!$O75:$R75), "TBD") -> 3 | I75: You And Me | J75: Attack! Attack! | K75: 3 | L75: 4 | M75: 2 | N75: 1 | O75: 1 | P75: 3 | R75: 5 | S75: =IF(SUM(Rankings!$K75:$R75)>0, COUNTIFS(Rankings!$D$2:$D$987, Rankings!$D75, Rankings!$F$2:$F$987, "<"&Rankings!$F75) + COUNTIFS(Rankings!$D$2:$D$987, Rankings!$D75, Rankings!$F$2:$F$987, Rankings!$F75, Rankings!$G$2:$G$987, "<"&Rankings!$G75)+1, "TBD") -> 1 | T75: 1 | U75: =Rankings!$S75=Rankings!$T75 -> TRUE
D76: =D72 -> 45931 | E76: =$O$1 -> TTAC | F76: =IFERROR(AVERAGE(Rankings!$K76:$R76), "TBD") -> 5.2857143 | G76: =IFERROR(_xlfn.STDEV.P(Rankings!$K76:$R76), "TBD") -> 1.7496355 | H76: =IFERROR(AVERAGE(Rankings!$K76:$N76, Rankings!$P76:$R76), "TBD") -> 5.3333333 | I76: Time Warp | J76: Little Nell, Patricia Quinn, Richard O'Brian | K76: 4 | L76: 7 | M76: 7 | N76: 5 | O76: 5 | P76: 7 | R76: 2 | S76: =IF(SUM(Rankings!$K76:$R76)>0, COUNTIFS(Rankings!$D$2:$D$987, Rankings!$D76, Rankings!$F$2:$F$987, "<"&Rankings!$F76) + COUNTIFS(Rankings!$D$2:$D$987, Rankings!$D76, Rankings!$F$2:$F$987, Rankings!$F76, Rankings!$G$2:$G$987, "<"&Rankings!$G76)+1, "TBD") -> 7 | T76: 1 | U76: =Rankings!$S76=Rankings!$T76 -> FALSE
D77: =D73 -> 45931 | E77: =$P$1 -> Weston | F77: =IFERROR(AVERAGE(Rankings!$K77:$R77), "TBD") -> 4.2857143 | G77: =IFERROR(_xlfn.STDEV.P(Rankings!$K77:$R77), "TBD") -> 1.905952 | H77: =IFERROR(AVERAGE(Rankings!$K77:$O77, Rankings!$R77), "TBD") -> 4.8333333 | I77: Killing my love | J77: Leslie Parrish | K77: 6 | L77: 5 | M77: 6 | N77: 6 | O77: 2 | P77: 1 | R77: 4 | S77: =IF(SUM(Rankings!$K77:$R77)>0, COUNTIFS(Rankings!$D$2:$D$987, Rankings!$D77, Rankings!$F$2:$F$987, "<"&Rankings!$F77) + COUNTIFS(Rankings!$D$2:$D$987, Rankings!$D77, Rankings!$F$2:$F$987, Rankings!$F77, Rankings!$G$2:$G$987, "<"&Rankings!$G77)+1, "TBD") -> 5 | T77: 1 | U77: =Rankings!$S77=Rankings!$T77 -> FALSE
D78: =D74 -> 45931 | E78: =$R$1 -> Jake | F78: =IFERROR(AVERAGE(Rankings!$K78:$R78), "TBD") -> 3.7142857 | G78: =IFERROR(_xlfn.STDEV.P(Rankings!$K78:$R78), "TBD") -> 1.5779087 | H78: =IFERROR(AVERAGE(Rankings!$K78:$P78), "TBD") -> 3.8333333 | I78: Haunted | J78: Poe | K78: 5 | L78: 3 | M78: 3 | N78: 3 | O78: 7 | P78: 2 | R78: 3 | S78: =IF(SUM(Rankings!$K78:$R78)>0, COUNTIFS(Rankings!$D$2:$D$987, Rankings!$D78, Rankings!$F$2:$F$987, "<"&Rankings!$F78) + COUNTIFS(Rankings!$D$2:$D$987, Rankings!$D78, Rankings!$F$2:$F$987, Rankings!$F78, Rankings!$G$2:$G$987, "<"&Rankings!$G78)+1, "TBD") -> 3 | T78: 1 | U78: =Rankings!$S78=Rankings!$T78 -> FALSE
A79: 45933 | C79: {=INDEX(Rankings!$E79:$E85, MATCH(1, (Rankings!$D79:$D85=$A79)*(Rankings!$U79:$U85=TRUE()), 0))} -> Rosey | D79: =A79 -> 45933 | E79: =$K$1 -> Logan | F79: =IFERROR(AVERAGE(Rankings!$K79:$R79), "TBD") -> 3.4285714 | G79: =IFERROR(_xlfn.STDEV.P(Rankings!$K79:$R79), "TBD") -> 1.5907898 | H79: =IFERROR(AVERAGE(Rankings!$L79:$R79), "TBD") -> 3.6666667 | I79: Ash | J79: LE SSERAFIM | K79: 2 | L79: 4 | M79: 5 | N79: 3 | O79: 3 | P79: 6 | R79: 1 | S79: =IF(SUM(Rankings!$K79:$R79)>0, COUNTIFS(Rankings!$D$2:$D$987, Rankings!$D79, Rankings!$F$2:$F$987, "<"&Rankings!$F79) + COUNTIFS(Rankings!$D$2:$D$987, Rankings!$D79, Rankings!$F$2:$F$987, Rankings!$F79, Rankings!$G$2:$G$987, "<"&Rankings!$G79)+1, "TBD") -> 4 | T79: 1 | U79: =Rankings!$S79=Rankings!$T79 -> FALSE | W79: Theme: Bechdel Test
D80: =D79 -> 45933 | E80: =$L$1 -> Parker | F80: =IFERROR(AVERAGE(Rankings!$K80:$R80), "TBD") -> 2.8571429 | G80: =IFERROR(_xlfn.STDEV.P(Rankings!$K80:$R80), "TBD") -> 1.7261494 | H80: =IFERROR(AVERAGE(Rankings!$K80, Rankings!$M80:$R80), "TBD") -> 3 | I80: Cross Your Mind | J80: Shelly | K80: 4 | L80: 2 | M80: 1 | N80: 4 | O80: 1 | P80: 2 | R80: 6 | S80: =IF(SUM(Rankings!$K80:$R80)>0, COUNTIFS(Rankings!$D$2:$D$987, Rankings!$D80, Rankings!$F$2:$F$987, "<"&Rankings!$F80) + COUNTIFS(Rankings!$D$2:$D$987, Rankings!$D80, Rankings!$F$2:$F$987, Rankings!$F80, Rankings!$G$2:$G$987, "<"&Rankings!$G80)+1, "TBD") -> 2 | T80: 1 | U80: =Rankings!$S80=Rankings!$T80 -> FALSE
D81: =D79 -> 45933 | E81: =$M$1 -> Giacomo | F81: =IFERROR(AVERAGE(Rankings!$K81:$R81), "TBD") -> 3 | G81: =IFERROR(_xlfn.STDEV.P(Rankings!$K81:$R81), "TBD") -> 1.4142136 | H81: =IFERROR(AVERAGE(Rankings!$K81:$L81, Rankings!$N81:$R81), "TBD") -> 3.1666667 | I81: Caroline | J81: Baby Rose, Mereba, BADBADNOTGOOD | K81: 5 | L81: 1 | M81: 2 | N81: 2 | O81: 5 | P81: 3 | R81: 3 | S81: =IF(SUM(Rankings!$K81:$R81)>0, COUNTIFS(Rankings!$D$2:$D$987, Rankings!$D81, Rankings!$F$2:$F$987, "<"&Rankings!$F81) + COUNTIFS(Rankings!$D$2:$D$987, Rankings!$D81, Rankings!$F$2:$F$987, Rankings!$F81, Rankings!$G$2:$G$987, "<"&Rankings!$G81)+1, "TBD") -> 3 | T81: 1 | U81: =Rankings!$S81=Rankings!$T81 -> FALSE
D82: =D79 -> 45933 | E82: =$N$1 -> Rosey | F82: =IFERROR(AVERAGE(Rankings!$K82:$R82), "TBD") -> 2.5714286 | G82: =IFERROR(_xlfn.STDEV.P(Rankings!$K82:$R82), "TBD") -> 1.5907898 | H82: =IFERROR(AVERAGE(Rankings!$K82:$M82, Rankings!$O82:$R82), "TBD") -> 2.8333333 | I82: All The Things She Said | J82: t.A.T.u | K82: 3 | L82: 3 | M82: 6 | N82: 1 | O82: 2 | P82: 1 | R82: 2 | S82: =IF(SUM(Rankings!$K82:$R82)>0, COUNTIFS(Rankings!$D$2:$D$987, Rankings!$D82, Rankings!$F$2:$F$987, "<"&Rankings!$F82) + COUNTIFS(Rankings!$D$2:$D$987, Rankings!$D82, Rankings!$F$2:$F$987, Rankings!$F82, Rankings!$G$2:$G$987, "<"&Rankings!$G82)+1, "TBD") -> 1 | T82: 1 | U82: =Rankings!$S82=Rankings!$T82 -> TRUE
D83: =D79 -> 45933 | E83: =$O$1 -> TTAC | F83: =IFERROR(AVERAGE(Rankings!$K83:$R83), "TBD") -> 7 | G83: =IFERROR(_xlfn.STDEV.P(Rankings!$K83:$R83), "TBD") -> 0 | H83: =IFERROR(AVERAGE(Rankings!$K83:$N83, Rankings!$P83:$R83), "TBD") -> 7 | I83: Still Woman Enough (feat. Reba McEntire & Carrie Underwood | J83: Loretta Lynn, Reba McEntire, Carrie Underwood | K83: 7 | L83: 7 | M83: 7 | N83: 7 | O83: 7 | P83: 7 | R83: 7 | S83: =IF(SUM(Rankings!$K83:$R83)>0, COUNTIFS(Rankings!$D$2:$D$987, Rankings!$D83, Rankings!$F$2:$F$987, "<"&Rankings!$F83) + COUNTIFS(Rankings!$D$2:$D$987, Rankings!$D83, Rankings!$F$2:$F$987, Rankings!$F83, Rankings!$G$2:$G$987, "<"&Rankings!$G83)+1, "TBD") -> 7 | T83: 1 | U83: =Rankings!$S83=Rankings!$T83 -> FALSE
D84: =D80 -> 45933 | E84: =$P$1 -> Weston | F84: =IFERROR(AVERAGE(Rankings!$K84:$R84), "TBD") -> 5 | G84: =IFERROR(_xlfn.STDEV.P(Rankings!$K84:$R84), "TBD") -> 1.1952286 | H84: =IFERROR(AVERAGE(Rankings!$K84:$O84, Rankings!$R84), "TBD") -> 5.1666667 | I84: Hospital | J84: Madison Cunningham, Remi Wolf | K84: 6 | L84: 6 | M84: 3 | N84: 6 | O84: 6 | P84: 4 | R84: 4 | S84: =IF(SUM(Rankings!$K84:$R84)>0, COUNTIFS(Rankings!$D$2:$D$987, Rankings!$D84, Rankings!$F$2:$F$987, "<"&Rankings!$F84) + COUNTIFS(Rankings!$D$2:$D$987, Rankings!$D84, Rankings!$F$2:$F$987, Rankings!$F84, Rankings!$G$2:$G$987, "<"&Rankings!$G84)+1, "TBD") -> 6 | T84: 1 | U84: =Rankings!$S84=Rankings!$T84 -> FALSE
D85: =D81 -> 45933 | E85: =$R$1 -> Jake | F85: =IFERROR(AVERAGE(Rankings!$K85:$R85), "TBD") -> 4.1428571 | G85: =IFERROR(_xlfn.STDEV.P(Rankings!$K85:$R85), "TBD") -> 1.3552619 | H85: =IFERROR(AVERAGE(Rankings!$K85:$P85), "TBD") -> 4 | I85: Pink Roses | J85: Say She She | K85: 1 | L85: 5 | M85: 4 | N85: 5 | O85: 4 | P85: 5 | R85: 5 | S85: =IF(SUM(Rankings!$K85:$R85)>0, COUNTIFS(Rankings!$D$2:$D$987, Rankings!$D85, Rankings!$F$2:$F$987, "<"&Rankings!$F85) + COUNTIFS(Rankings!$D$2:$D$987, Rankings!$D85, Rankings!$F$2:$F$987, Rankings!$F85, Rankings!$G$2:$G$987, "<"&Rankings!$G85)+1, "TBD") -> 5 | T85: 1 | U85: =Rankings!$S85=Rankings!$T85 -> FALSE
A86: 45936 | C86: {=INDEX(Rankings!$E86:$E92, MATCH(1, (Rankings!$D86:$D92=$A86)*(Rankings!$U86:$U92=TRUE()), 0))} -> TTAC | D86: =A86 -> 45936 | E86: =$K$1 -> Logan | F86: =IFERROR(AVERAGE(Rankings!$K86:$R86), "TBD") -> 5.2857143 | G86: =IFERROR(_xlfn.STDEV.P(Rankings!$K86:$R86), "TBD") -> 1.7496355 | H86: =IFERROR(AVERAGE(Rankings!$L86:$R86), "TBD") -> 5.6666667 | I86: ADD | J86: Khantrast | K86: 3 | L86: 6 | M86: 7 | N86: 4 | O86: 7 | P86: 7 | R86: 3 | S86: =IF(SUM(Rankings!$K86:$R86)>0, COUNTIFS(Rankings!$D$2:$D$987, Rankings!$D86, Rankings!$F$2:$F$987, "<"&Rankings!$F86) + COUNTIFS(Rankings!$D$2:$D$987, Rankings!$D86, Rankings!$F$2:$F$987, Rankings!$F86, Rankings!$G$2:$G$987, "<"&Rankings!$G86)+1, "TBD") -> 6 | T86: 1 | U86: =Rankings!$S86=Rankings!$T86 -> FALSE
D87: =D86 -> 45936 | E87: =$L$1 -> Parker | F87: =IFERROR(AVERAGE(Rankings!$K87:$R87), "TBD") -> 5 | G87: =IFERROR(_xlfn.STDEV.P(Rankings!$K87:$R87), "TBD") -> 1.3093073 | H87: =IFERROR(AVERAGE(Rankings!$K87, Rankings!$M87:$R87), "TBD") -> 5.3333333 | I87: Chills | J87: Dave East | K87: 6 | L87: 3 | M87: 3 | N87: 6 | O87: 6 | P87: 5 | R87: 6 | S87: =IF(SUM(Rankings!$K87:$R87)>0, COUNTIFS(Rankings!$D$2:$D$987, Rankings!$D87, Rankings!$F$2:$F$987, "<"&Rankings!$F87) + COUNTIFS(Rankings!$D$2:$D$987, Rankings!$D87, Rankings!$F$2:$F$987, Rankings!$F87, Rankings!$G$2:$G$987, "<"&Rankings!$G87)+1, "TBD") -> 5 | T87: 1 | U87: =Rankings!$S87=Rankings!$T87 -> FALSE
D88: =D86 -> 45936 | E88: =$M$1 -> Giacomo | F88: =IFERROR(AVERAGE(Rankings!$K88:$R88), "TBD") -> 2.1428571 | G88: =IFERROR(_xlfn.STDEV.P(Rankings!$K88:$R88), "TBD") -> 1.3552619 | H88: =IFERROR(AVERAGE(Rankings!$K88:$L88, Rankings!$N88:$R88), "TBD") -> 2.3333333 | I88: One Wish | J88: Ravyn Lenae, Childish Gambino | K88: 1 | L88: 1 | M88: 1 | N88: 2 | O88: 2 | P88: 3 | R88: 5 | S88: =IF(SUM(Rankings!$K88:$R88)>0, COUNTIFS(Rankings!$D$2:$D$987, Rankings!$D88, Rankings!$F$2:$F$987, "<"&Rankings!$F88) + COUNTIFS(Rankings!$D$2:$D$987, Rankings!$D88, Rankings!$F$2:$F$987, Rankings!$F88, Rankings!$G$2:$G$987, "<"&Rankings!$G88)+1, "TBD") -> 2 | T88: 1 | U88: =Rankings!$S88=Rankings!$T88 -> FALSE
D89: =D86 -> 45936 | E89: =$N$1 -> Rosey | F89: =IFERROR(AVERAGE(Rankings!$K89:$R89), "TBD") -> 3.2857143 | G89: =IFERROR(_xlfn.STDEV.P(Rankings!$K89:$R89), "TBD") -> 0.88063057 | H89: =IFERROR(AVERAGE(Rankings!$K89:$M89, Rankings!$O89:$R89), "TBD") -> 3.3333333 | I89: Levels | J89: BigXthaPlug | K89: 2 | L89: 4 | M89: 4 | N89: 3 | O89: 4 | P89: 4 | R89: 2 | S89: =IF(SUM(Rankings!$K89:$R89)>0, COUNTIFS(Rankings!$D$2:$D$987, Rankings!$D89, Rankings!$F$2:$F$987, "<"&Rankings!$F89) + COUNTIFS(Rankings!$D$2:$D$987, Rankings!$D89, Rankings!$F$2:$F$987, Rankings!$F89, Rankings!$G$2:$G$987, "<"&Rankings!$G89)+1, "TBD") -> 3 | T89: 1 | U89: =Rankings!$S89=Rankings!$T89 -> FALSE
D90: =D86 -> 45936 | E90: =$O$1 -> TTAC | F90: =IFERROR(AVERAGE(Rankings!$K90:$R90), "TBD") -> 1.8571429 | G90: =IFERROR(_xlfn.STDEV.P(Rankings!$K90:$R90), "TBD") -> 0.98974332 | H90: =IFERROR(AVERAGE(Rankings!$K90:$N90, Rankings!$P90:$R90), "TBD") -> 2 | I90: The Scythe | J90: The Last Dinner Party | K90: 4 | L90: 2 | M90: 2 | N90: 1 | O90: 1 | P90: 2 | R90: 1 | S90: =IF(SUM(Rankings!$K90:$R90)>0, COUNTIFS(Rankings!$D$2:$D$987, Rankings!$D90, Rankings!$F$2:$F$987, "<"&Rankings!$F90) + COUNTIFS(Rankings!$D$2:$D$987, Rankings!$D90, Rankings!$F$2:$F$987, Rankings!$F90, Rankings!$G$2:$G$987, "<"&Rankings!$G90)+1, "TBD") -> 1 | T90: 1 | U90: =Rankings!$S90=Rankings!$T90 -> TRUE
D91: =D87 -> 45936 | E91: =$P$1 -> Weston | F91: =IFERROR(AVERAGE(Rankings!$K91:$R91), "TBD") -> 4.7142857 | G91: =IFERROR(_xlfn.STDEV.P(Rankings!$K91:$R91), "TBD") -> 1.9794866 | H91: =IFERROR(AVERAGE(Rankings!$K91:$O91, Rankings!$R91), "TBD") -> 5.3333333 | I91: Astrovan | J91: Mt Joy | K91: 7 | L91: 5 | M91: 5 | N91: 5 | O91: 3 | P91: 1 | R91: 7 | S91: =IF(SUM(Rankings!$K91:$R91)>0, COUNTIFS(Rankings!$D$2:$D$987, Rankings!$D91, Rankings!$F$2:$F$987, "<"&Rankings!$F91) + COUNTIFS(Rankings!$D$2:$D$987, Rankings!$D91, Rankings!$F$2:$F$987, Rankings!$F91, Rankings!$G$2:$G$987, "<"&Rankings!$G91)+1, "TBD") -> 4 | T91: 1 | U91: =Rankings!$S91=Rankings!$T91 -> FALSE
D92: =D88 -> 45936 | E92: =$R$1 -> Jake | F92: =IFERROR(AVERAGE(Rankings!$K92:$R92), "TBD") -> 5.7142857 | G92: =IFERROR(_xlfn.STDEV.P(Rankings!$K92:$R92), "TBD") -> 1.0301575 | H92: =IFERROR(AVERAGE(Rankings!$K92:$P92), "TBD") -> 6 | I92: Don't Worry About the Government | J92: Talking Heads | K92: 5 | L92: 7 | M92: 6 | N92: 7 | O92: 5 | P92: 6 | R92: 4 | S92: =IF(SUM(Rankings!$K92:$R92)>0, COUNTIFS(Rankings!$D$2:$D$987, Rankings!$D92, Rankings!$F$2:$F$987, "<"&Rankings!$F92) + COUNTIFS(Rankings!$D$2:$D$987, Rankings!$D92, Rankings!$F$2:$F$987, Rankings!$F92, Rankings!$G$2:$G$987, "<"&Rankings!$G92)+1, "TBD") -> 7 | T92: 1 | U92: =Rankings!$S92=Rankings!$T92 -> FALSE
A93: 45938 | C93: {=INDEX(Rankings!$E93:$E99, MATCH(1, (Rankings!$D93:$D99=$A93)*(Rankings!$U93:$U99=TRUE()), 0))} -> TTAC | D93: =A93 -> 45938 | E93: =$K$1 -> Logan | F93: =IFERROR(AVERAGE(Rankings!$K93:$R93), "TBD") -> 3.8571429 | G93: =IFERROR(_xlfn.STDEV.P(Rankings!$K93:$R93), "TBD") -> 2.531435 | H93: =IFERROR(AVERAGE(Rankings!$L93:$R93), "TBD") -> 4.3333333 | I93: Flyers | J93: BRADIO | K93: 1 | L93: 6 | M93: 5 | N93: 1 | O93: 1 | P93: 6 | R93: 7 | S93: =IF(SUM(Rankings!$K93:$R93)>0, COUNTIFS(Rankings!$D$2:$D$987, Rankings!$D93, Rankings!$F$2:$F$987, "<"&Rankings!$F93) + COUNTIFS(Rankings!$D$2:$D$987, Rankings!$D93, Rankings!$F$2:$F$987, Rankings!$F93, Rankings!$G$2:$G$987, "<"&Rankings!$G93)+1, "TBD") -> 4 | T93: 1 | U93: =Rankings!$S93=Rankings!$T93 -> FALSE
D94: =D93 -> 45938 | E94: =$L$1 -> Parker | F94: =IFERROR(AVERAGE(Rankings!$K94:$R94), "TBD") -> 3.1428571 | G94: =IFERROR(_xlfn.STDEV.P(Rankings!$K94:$R94), "TBD") -> 1.2453997 | H94: =IFERROR(AVERAGE(Rankings!$K94, Rankings!$M94:$R94), "TBD") -> 3.5 | I94: NO ME QUIERO CASAR | J94: Bad Bunny | K94: 2 | L94: 1 | M94: 4 | N94: 3 | O94: 5 | P94: 3 | R94: 4 | S94: =IF(SUM(Rankings!$K94:$R94)>0, COUNTIFS(Rankings!$D$2:$D$987, Rankings!$D94, Rankings!$F$2:$F$987, "<"&Rankings!$F94) + COUNTIFS(Rankings!$D$2:$D$987, Rankings!$D94, Rankings!$F$2:$F$987, Rankings!$F94, Rankings!$G$2:$G$987, "<"&Rankings!$G94)+1, "TBD") -> 2 | T94: 1 | U94: =Rankings!$S94=Rankings!$T94 -> FALSE
D95: =D93 -> 45938 | E95: =$M$1 -> Giacomo | F95: =IFERROR(AVERAGE(Rankings!$K95:$R95), "TBD") -> 3.7142857 | G95: =IFERROR(_xlfn.STDEV.P(Rankings!$K95:$R95), "TBD") -> 1.2777531 | H95: =IFERROR(AVERAGE(Rankings!$K95:$L95, Rankings!$N95:$R95), "TBD") -> 4 | I95: You a Joke | J95: BIGBABYGUCCI | K95: 5 | L95: 3 | M95: 2 | N95: 2 | O95: 4 | P95: 5 | R95: 5 | S95: =IF(SUM(Rankings!$K95:$R95)>0, COUNTIFS(Rankings!$D$2:$D$987, Rankings!$D95, Rankings!$F$2:$F$987, "<"&Rankings!$F95) + COUNTIFS(Rankings!$D$2:$D$987, Rankings!$D95, Rankings!$F$2:$F$987, Rankings!$F95, Rankings!$G$2:$G$987, "<"&Rankings!$G95)+1, "TBD") -> 3 | T95: 1 | U95: =Rankings!$S95=Rankings!$T95 -> FALSE
D96: =D93 -> 45938 | E96: =$N$1 -> Rosey | F96: =IFERROR(AVERAGE(Rankings!$K96:$R96), "TBD") -> 4.8571429 | G96: =IFERROR(_xlfn.STDEV.P(Rankings!$K96:$R96), "TBD") -> 1.6413036 | H96: =IFERROR(AVERAGE(Rankings!$K96:$M96, Rankings!$O96:$R96), "TBD") -> 5 | I96: Determinate | J96: Lemonade Mouth | K96: 3 | L96: 4 | M96: 7 | N96: 4 | O96: 3 | P96: 7 | R96: 6 | S96: =IF(SUM(Rankings!$K96:$R96)>0, COUNTIFS(Rankings!$D$2:$D$987, Rankings!$D96, Rankings!$F$2:$F$987, "<"&Rankings!$F96) + COUNTIFS(Rankings!$D$2:$D$987, Rankings!$D96, Rankings!$F$2:$F$987, Rankings!$F96, Rankings!$G$2:$G$987, "<"&Rankings!$G96)+1, "TBD") -> 6 | T96: 1 | U96: =Rankings!$S96=Rankings!$T96 -> FALSE
D97: =D93 -> 45938 | E97: =$O$1 -> TTAC | F97: =IFERROR(AVERAGE(Rankings!$K97:$R97), "TBD") -> 3 | G97: =IFERROR(_xlfn.STDEV.P(Rankings!$K97:$R97), "TBD") -> 2 | H97: =IFERROR(AVERAGE(Rankings!$K97:$N97, Rankings!$P97:$R97), "TBD") -> 3.1666667 | I97: By and By | J97: Caamp | K97: 6 | L97: 2 | M97: 3 | N97: 6 | O97: 2 | P97: 1 | R97: 1 | S97: =IF(SUM(Rankings!$K97:$R97)>0, COUNTIFS(Rankings!$D$2:$D$987, Rankings!$D97, Rankings!$F$2:$F$987, "<"&Rankings!$F97) + COUNTIFS(Rankings!$D$2:$D$987, Rankings!$D97, Rankings!$F$2:$F$987, Rankings!$F97, Rankings!$G$2:$G$987, "<"&Rankings!$G97)+1, "TBD") -> 1 | T97: 1 | U97: =Rankings!$S97=Rankings!$T97 -> TRUE
D98: =D94 -> 45938 | E98: =$P$1 -> Weston | F98: =IFERROR(AVERAGE(Rankings!$K98:$R98), "TBD") -> 4 | G98: =IFERROR(_xlfn.STDEV.P(Rankings!$K98:$R98), "TBD") -> 2.2677868 | H98: =IFERROR(AVERAGE(Rankings!$K98:$O98, Rankings!$R98), "TBD") -> 4.3333333 | I98: Victory Lap | J98: Fred Again, Skepta | K98: 4 | L98: 5 | M98: 1 | N98: 7 | O98: 7 | P98: 2 | R98: 2 | S98: =IF(SUM(Rankings!$K98:$R98)>0, COUNTIFS(Rankings!$D$2:$D$987, Rankings!$D98, Rankings!$F$2:$F$987, "<"&Rankings!$F98) + COUNTIFS(Rankings!$D$2:$D$987, Rankings!$D98, Rankings!$F$2:$F$987, Rankings!$F98, Rankings!$G$2:$G$987, "<"&Rankings!$G98)+1, "TBD") -> 5 | T98: 1 | U98: =Rankings!$S98=Rankings!$T98 -> FALSE
D99: =D95 -> 45938 | E99: =$R$1 -> Jake | F99: =IFERROR(AVERAGE(Rankings!$K99:$R99), "TBD") -> 5.4285714 | G99: =IFERROR(_xlfn.STDEV.P(Rankings!$K99:$R99), "TBD") -> 1.3997084 | H99: =IFERROR(AVERAGE(Rankings!$K99:$P99), "TBD") -> 5.8333333 | I99: Goliath | J99: Woodkid | K99: 7 | L99: 7 | M99: 6 | N99: 5 | O99: 6 | P99: 4 | R99: 3 | S99: =IF(SUM(Rankings!$K99:$R99)>0, COUNTIFS(Rankings!$D$2:$D$987, Rankings!$D99, Rankings!$F$2:$F$987, "<"&Rankings!$F99) + COUNTIFS(Rankings!$D$2:$D$987, Rankings!$D99, Rankings!$F$2:$F$987, Rankings!$F99, Rankings!$G$2:$G$987, "<"&Rankings!$G99)+1, "TBD") -> 7 | T99: 1 | U99: =Rankings!$S99=Rankings!$T99 -> FALSE
A100: 45940 | C100: {=INDEX(Rankings!$E100:$E106, MATCH(1, (Rankings!$D100:$D106=$A100)*(Rankings!$U100:$U106=TRUE()), 0))} -> Weston | D100: =A100 -> 45940 | E100: =$K$1 -> Logan | F100: =IFERROR(AVERAGE(Rankings!$K100:$R100), "TBD") -> 2.5714286 | G100: =IFERROR(_xlfn.STDEV.P(Rankings!$K100:$R100), "TBD") -> 1.9166297 | H100: =IFERROR(AVERAGE(Rankings!$L100:$R100), "TBD") -> 2.6666667 | I100: In The Morning | J100: Jay Prince | K100: 2 | L100: 1 | M100: 7 | N100: 1 | O100: 2 | P100: 2 | R100: 3 | S100: =IF(SUM(Rankings!$K100:$R100)>0, COUNTIFS(Rankings!$D$2:$D$987, Rankings!$D100, Rankings!$F$2:$F$987, "<"&Rankings!$F100) + COUNTIFS(Rankings!$D$2:$D$987, Rankings!$D100, Rankings!$F$2:$F$987, Rankings!$F100, Rankings!$G$2:$G$987, "<"&Rankings!$G100)+1, "TBD") -> 2 | T100: 1 | U100: =Rankings!$S100=Rankings!$T100 -> FALSE
...

Sheet Leaderboard
B2: =CONCAT("Day ",COUNTIF(Rankings!A:A,"<="&TODAY())) -> Day 165 | C2: Number of Wins | D2: Sum of Average | E2: Overall Average | F2: Place | G2: Constructors
B3: =Rankings!$K$1 -> Logan | C3: =COUNTIFS(Rankings!$E$2:$E$987,$B3, Rankings!$U$2:$U$987,TRUE()) -> 15 | D3: {=SUM(IF(Rankings!$E$2:$E$987=$B3, Rankings!$F$2:$F$987))} -> 557.73333 | E3: {=AVERAGE(IF(Rankings!$E$2:$E$987=$B3, Rankings!$F$2:$F$987))} -> 3.9002331 | F3: =_xlfn.RANK.EQ(C3,$C$3:$C$10,0) -> 5 | G3: =_xlfn.RANK.EQ(E3,$E$3:$E$10,1) -> 6
B4: =Rankings!$L$1 -> Parker | C4: =COUNTIFS(Rankings!$E$2:$E$987,$B4, Rankings!$U$2:$U$987,TRUE()) -> 22 | D4: {=SUM(IF(Rankings!$E$2:$E$987=$B4, Rankings!$F$2:$F$987))} -> 517.86667 | E4: {=AVERAGE(IF(Rankings!$E$2:$E$987=$B4, Rankings!$F$2:$F$987))} -> 3.6214452 | F4: =_xlfn.RANK.EQ(C4,$C$3:$C$10,0) -> 3 | G4: =_xlfn.RANK.EQ(E4,$E$3:$E$10,1) -> 2
B5: =Rankings!$M$1 -> Giacomo | C5: =COUNTIFS(Rankings!$E$2:$E$987,$B5, Rankings!$U$2:$U$987,TRUE()) -> 20 | D5: {=SUM(IF(Rankings!$E$2:$E$987=$B5, Rankings!$F$2:$F$987))} -> 518.9 | E5: {=AVERAGE(IF(Rankings!$E$2:$E$987=$B5, Rankings!$F$2:$F$987))} -> 3.6286713 | F5: =_xlfn.RANK.EQ(C5,$C$3:$C$10,0) -> 4 | G5: =_xlfn.RANK.EQ(E5,$E$3:$E$10,1) -> 3
B6: =Rankings!$N$1 -> Rosey | C6: =COUNTIFS(Rankings!$E$2:$E$987,$B6, Rankings!$U$2:$U$987,TRUE()) -> 26 | D6: {=SUM(IF(Rankings!$E$2:$E$987=$B6, Rankings!$F$2:$F$987))} -> 378.78571 | E6: {=AVERAGE(IF(Rankings!$E$2:$E$987=$B6, Rankings!$F$2:$F$987))} -> 3.6421703 | F6: =_xlfn.RANK.EQ(C6,$C$3:$C$10,0) -> 2 | G6: =_xlfn.RANK.EQ(E6,$E$3:$E$10,1) -> 5
B7: =Rankings!$O$1 -> TTAC | C7: =COUNTIFS(Rankings!$E$2:$E$987,$B7, Rankings!$U$2:$U$987,TRUE()) -> 12 | D7: {=SUM(IF(Rankings!$E$2:$E$987=$B7, Rankings!$F$2:$F$987))} -> 632.40476 | E7: {=AVERAGE(IF(Rankings!$E$2:$E$987=$B7, Rankings!$F$2:$F$987))} -> 4.4535547 | F7: =_xlfn.RANK.EQ(C7,$C$3:$C$10,0) -> 7 | G7: =_xlfn.RANK.EQ(E7,$E$3:$E$10,1) -> 8
B8: =Rankings!$P$1 -> Weston | C8: =COUNTIFS(Rankings!$E$2:$E$987,$B8, Rankings!$U$2:$U$987,TRUE()) -> 30 | D8: {=SUM(IF(Rankings!$E$2:$E$987=$B8, Rankings!$F$2:$F$987))} -> 512.04762 | E8: {=AVERAGE(IF(Rankings!$E$2:$E$987=$B8, Rankings!$F$2:$F$987))} -> 3.6059691 | F8: =_xlfn.RANK.EQ(C8,$C$3:$C$10,0) -> 1 | G8: =_xlfn.RANK.EQ(E8,$E$3:$E$10,1) -> 1
B9: =Rankings!$R$1 -> Jake | C9: =COUNTIFS(Rankings!$E$2:$E$987,$B9, Rankings!$U$2:$U$987,TRUE()) -> 2 | D9: {=SUM(IF(Rankings!$E$2:$E$987=$B9, Rankings!$F$2:$F$987))} -> 209.02381 | E9: {=AVERAGE(IF(Rankings!$E$2:$E$987=$B9, Rankings!$F$2:$F$987))} -> 4.265792 | F9: =_xlfn.RANK.EQ(C9,$C$3:$C$10,0) -> 8 | G9: =_xlfn.RANK.EQ(E9,$E$3:$E$10,1) -> 7
B10: =Rankings!$Q$1 -> Flocco | C10: =COUNTIFS(Rankings!$E$2:$E$987,$B10, Rankings!$U$2:$U$987,TRUE()) -> 15 | D10: {=SUM(IF(Rankings!$E$2:$E$987=$B10, Rankings!$F$2:$F$987))} -> 272.19048 | E10: {=AVERAGE(IF(Rankings!$E$2:$E$987=$B10, Rankings!$F$2:$F$987))} -> 3.6292063 | F10: =_xlfn.RANK.EQ(C10,$C$3:$C$10,0) -> 5 | G10: =_xlfn.RANK.EQ(E10,$E$3:$E$10,1) -> 4
B12: Average Rank
B13: Poster/Voter | C13: =Rankings!$K$1 -> Logan | D13: =Rankings!$L$1 -> Parker | E13: =Rankings!$M$1 -> Giacomo | F13: =Rankings!$N$1 -> Rosey | G13: =Rankings!$O$1 -> TTAC | H13: =Rankings!$P$1 -> Weston | I13: =Rankings!$R$1 -> Jake | J13: =Rankings!$Q$1 -> Flocco
B14: =Rankings!$K$1 -> Logan | C14: =AVERAGEIF(Rankings!$E:$E, $B14, Rankings!K:K) -> 2.195122 | D14: =AVERAGEIF(Rankings!$E:$E, $B14, Rankings!L:L) -> 4.037037 | E14: =AVERAGEIF(Rankings!$E:$E, $B14, Rankings!M:M) -> 4.4233129 | F14: =AVERAGEIF(Rankings!$E:$E, $B14, Rankings!N:N) -> 3.8383838 | G14: =AVERAGEIF(Rankings!$E:$E, $B14, Rankings!O:O) -> 4.402439 | H14: =AVERAGEIF(Rankings!$E:$E, $B14, Rankings!P:P) -> 4.1509434 | I14: =AVERAGEIF(Rankings!$E:$E, $B14, Rankings!R:R) -> 3.7777778 | J14: =AVERAGEIF(Rankings!$E:$E, $B14, Rankings!Q:Q) -> 4.0465116
B15: =Rankings!$L$1 -> Parker | C15: =AVERAGEIF(Rankings!$E:$E, $B15, Rankings!K:K) -> 3.7743902 | D15: =AVERAGEIF(Rankings!$E:$E, $B15, Rankings!L:L) -> 2.1165644 | E15: =AVERAGEIF(Rankings!$E:$E, $B15, Rankings!M:M) -> 3.2638037 | F15: =AVERAGEIF(Rankings!$E:$E, $B15, Rankings!N:N) -> 4.1212121 | G15: =AVERAGEIF(Rankings!$E:$E, $B15, Rankings!O:O) -> 3.7926829 | H15: =AVERAGEIF(Rankings!$E:$E, $B15, Rankings!P:P) -> 3.836478 | I15: =AVERAGEIF(Rankings!$E:$E, $B15, Rankings!R:R) -> 4.3777778 | J15: =AVERAGEIF(Rankings!$E:$E, $B15, Rankings!Q:Q) -> 4.2906977
B16: =Rankings!$M$1 -> Giacomo | C16: =AVERAGEIF(Rankings!$E:$E, $B16, Rankings!K:K) -> 3.8902439 | D16: =AVERAGEIF(Rankings!$E:$E, $B16, Rankings!L:L) -> 3.1851852 | E16: =AVERAGEIF(Rankings!$E:$E, $B16, Rankings!M:M) -> 1.7546012 | F16: =AVERAGEIF(Rankings!$E:$E, $B16, Rankings!N:N) -> 4.1818182 | G16: =AVERAGEIF(Rankings!$E:$E, $B16, Rankings!O:O) -> 4.1219512 | H16: =AVERAGEIF(Rankings!$E:$E, $B16, Rankings!P:P) -> 3.7484277 | I16: =AVERAGEIF(Rankings!$E:$E, $B16, Rankings!R:R) -> 4.4888889 | J16: =AVERAGEIF(Rankings!$E:$E, $B16, Rankings!Q:Q) -> 4.9883721
B17: =Rankings!$N$1 -> Rosey | C17: =AVERAGEIF(Rankings!$E:$E, $B17, Rankings!K:K) -> 3.5673077 | D17: =AVERAGEIF(Rankings!$E:$E, $B17, Rankings!L:L) -> 3.8653846 | E17: =AVERAGEIF(Rankings!$E:$E, $B17, Rankings!M:M) -> 4.1165049 | F17: =AVERAGEIF(Rankings!$E:$E, $B17, Rankings!N:N) -> 1.9191919 | G17: =AVERAGEIF(Rankings!$E:$E, $B17, Rankings!O:O) -> 3.8058252 | H17: =AVERAGEIF(Rankings!$E:$E, $B17, Rankings!P:P) -> 4.223301 | I17: =AVERAGEIF(Rankings!$E:$E, $B17, Rankings!R:R) -> 4 | J17: =AVERAGEIF(Rankings!$E:$E, $B17, Rankings!Q:Q) -> 3.9767442
B18: =Rankings!$O$1 -> TTAC | C18: =AVERAGEIF(Rankings!$E:$E, $B18, Rankings!K:K) -> 4.8719512 | D18: =AVERAGEIF(Rankings!$E:$E, $B18, Rankings!L:L) -> 4.9691358 | E18: =AVERAGEIF(Rankings!$E:$E, $B18, Rankings!M:M) -> 4.9141104 | F18: =AVERAGEIF(Rankings!$E:$E, $B18, Rankings!N:N) -> 5.3030303 | G18: =AVERAGEIF(Rankings!$E:$E, $B18, Rankings!O:O) -> 2.4756098 | H18: =AVERAGEIF(Rankings!$E:$E, $B18, Rankings!P:P) -> 4.5031447 | I18: =AVERAGEIF(Rankings!$E:$E, $B18, Rankings!R:R) -> 5.2888889 | J18: =AVERAGEIF(Rankings!$E:$E, $B18, Rankings!Q:Q) -> 3.7325581
B19: =Rankings!$P$1 -> Weston | C19: =AVERAGEIF(Rankings!$E:$E, $B19, Rankings!K:K) -> 3.8780488 | D19: =AVERAGEIF(Rankings!$E:$E, $B19, Rankings!L:L) -> 3.9753086 | E19: =AVERAGEIF(Rankings!$E:$E, $B19, Rankings!M:M) -> 3.6687117 | F19: =AVERAGEIF(Rankings!$E:$E, $B19, Rankings!N:N) -> 3.9494949 | G19: =AVERAGEIF(Rankings!$E:$E, $B19, Rankings!O:O) -> 4.1585366 | H19: =AVERAGEIF(Rankings!$E:$E, $B19, Rankings!P:P) -> 2.0440252 | I19: =AVERAGEIF(Rankings!$E:$E, $B19, Rankings!R:R) -> 3.4888889 | J19: =AVERAGEIF(Rankings!$E:$E, $B19, Rankings!Q:Q) -> 3.6976744
B20: =Rankings!$R$1 -> Jake | C20: =AVERAGEIF(Rankings!$E:$E, $B20, Rankings!K:K) -> 4.7346939 | D20: =AVERAGEIF(Rankings!$E:$E, $B20, Rankings!L:L) -> 4.7755102 | E20: =AVERAGEIF(Rankings!$E:$E, $B20, Rankings!M:M) -> 4.6938776 | F20: =AVERAGEIF(Rankings!$E:$E, $B20, Rankings!N:N) -> 4.2857143 | G20: =AVERAGEIF(Rankings!$E:$E, $B20, Rankings!O:O) -> 4.244898 | H20: =AVERAGEIF(Rankings!$E:$E, $B20, Rankings!P:P) -> 4.4081633 | I20: =AVERAGEIF(Rankings!$E:$E, $B20, Rankings!R:R) -> 2.5777778 | J20: N/A
B21: =Rankings!$Q$1 -> Flocco | C21: =AVERAGEIF(Rankings!$E:$E, $B21, Rankings!K:K) -> 3.8372093 | D21: =AVERAGEIF(Rankings!$E:$E, $B21, Rankings!L:L) -> 4.1627907 | E21: =AVERAGEIF(Rankings!$E:$E, $B21, Rankings!M:M) -> 4.3488372 | F21: =AVERAGEIF(Rankings!$E:$E, $B21, Rankings!N:N) -> 4.45 | G21: =AVERAGEIF(Rankings!$E:$E, $B21, Rankings!O:O) -> 3.1627907 | H21: =AVERAGEIF(Rankings!$E:$E, $B21, Rankings!P:P) -> 4.0348837 | I21: N/A | J21: =AVERAGEIF(Rankings!$E:$E, $B21, Rankings!Q:Q) -> 1.6823529
B23: Best Rank
B24: Poster/Voter | C24: =Rankings!$K$1 -> Logan | D24: =Rankings!$L$1 -> Parker | E24: =Rankings!$M$1 -> Giacomo | F24: =Rankings!$N$1 -> Rosey | G24: =Rankings!$O$1 -> TTAC | H24: =Rankings!$P$1 -> Weston | I24: =Rankings!$R$1 -> Jake | J24: =Rankings!$Q$1 -> Flocco
B25: =Rankings!$K$1 -> Logan | C25: =MINIFS(Rankings!K:K, Rankings!$E:$E, $B25) -> 1 | D25: =MINIFS(Rankings!L:L, Rankings!$E:$E, $B25) -> 1 | E25: =MINIFS(Rankings!M:M, Rankings!$E:$E, $B25) -> 1 | F25: =MINIFS(Rankings!N:N, Rankings!$E:$E, $B25) -> 1 | G25: =MINIFS(Rankings!O:O, Rankings!$E:$E, $B25) -> 1 | H25: =MINIFS(Rankings!P:P, Rankings!$E:$E, $B25) -> 1 | I25: =MINIFS(Rankings!R:R, Rankings!$E:$E, $B25) -> 1 | J25: =MINIFS(Rankings!Q:Q, Rankings!$E:$E, $B25) -> 1
B26: =Rankings!$L$1 -> Parker | C26: =MINIFS(Rankings!K:K, Rankings!$E:$E, $B26) -> 1 | D26: =MINIFS(Rankings!L:L, Rankings!$E:$E, $B26) -> 1 | E26: =MINIFS(Rankings!M:M, Rankings!$E:$E, $B26) -> 1 | F26: =MINIFS(Rankings!N:N, Rankings!$E:$E, $B26) -> 1 | G26: =MINIFS(Rankings!O:O, Rankings!$E:$E, $B26) -> 1 | H26: =MINIFS(Rankings!P:P, Rankings!$E:$E, $B26) -> 1 | I26: =MINIFS(Rankings!R:R, Rankings!$E:$E, $B26) -> 1 | J26: =MINIFS(Rankings!Q:Q, Rankings!$E:$E, $B26) -> 1
B27: =Rankings!$M$1 -> Giacomo | C27: =MINIFS(Rankings!K:K, Rankings!$E:$E, $B27) -> 1 | D27: =MINIFS(Rankings!L:L, Rankings!$E:$E, $B27) -> 1 | E27: =MINIFS(Rankings!M:M, Rankings!$E:$E, $B27) -> 1 | F27: =MINIFS(Rankings!N:N, Rankings!$E:$E, $B27) -> 1 | G27: =MINIFS(Rankings!O:O, Rankings!$E:$E, $B27) -> 1 | H27: =MINIFS(Rankings!P:P, Rankings!$E:$E, $B27) -> 1 | I27: =MINIFS(Rankings!R:R, Rankings!$E:$E, $B27) -> 1 | J27: =MINIFS(Rankings!Q:Q, Rankings!$E:$E, $B27) -> 1
B28: =Rankings!$N$1 -> Rosey | C28: =MINIFS(Rankings!K:K, Rankings!$E:$E, $B28) -> 1 | D28: =MINIFS(Rankings!L:L, Rankings!$E:$E, $B28) -> 1 | E28: =MINIFS(Rankings!M:M, Rankings!$E:$E, $B28) -> 1 | F28: =MINIFS(Rankings!N:N, Rankings!$E:$E, $B28) -> 1 | G28: =MINIFS(Rankings!O:O, Rankings!$E:$E, $B28) -> 1 | H28: =MINIFS(Rankings!P:P, Rankings!$E:$E, $B28) -> 1 | I28: =MINIFS(Rankings!R:R, Rankings!$E:$E, $B28) -> 1 | J28: =MINIFS(Rankings!Q:Q, Rankings!$E:$E, $B28) -> 1
B29: =Rankings!$O$1 -> TTAC | C29: =MINIFS(Rankings!K:K, Rankings!$E:$E, $B29) -> 1 | D29: =MINIFS(Rankings!L:L, Rankings!$E:$E, $B29) -> 1 | E29: =MINIFS(Rankings!M:M, Rankings!$E:$E, $B29) -> 1 | F29: =MINIFS(Rankings!N:N, Rankings!$E:$E, $B29) -> 1 | G29: =MINIFS(Rankings!O:O, Rankings!$E:$E, $B29) -> 1 | H29: =MINIFS(Rankings!P:P, Rankings!$E:$E, $B29) -> 1 | I29: =MINIFS(Rankings!R:R, Rankings!$E:$E, $B29) -> 1 | J29: =MINIFS(Rankings!Q:Q, Rankings!$E:$E, $B29) -> 1
B30: =Rankings!$P$1 -> Weston | C30: =MINIFS(Rankings!K:K, Rankings!$E:$E, $B30) -> 1 | D30: =MINIFS(Rankings!L:L, Rankings!$E:$E, $B30) -> 1 | E30: =MINIFS(Rankings!M:M, Rankings!$E:$E, $B30) -> 1 | F30: =MINIFS(Rankings!N:N, Rankings!$E:$E, $B30) -> 1 | G30: =MINIFS(Rankings!O:O, Rankings!$E:$E, $B30) -> 1 | H30: =MINIFS(Rankings!P:P, Rankings!$E:$E, $B30) -> 1 | I30: =MINIFS(Rankings!R:R, Rankings!$E:$E, $B30) -> 1 | J30: =MINIFS(Rankings!Q:Q, Rankings!$E:$E, $B30) -> 1
B31: =Rankings!$R$1 -> Jake | C31: =MINIFS(Rankings!K:K, Rankings!$E:$E, $B31) -> 1 | D31: =MINIFS(Rankings!L:L, Rankings!$E:$E, $B31) -> 1 | E31: =MINIFS(Rankings!M:M, Rankings!$E:$E, $B31) -> 1 | F31: =MINIFS(Rankings!N:N, Rankings!$E:$E, $B31) -> 1 | G31: =MINIFS(Rankings!O:O, Rankings!$E:$E, $B31) -> 1 | H31: =MINIFS(Rankings!P:P, Rankings!$E:$E, $B31) -> 1 | I31: =MINIFS(Rankings!R:R, Rankings!$E:$E, $B31) -> 1 | J31: N/A
B32: =Rankings!$Q$1 -> Flocco | C32: =MINIFS(Rankings!K:K, Rankings!$E:$E, $B32) -> 1 | D32: =MINIFS(Rankings!L:L, Rankings!$E:$E, $B32) -> 1 | E32: =MINIFS(Rankings!M:M, Rankings!$E:$E, $B32) -> 1 | F32: =MINIFS(Rankings!N:N, Rankings!$E:$E, $B32) -> 1 | G32: =MINIFS(Rankings!O:O, Rankings!$E:$E, $B32) -> 1 | H32: =MINIFS(Rankings!P:P, Rankings!$E:$E, $B32) -> 1 | I32: N/A | J32: =MINIFS(Rankings!Q:Q, Rankings!$E:$E, $B32) -> 1
B34: Worst Rank
B35: Poster/Voter | C35: =Rankings!$K$1 -> Logan | D35: =Rankings!$L$1 -> Parker | E35: =Rankings!$M$1 -> Giacomo | F35: =Rankings!$N$1 -> Rosey | G35: =Rankings!$O$1 -> TTAC | H35: =Rankings!$P$1 -> Weston | I35: =Rankings!$R$1 -> Jake | J35: =Rankings!$Q$1 -> Flocco
B36: =Rankings!$K$1 -> Logan | C36: =MAXIFS(Rankings!K:K, Rankings!$E:$E, $B36) -> 7 | D36: =MAXIFS(Rankings!L:L, Rankings!$E:$E, $B36) -> 7 | E36: =MAXIFS(Rankings!M:M, Rankings!$E:$E, $B36) -> 7 | F36: =MAXIFS(Rankings!N:N, Rankings!$E:$E, $B36) -> 7 | G36: =MAXIFS(Rankings!O:O, Rankings!$E:$E, $B36) -> 7 | H36: =MAXIFS(Rankings!P:P, Rankings!$E:$E, $B36) -> 7 | I36: =MAXIFS(Rankings!R:R, Rankings!$E:$E, $B36) -> 7 | J36: =MAXIFS(Rankings!Q:Q, Rankings!$E:$E, $B36) -> 7
B37: =Rankings!$L$1 -> Parker | C37: =MAXIFS(Rankings!K:K, Rankings!$E:$E, $B37) -> 7 | D37: =MAXIFS(Rankings!L:L, Rankings!$E:$E, $B37) -> 5 | E37: =MAXIFS(Rankings!M:M, Rankings!$E:$E, $B37) -> 7 | F37: =MAXIFS(Rankings!N:N, Rankings!$E:$E, $B37) -> 7 | G37: =MAXIFS(Rankings!O:O, Rankings!$E:$E, $B37) -> 7 | H37: =MAXIFS(Rankings!P:P, Rankings!$E:$E, $B37) -> 7 | I37: =MAXIFS(Rankings!R:R, Rankings!$E:$E, $B37) -> 7 | J37: =MAXIFS(Rankings!Q:Q, Rankings!$E:$E, $B37) -> 7
B38: =Rankings!$M$1 -> Giacomo | C38: =MAXIFS(Rankings!K:K, Rankings!$E:$E, $B38) -> 7 | D38: =MAXIFS(Rankings!L:L, Rankings!$E:$E, $B38) -> 7 | E38: =MAXIFS(Rankings!M:M, Rankings!$E:$E, $B38) -> 6 | F38: =MAXIFS(Rankings!N:N, Rankings!$E:$E, $B38) -> 7 | G38: =MAXIFS(Rankings!O:O, Rankings!$E:$E, $B38) -> 7 | H38: =MAXIFS(Rankings!P:P, Rankings!$E:$E, $B38) -> 7 | I38: =MAXIFS(Rankings!R:R, Rankings!$E:$E, $B38) -> 7 | J38: =MAXIFS(Rankings!Q:Q, Rankings!$E:$E, $B38) -> 7
B39: =Rankings!$N$1 -> Rosey | C39: =MAXIFS(Rankings!K:K, Rankings!$E:$E, $B39) -> 7 | D39: =MAXIFS(Rankings!L:L, Rankings!$E:$E, $B39) -> 7 | E39: =MAXIFS(Rankings!M:M, Rankings!$E:$E, $B39) -> 7 | F39: =MAXIFS(Rankings!N:N, Rankings!$E:$E, $B39) -> 6 | G39: =MAXIFS(Rankings!O:O, Rankings!$E:$E, $B39) -> 7 | H39: =MAXIFS(Rankings!P:P, Rankings!$E:$E, $B39) -> 7 | I39: =MAXIFS(Rankings!R:R, Rankings!$E:$E, $B39) -> 7 | J39: =MAXIFS(Rankings!Q:Q, Rankings!$E:$E, $B39) -> 7
B40: =Rankings!$O$1 -> TTAC | C40: =MAXIFS(Rankings!K:K, Rankings!$E:$E, $B40) -> 7 | D40: =MAXIFS(Rankings!L:L, Rankings!$E:$E, $B40) -> 7 | E40: =MAXIFS(Rankings!M:M, Rankings!$E:$E, $B40) -> 7 | F40: =MAXIFS(Rankings!N:N, Rankings!$E:$E, $B40) -> 7 | G40: =MAXIFS(Rankings!O:O, Rankings!$E:$E, $B40) -> 7 | H40: =MAXIFS(Rankings!P:P, Rankings!$E:$E, $B40) -> 7 | I40: =MAXIFS(Rankings!R:R, Rankings!$E:$E, $B40) -> 7 | J40: =MAXIFS(Rankings!Q:Q, Rankings!$E:$E, $B40) -> 7
B41: =Rankings!$P$1 -> Weston | C41: =MAXIFS(Rankings!K:K, Rankings!$E:$E, $B41) -> 7 | D41: =MAXIFS(Rankings!L:L, Rankings!$E:$E, $B41) -> 7 | E41: =MAXIFS(Rankings!M:M, Rankings!$E:$E, $B41) -> 7 | F41: =MAXIFS(Rankings!N:N, Rankings!$E:$E, $B41) -> 7 | G41: =MAXIFS(Rankings!O:O, Rankings!$E:$E, $B41) -> 7 | H41: =MAXIFS(Rankings!P:P, Rankings!$E:$E, $B41) -> 7 | I41: =MAXIFS(Rankings!R:R, Rankings!$E:$E, $B41) -> 7 | J41: =MAXIFS(Rankings!Q:Q, Rankings!$E:$E, $B41) -> 7
B42: =Rankings!$R$1 -> Jake | C42: =MAXIFS(Rankings!K:K, Rankings!$E:$E, $B42) -> 7 | D42: =MAXIFS(Rankings!L:L, Rankings!$E:$E, $B42) -> 7 | E42: =MAXIFS(Rankings!M:M, Rankings!$E:$E, $B42) -> 7 | F42: =MAXIFS(Rankings!N:N, Rankings!$E:$E, $B42) -> 7 | G42: =MAXIFS(Rankings!O:O, Rankings!$E:$E, $B42) -> 7 | H42: =MAXIFS(Rankings!P:P, Rankings!$E:$E, $B42) -> 7 | I42: =MAXIFS(Rankings!R:R, Rankings!$E:$E, $B42) -> 5 | J42: N/A
B43: =Rankings!$Q$1 -> Flocco | C43: =MAXIFS(Rankings!K:K, Rankings!$E:$E, $B43) -> 7 | D43: =MAXIFS(Rankings!L:L, Rankings!$E:$E, $B43) -> 7 | E43: =MAXIFS(Rankings!M:M, Rankings!$E:$E, $B43) -> 7 | F43: =MAXIFS(Rankings!N:N, Rankings!$E:$E, $B43) -> 7 | G43: =MAXIFS(Rankings!O:O, Rankings!$E:$E, $B43) -> 7 | H43: =MAXIFS(Rankings!P:P, Rankings!$E:$E, $B43) -> 7 | I43: N/A | J43: =MAXIFS(Rankings!Q:Q, Rankings!$E:$E, $B43) -> 7
B45: Hall of Fame | K45: Hall of Shame | S45: Hall of Same | AA45: Clown Award
B46: Date | C46: Poster | D46: Average | E46: STDEV | F46: Peer Rank | G46: Song Title | H46: Song Artist | K46: Date | L46: Poster | M46: Average | N46: STDEV | O46: Peer Rank | P46: Song Title | Q46: Song Artist | S46: Date | T46: Poster | U46: Average | V46: STDEV | W46: Peer Rank | X46: Song Title | Y46: Song Artist | AA46: Date | AB46: Poster | AC46: Average | AD46: STDEV | AE46: Peer Rank | AF46: Song Title | AG46: Song Artist
B47: =IFERROR(__xludf.DUMMYFUNCTION("FILTER(Rankings!D:J, Rankings!F:F = MIN(Rankings!F:F))"),45919.0) -> 45919 | C47: =IFERROR(__xludf.DUMMYFUNCTION("""COMPUTED_VALUE"""),"Rosey") -> Rosey | D47: =IFERROR(__xludf.DUMMYFUNCTION("""COMPUTED_VALUE"""),1.0) -> 1 | E47: =IFERROR(__xludf.DUMMYFUNCTION("""COMPUTED_VALUE"""),0.0) -> 0 | F47: =IFERROR(__xludf.DUMMYFUNCTION("""COMPUTED_VALUE"""),1.0) -> 1 | G47: =IFERROR(__xludf.DUMMYFUNCTION("""COMPUTED_VALUE"""),"TEMPTATION") -> TEMPTATION | H47: =IFERROR(__xludf.DUMMYFUNCTION("""COMPUTED_VALUE"""),"Joey Bada$$") -> Joey Bada$$ | K47: =IFERROR(__xludf.DUMMYFUNCTION("FILTER(Rankings!D:J, Rankings!F:F = MAX(Rankings!F:F))"),45933.0) -> 45933 | L47: =IFERROR(__xludf.DUMMYFUNCTION("""COMPUTED_VALUE"""),"TTAC") -> TTAC | M47: =IFERROR(__xludf.DUMMYFUNCTION("""COMPUTED_VALUE"""),7.0) -> 7 | N47: =IFERROR(__xludf.DUMMYFUNCTION("""COMPUTED_VALUE"""),0.0) -> 0 | O47: =IFERROR(__xludf.DUMMYFUNCTION("""COMPUTED_VALUE"""),7.0) -> 7 | P47: =IFERROR(__xludf.DUMMYFUNCTION("""COMPUTED_VALUE"""),"Still Woman Enough (feat. Reba McEntire & Carrie Underwood") -> Still Woman Enough (feat. Reba McEntire & Carrie Underwood | Q47: =IFERROR(__xludf.DUMMYFUNCTION("""COMPUTED_VALUE"""),"Loretta Lynn, Reba McEntire, Carrie Underwood") -> Loretta Lynn, Reba McEntire, Carrie Underwood | S47: =IFERROR(__xludf.DUMMYFUNCTION("FILTER(Rankings!D:J, Rankings!F:F <> 1,Rankings!F:F <>7, Rankings!G:G = 0)"),"") | U47: =IFERROR(__xludf.DUMMYFUNCTION("""COMPUTED_VALUE"""),"#NeverForget #Kirk") -> #NeverForget #Kirk | AA47: =IFERROR(__xludf.DUMMYFUNCTION("FILTER(Rankings!D:J, (Rankings!F:F = MAX(Rankings!H:H)*(Rankings!F:F<7)))"),"#N/A") -> #N/A
B48: =IFERROR(__xludf.DUMMYFUNCTION("""COMPUTED_VALUE"""),46220.0) -> 46220 | C48: =IFERROR(__xludf.DUMMYFUNCTION("""COMPUTED_VALUE"""),"Giacomo") -> Giacomo | D48: =IFERROR(__xludf.DUMMYFUNCTION("""COMPUTED_VALUE"""),1.0) -> 1 | E48: =IFERROR(__xludf.DUMMYFUNCTION("""COMPUTED_VALUE"""),0.0) -> 0 | F48: =IFERROR(__xludf.DUMMYFUNCTION("""COMPUTED_VALUE"""),1.0) -> 1 | G48: =IFERROR(__xludf.DUMMYFUNCTION("""COMPUTED_VALUE"""),"TELEPATHY LOVE") -> TELEPATHY LOVE | H48: =IFERROR(__xludf.DUMMYFUNCTION("""COMPUTED_VALUE"""),"BNYX®, Clara La San") -> BNYX®, Clara La San | K48: =IFERROR(__xludf.DUMMYFUNCTION("""COMPUTED_VALUE"""),46015.0) -> 46015 | L48: =IFERROR(__xludf.DUMMYFUNCTION("""COMPUTED_VALUE"""),"Weston") -> Weston | M48: =IFERROR(__xludf.DUMMYFUNCTION("""COMPUTED_VALUE"""),7.0) -> 7 | N48: =IFERROR(__xludf.DUMMYFUNCTION("""COMPUTED_VALUE"""),0.0) -> 0 | O48: =IFERROR(__xludf.DUMMYFUNCTION("""COMPUTED_VALUE"""),7.0) -> 7 | P48: =IFERROR(__xludf.DUMMYFUNCTION("""COMPUTED_VALUE"""),"Santa Diss Track") -> Santa Diss Track | Q48: =IFERROR(__xludf.DUMMYFUNCTION("""COMPUTED_VALUE"""),"Logan Paul") -> Logan Paul
S54: =IFERROR(__xludf.DUMMYFUNCTION("""COMPUTED_VALUE"""),46307.0) -> 46307 | T54: =IFERROR(__xludf.DUMMYFUNCTION("""COMPUTED_VALUE"""),"Giacomo") -> Giacomo | U54: =IFERROR(__xludf.DUMMYFUNCTION("""COMPUTED_VALUE"""),5.0) -> 5 | V54: =IFERROR(__xludf.DUMMYFUNCTION("""COMPUTED_VALUE"""),0.0) -> 0 | W54: =IFERROR(__xludf.DUMMYFUNCTION("""COMPUTED_VALUE"""),5.0) -> 5 | X54: =IFERROR(__xludf.DUMMYFUNCTION("""COMPUTED_VALUE"""),"Dance Cracka") -> Dance Cracka | Y54: =IFERROR(__xludf.DUMMYFUNCTION("""COMPUTED_VALUE"""),"1900Rugrat, BLP KOSHER") -> 1900Rugrat, BLP KOSHER

Sheet Themes
B1: Up for Vote Themes | D1: Voters | K1: Results | M1: Poster | N1: Theme Pool | P1: Picked | Q1: Date | R1: Winning Song | S1: Winner
A2: Proponent | B2: Theme Suggestion | C2: Theme Description (Optional) | D2: Logan | E2: Parker | F2: Giacomo | G2: Rosey | H2: TTAC | I2: Weston | J2: Jake / Flocco | M2: =IFERROR(__xludf.DUMMYFUNCTION("FILTER($A:$C,$K:$K = ""Passed"")"),"Logan") -> Logan | N2: =IFERROR(__xludf.DUMMYFUNCTION("""COMPUTED_VALUE"""),"Bad Bitch Era") -> Bad Bitch Era | O2: =IFERROR(__xludf.DUMMYFUNCTION("""COMPUTED_VALUE"""),"A song that makes you feel like a bad bitch") -> A song that makes you feel like a bad bitch | P2: Yes | Q2: 46101 | R2: B.I.T.C.H. | S2: Rosey
A3: Logan | B3: Bad Bitch Era | C3: A song that makes you feel like a bad bitch | E3: In Favor | F3: In Favor | G3: In Favor | H3: In Favor | I3: In Favor | K3: =IF(COUNTIF(D3:J3, "Opposed") >=3,"Failed", IF(COUNTIF(D3:J3, "In Favor") >=4, "Passed", "")) -> Passed | M3: =IFERROR(__xludf.DUMMYFUNCTION("""COMPUTED_VALUE"""),"Parker") -> Parker | N3: =IFERROR(__xludf.DUMMYFUNCTION("""COMPUTED_VALUE"""),"Murdered/Murdered Someone") -> Murdered/Murdered Someone | P3: Yes | Q3: 46115 | R3: Perfect Ten | S3: Parker
A4: Parker | B4: Murdered/Murdered Someone | D4: In Favor | F4: In Favor | G4: In Favor | H4: In Favor | I4: In Favor | K4: =IF(COUNTIF(D4:J4, "Opposed") >=3,"Failed", IF(COUNTIF(D4:J4, "In Favor") >=4, "Passed", "")) -> Passed | M4: =IFERROR(__xludf.DUMMYFUNCTION("""COMPUTED_VALUE"""),"Giacomo") -> Giacomo | N4: =IFERROR(__xludf.DUMMYFUNCTION("""COMPUTED_VALUE"""),"Bechdel Test") -> Bechdel Test | O4: =IFERROR(__xludf.DUMMYFUNCTION("""COMPUTED_VALUE"""),"Has to pass it") -> Has to pass it | P4: Yes | Q4: 45933 | R4: All The Things She Said | S4: Rosey
A5: Giacomo | B5: Bechdel Test | C5: Has to pass it | D5: In Favor | E5: In Favor | F5: In Favor | G5: In Favor | H5: In Favor | I5: In Favor | J5: In Favor | K5: =IF(COUNTIF(D5:J5, "Opposed") >=3,"Failed", IF(COUNTIF(D5:J5, "In Favor") >=4, "Passed", "")) -> Passed | M5: =IFERROR(__xludf.DUMMYFUNCTION("""COMPUTED_VALUE"""),"Rosey") -> Rosey | N5: =IFERROR(__xludf.DUMMYFUNCTION("""COMPUTED_VALUE"""),"Sad Boy Hours") -> Sad Boy Hours | P5: Yes | Q5: 46073 | R5: Y LLORO | S5: Parker
A6: Rosey | B6: Sad Boy Hours | D6: In Favor | E6: In Favor | F6: In Favor | H6: In Favor | I6: In Favor | K6: =IF(COUNTIF(D6:J6, "Opposed") >=3,"Failed", IF(COUNTIF(D6:J6, "In Favor") >=4, "Passed", "")) -> Passed | M6: =IFERROR(__xludf.DUMMYFUNCTION("""COMPUTED_VALUE"""),"TTAC") -> TTAC | N6: =IFERROR(__xludf.DUMMYFUNCTION("""COMPUTED_VALUE"""),"Music Videos") -> Music Videos | O6: =IFERROR(__xludf.DUMMYFUNCTION("""COMPUTED_VALUE"""),"The music vid can take apart as the score or as separate, but it has to atleast be a song where the video adds to the experience or is iconic in one way or another ") -> The music vid can take apart as the score or as separate, but it has to atleast be a song where the video adds to the experience or is iconic in one way or another
A7: TTAC | B7: Music Videos | C7: The music vid can take apart as the score or as separate, but it has to atleast be a song where the video adds to the experience or is iconic in one way or another | D7: In Favor | E7: In Favor | F7: In Favor | G7: In Favor | I7: In Favor | K7: =IF(COUNTIF(D7:J7, "Opposed") >=3,"Failed", IF(COUNTIF(D7:J7, "In Favor") >=4, "Passed", "")) -> Passed | M7: =IFERROR(__xludf.DUMMYFUNCTION("""COMPUTED_VALUE"""),"Weston") -> Weston | N7: =IFERROR(__xludf.DUMMYFUNCTION("""COMPUTED_VALUE"""),"Quickscope montage") -> Quickscope montage | O7: =IFERROR(__xludf.DUMMYFUNCTION("""COMPUTED_VALUE"""),"Any song from a cod/cs/val edit") -> Any song from a cod/cs/val edit
A8: Weston | B8: Quickscope montage | C8: Any song from a cod/cs/val edit | D8: In Favor | E8: In Favor | F8: Opposed | G8: In Favor | H8: In Favor | J8: Opposed | K8: =IF(COUNTIF(D8:J8, "Opposed") >=3,"Failed", IF(COUNTIF(D8:J8, "In Favor") >=4, "Passed", "")) -> Passed | M8: =IFERROR(__xludf.DUMMYFUNCTION("""COMPUTED_VALUE"""),"Jake") -> Jake | N8: =IFERROR(__xludf.DUMMYFUNCTION("""COMPUTED_VALUE"""),"Famous Song in a Movie") -> Famous Song in a Movie | P8: Yes | Q8: 46059 | R8: I2I | S8: Weston
A9: Jake | B9: Famous Song in a Movie | D9: In Favor | E9: In Favor | F9: Opposed | G9: In Favor | H9: In Favor | I9: In Favor | J9: In Favor | K9: =IF(COUNTIF(D9:J9, "Opposed") >=3,"Failed", IF(COUNTIF(D9:J9, "In Favor") >=4, "Passed", "")) -> Passed | M9: =IFERROR(__xludf.DUMMYFUNCTION("""COMPUTED_VALUE"""),"Giacomo") -> Giacomo | N9: =IFERROR(__xludf.DUMMYFUNCTION("""COMPUTED_VALUE"""),"Horny") -> Horny | O9: =IFERROR(__xludf.DUMMYFUNCTION("""COMPUTED_VALUE"""),"Some freaky ahh shit that gon make you act up") -> Some freaky ahh shit that gon make you act up
A10: Logan | B10: Speed Round | C10: Song that's less than 1 minute | E10: Opposed | F10: Opposed | G10: Opposed | H10: In Favor | I10: In Favor | J10: In Favor | K10: =IF(COUNTIF(D10:J10, "Opposed") >=3,"Failed", IF(COUNTIF(D10:J10, "In Favor") >=4, "Passed", "")) -> Failed | M10: =IFERROR(__xludf.DUMMYFUNCTION("""COMPUTED_VALUE"""),"Rosey") -> Rosey | N10: =IFERROR(__xludf.DUMMYFUNCTION("""COMPUTED_VALUE"""),"XXL Freshman") -> XXL Freshman | P10: Yes | Q10: 46003 | R10: RNP | S10: Rosey
A11: Giacomo | B11: Horny | C11: Some freaky ahh shit that gon make you act up | D11: In Favor | E11: In Favor | H11: In Favor | I11: In Favor | J11: In Favor | K11: =IF(COUNTIF(D11:J11, "Opposed") >=3,"Failed", IF(COUNTIF(D11:J11, "In Favor") >=4, "Passed", "")) -> Passed | M11: =IFERROR(__xludf.DUMMYFUNCTION("""COMPUTED_VALUE"""),"TTAC") -> TTAC | N11: =IFERROR(__xludf.DUMMYFUNCTION("""COMPUTED_VALUE"""),"X-Mas Songs") -> X-Mas Songs | O11: =IFERROR(__xludf.DUMMYFUNCTION("""COMPUTED_VALUE"""),"Sometime in DEC") -> Sometime in DEC | P11: Yes | Q11: 46015 | R11: Last Christmas | S11: Rosey
A12: Rosey | B12: XXL Freshman | D12: In Favor | E12: In Favor | F12: In Favor | H12: In Favor | I12: In Favor | J12: In Favor | K12: =IF(COUNTIF(D12:J12, "Opposed") >=3,"Failed", IF(COUNTIF(D12:J12, "In Favor") >=4, "Passed", "")) -> Passed | M12: =IFERROR(__xludf.DUMMYFUNCTION("""COMPUTED_VALUE"""),"Jake") -> Jake | N12: =IFERROR(__xludf.DUMMYFUNCTION("""COMPUTED_VALUE"""),"Spooky/Scary Songs") -> Spooky/Scary Songs | P12: Yes | Q12: 45961 | R12: Lavender Town | S12: Logan
A13: TTAC | B13: X-Mas Songs | C13: Sometime in DEC | D13: In Favor | E13: In Favor | F13: In Favor | H13: In Favor | I13: In Favor | J13: Opposed | K13: =IF(COUNTIF(D13:J13, "Opposed") >=3,"Failed", IF(COUNTIF(D13:J13, "In Favor") >=4, "Passed", "")) -> Passed | M13: =IFERROR(__xludf.DUMMYFUNCTION("""COMPUTED_VALUE"""),"Logan") -> Logan | N13: =IFERROR(__xludf.DUMMYFUNCTION("""COMPUTED_VALUE"""),"Receiptify Top Artist") -> Receiptify Top Artist | O13: =IFERROR(__xludf.DUMMYFUNCTION("""COMPUTED_VALUE"""),"https://receiptify.herokuapp.com - Use this link to see your Top Artist at the time - 6 Months") -> https://receiptify.herokuapp.com - Use this link to see your Top Artist at the time - 6 Months
A14: Weston | B14: 27 club | C14: died at 27 years old | D14: In Favor | E14: Opposed | F14: Opposed | G14: Opposed | H14: In Favor | J14: In Favor | K14: =IF(COUNTIF(D14:J14, "Opposed") >=3,"Failed", IF(COUNTIF(D14:J14, "In Favor") >=4, "Passed", "")) -> Failed | M14: =IFERROR(__xludf.DUMMYFUNCTION("""COMPUTED_VALUE"""),"Giacomo") -> Giacomo | N14: =IFERROR(__xludf.DUMMYFUNCTION("""COMPUTED_VALUE"""),"Wrapped Song") -> Wrapped Song | O14: =IFERROR(__xludf.DUMMYFUNCTION("""COMPUTED_VALUE"""),"Pick a top 5 song from any of your wrapped") -> Pick a top 5 song from any of your wrapped
A15: Jake | B15: Spooky/Scary Songs | D15: In Favor | E15: In Favor | F15: In Favor | G15: In Favor | H15: In Favor | I15: In Favor | K15: =IF(COUNTIF(D15:J15, "Opposed") >=3,"Failed", IF(COUNTIF(D15:J15, "In Favor") >=4, "Passed", "")) -> Passed | M15: =IFERROR(__xludf.DUMMYFUNCTION("""COMPUTED_VALUE"""),"TTAC") -> TTAC | N15: =IFERROR(__xludf.DUMMYFUNCTION("""COMPUTED_VALUE"""),"Video Game OST") -> Video Game OST | P15: Yes | Q15: 45947 | R15: Unshaken | S15: Parker
A16: Logan | B16: Receiptify Top Artist | C16: https://receiptify.herokuapp.com - Use this link to see your Top Artist at the time - 6 Months | E16: In Favor | F16: Opposed | G16: In Favor | H16: In Favor | I16: In Favor | K16: =IF(COUNTIF(D16:J16, "Opposed") >=3,"Failed", IF(COUNTIF(D16:J16, "In Favor") >=4, "Passed", "")) -> Passed | M16: =IFERROR(__xludf.DUMMYFUNCTION("""COMPUTED_VALUE"""),"Weston") -> Weston | N16: =IFERROR(__xludf.DUMMYFUNCTION("""COMPUTED_VALUE"""),"Haters") -> Haters | O16: =IFERROR(__xludf.DUMMYFUNCTION("""COMPUTED_VALUE"""),"Diss tracks or songs that were made to spite someone/something") -> Diss tracks or songs that were made to spite someone/something | P16: Yes | Q16: 45975 | R16: HISS | S16: Logan
A17: Giacomo | B17: Wrapped Song | C17: Pick a top 5 song from any of your wrapped | D17: In Favor | E17: In Favor | G17: In Favor | H17: In Favor | I17: In Favor | K17: =IF(COUNTIF(D17:J17, "Opposed") >=3,"Failed", IF(COUNTIF(D17:J17, "In Favor") >=4, "Passed", "")) -> Passed | M17: =IFERROR(__xludf.DUMMYFUNCTION("""COMPUTED_VALUE"""),"Jake") -> Jake | N17: =IFERROR(__xludf.DUMMYFUNCTION("""COMPUTED_VALUE"""),"Secret Missions") -> Secret Missions | O17: =IFERROR(__xludf.DUMMYFUNCTION("""COMPUTED_VALUE"""),"Each person is assigned another theme at random and in secret and you have to pick a song for your secret theme. People can also guess at what other peoples secret theme was. ") -> Each person is assigned another theme at random and in secret and you have to pick a song for your secret theme. People can also guess at what other peoples secret theme was.
A18: TTAC | B18: Video Game OST | D18: In Favor | E18: In Favor | F18: Opposed | G18: In Favor | H18: In Favor | I18: In Favor | J18: In Favor | K18: =IF(COUNTIF(D18:J18, "Opposed") >=3,"Failed", IF(COUNTIF(D18:J18, "In Favor") >=4, "Passed", "")) -> Passed | M18: =IFERROR(__xludf.DUMMYFUNCTION("""COMPUTED_VALUE"""),"Logan") -> Logan | N18: =IFERROR(__xludf.DUMMYFUNCTION("""COMPUTED_VALUE"""),"Guilty Pleasure") -> Guilty Pleasure | O18: =IFERROR(__xludf.DUMMYFUNCTION("""COMPUTED_VALUE"""),"A song you are embaressed to like") -> A song you are embaressed to like | P18: Yes | Q18: 46241 | R18: Agora Hills | S18: Parker
A19: Weston | B19: Haters | C19: Diss tracks or songs that were made to spite someone/something | D19: In Favor | E19: In Favor | F19: In Favor | H19: In Favor | K19: =IF(COUNTIF(D19:J19, "Opposed") >=3,"Failed", IF(COUNTIF(D19:J19, "In Favor") >=4, "Passed", "")) -> Passed | M19: =IFERROR(__xludf.DUMMYFUNCTION("""COMPUTED_VALUE"""),"Giacomo") -> Giacomo | N19: =IFERROR(__xludf.DUMMYFUNCTION("""COMPUTED_VALUE"""),"The Ink Master") -> The Ink Master | O19: =IFERROR(__xludf.DUMMYFUNCTION("""COMPUTED_VALUE"""),"The winner of the flash challenge (last theme) has the power to assign the skulls (genre or topic) in the elimination tattoo (this theme)") -> The winner of the flash challenge (last theme) has the power to assign the skulls (genre or topic) in the elimination tattoo (this theme) | P19: Yes | Q19: 46045 | R19: Time | S19: Rosey
A20: Jake | B20: Secret Missions | C20: Each person is assigned another theme at random and in secret and you have to pick a song for your secret theme. People can also guess at what other peoples secret theme was. | D20: In Favor | E20: In Favor | F20: Opposed | H20: In Favor | I20: In Favor | K20: =IF(COUNTIF(D20:J20, "Opposed") >=3,"Failed", IF(COUNTIF(D20:J20, "In Favor") >=4, "Passed", "")) -> Passed | M20: =IFERROR(__xludf.DUMMYFUNCTION("""COMPUTED_VALUE"""),"Weston") -> Weston | N20: =IFERROR(__xludf.DUMMYFUNCTION("""COMPUTED_VALUE"""),"Local") -> Local | O20: =IFERROR(__xludf.DUMMYFUNCTION("""COMPUTED_VALUE"""),"Any Artist/band from NJ or Philly") -> Any Artist/band from NJ or Philly | P20: Yes | Q20: 45989 | R20: The Seed (2.0) | S20: Rosey
A21: Logan | B21: Guilty Pleasure | C21: A song you are embaressed to like | E21: In Favor | F21: In Favor | G21: In Favor | H21: In Favor | I21: In Favor | K21: =IF(COUNTIF(D21:J21, "Opposed") >=3,"Failed", IF(COUNTIF(D21:J21, "In Favor") >=4, "Passed", "")) -> Passed | M21: =IFERROR(__xludf.DUMMYFUNCTION("""COMPUTED_VALUE"""),"Jake") -> Jake | N21: =IFERROR(__xludf.DUMMYFUNCTION("""COMPUTED_VALUE"""),"Weeb Song") -> Weeb Song | O21: =IFERROR(__xludf.DUMMYFUNCTION("""COMPUTED_VALUE"""),"A Japanese song, doesn't need to be anime related") -> A Japanese song, doesn't need to be anime related | P21: Yes | Q21: 46255
A22: Giacomo | B22: The Ink Master | C22: The winner of the flash challenge (last theme) has the power to assign the skulls (genre or topic) in the elimination tattoo (this theme) | D22: In Favor | E22: In Favor | H22: In Favor | I22: In Favor | K22: =IF(COUNTIF(D22:J22, "Opposed") >=3,"Failed", IF(COUNTIF(D22:J22, "In Favor") >=4, "Passed", "")) -> Passed | M22: =IFERROR(__xludf.DUMMYFUNCTION("""COMPUTED_VALUE"""),"Logan") -> Logan | N22: =IFERROR(__xludf.DUMMYFUNCTION("""COMPUTED_VALUE"""),"Instruments only") -> Instruments only | O22: =IFERROR(__xludf.DUMMYFUNCTION("""COMPUTED_VALUE"""),"No EDM") -> No EDM | P22: Yes | Q22: 46199 | R22: Face My Fears | S22: Weston
A23: TTAC | B23: Genre Medley | C23: Everyone is assigned a person and they have to pick a genre of music for that person to oblige by | D23: Opposed | E23: Opposed | F23: In Favor | G23: Opposed | H23: In Favor | I23: Opposed | K23: =IF(COUNTIF(D23:J23, "Opposed") >=3,"Failed", IF(COUNTIF(D23:J23, "In Favor") >=4, "Passed", "")) -> Failed | M23: =IFERROR(__xludf.DUMMYFUNCTION("""COMPUTED_VALUE"""),"Weston") -> Weston | N23: =IFERROR(__xludf.DUMMYFUNCTION("""COMPUTED_VALUE"""),"Beat Switch") -> Beat Switch | O23: =IFERROR(__xludf.DUMMYFUNCTION("""COMPUTED_VALUE"""),"Songs with a beat switch in there") -> Songs with a beat switch in there
A24: Weston | B24: Local | C24: Any Artist/band from NJ or Philly | D24: In Favor | E24: In Favor | F24: In Favor | H24: In Favor | K24: =IF(COUNTIF(D24:J24, "Opposed") >=3,"Failed", IF(COUNTIF(D24:J24, "In Favor") >=4, "Passed", "")) -> Passed | M24: =IFERROR(__xludf.DUMMYFUNCTION("""COMPUTED_VALUE"""),"Jake") -> Jake | N24: =IFERROR(__xludf.DUMMYFUNCTION("""COMPUTED_VALUE"""),"Songs that make you want to drive 100 mph") -> Songs that make you want to drive 100 mph | O24: =IFERROR(__xludf.DUMMYFUNCTION("""COMPUTED_VALUE"""),"These are songs that make you wanna go fast!") -> These are songs that make you wanna go fast! | P24: Yes | Q24: 46213 | R24: COWBELL WARRIORS! | S24: Logan
A25: Jake | B25: Weeb Song | C25: A Japanese song, doesn't need to be anime related | D25: In Favor | E25: Opposed | F25: In Favor | G25: In Favor | H25: In Favor | I25: In Favor | K25: =IF(COUNTIF(D25:J25, "Opposed") >=3,"Failed", IF(COUNTIF(D25:J25, "In Favor") >=4, "Passed", "")) -> Passed | M25: =IFERROR(__xludf.DUMMYFUNCTION("""COMPUTED_VALUE"""),"Logan") -> Logan | N25: =IFERROR(__xludf.DUMMYFUNCTION("""COMPUTED_VALUE"""),"Hammock Vibes") -> Hammock Vibes | O25: =IFERROR(__xludf.DUMMYFUNCTION("""COMPUTED_VALUE"""),"Chill vibes of just relaxing") -> Chill vibes of just relaxing | P25: Yes | Q25: 46143 | R25: Red Red Wine | S25: Flocco
A26: Logan | B26: Instruments only | C26: No EDM | E26: Opposed | F26: Opposed | G26: In Favor | H26: In Favor | I26: In Favor | J26: In Favor | K26: =IF(COUNTIF(D26:J26, "Opposed") >=3,"Failed", IF(COUNTIF(D26:J26, "In Favor") >=4, "Passed", "")) -> Passed | M26: =IFERROR(__xludf.DUMMYFUNCTION("""COMPUTED_VALUE"""),"Parker") -> Parker | N26: =IFERROR(__xludf.DUMMYFUNCTION("""COMPUTED_VALUE"""),"GeoGuessr") -> GeoGuessr | O26: =IFERROR(__xludf.DUMMYFUNCTION("""COMPUTED_VALUE"""),"1-2 Games of Geoguessr and whatever countries you get right, artist has to be from/origin") -> 1-2 Games of Geoguessr and whatever countries you get right, artist has to be from/origin | P26: Yes | Q26: 46171 | R26: Jog Pra Lua | S26: Parker
A27: TTAC | B27: Top Song of Wrapped | C27: When spotify wrapped drops, play your number 1 played song of the year | D27: In Favor | E27: Opposed | F27: Opposed | G27: Opposed | H27: In Favor | I27: In Favor | K27: =IF(COUNTIF(D27:J27, "Opposed") >=3,"Failed", IF(COUNTIF(D27:J27, "In Favor") >=4, "Passed", "")) -> Failed | M27: =IFERROR(__xludf.DUMMYFUNCTION("""COMPUTED_VALUE"""),"Rosey") -> Rosey | N27: =IFERROR(__xludf.DUMMYFUNCTION("""COMPUTED_VALUE"""),"Theme Graveyard") -> Theme Graveyard | O27: =IFERROR(__xludf.DUMMYFUNCTION("""COMPUTED_VALUE"""),"A Theme is randomly selected out of the themes which were already done (Probably best to wait a bit on this one)") -> A Theme is randomly selected out of the themes which were already done (Probably best to wait a bit on this one)
A28: Weston | B28: Beat Switch | C28: Songs with a beat switch in there | D28: In Favor | E28: In Favor | F28: In Favor | H28: In Favor | K28: =IF(COUNTIF(D28:J28, "Opposed") >=3,"Failed", IF(COUNTIF(D28:J28, "In Favor") >=4, "Passed", "")) -> Passed | M28: =IFERROR(__xludf.DUMMYFUNCTION("""COMPUTED_VALUE"""),"Rosey") -> Rosey | N28: =IFERROR(__xludf.DUMMYFUNCTION("""COMPUTED_VALUE"""),"Good Head Songs") -> Good Head Songs | O28: =IFERROR(__xludf.DUMMYFUNCTION("""COMPUTED_VALUE"""),"")
A29: Jake | B29: Unique Sound | C29: Songs that don't sound like anything else | D29: In Favor | E29: Opposed | F29: Opposed | G29: Opposed | H29: In Favor | I29: In Favor | K29: =IF(COUNTIF(D29:J29, "Opposed") >=3,"Failed", IF(COUNTIF(D29:J29, "In Favor") >=4, "Passed", "")) -> Failed | M29: =IFERROR(__xludf.DUMMYFUNCTION("""COMPUTED_VALUE"""),"Jake") -> Jake | N29: =IFERROR(__xludf.DUMMYFUNCTION("""COMPUTED_VALUE"""),"Summer Songs") -> Summer Songs | O29: =IFERROR(__xludf.DUMMYFUNCTION("""COMPUTED_VALUE"""),"Songs that remind you of Summer") -> Songs that remind you of Summer | P29: Yes | Q29: 45666 | R29: Who Dat Girl | S29: Rosey
A30: Logan | B30: Skin Color | C30: Choose a song that when you listen to it and you go look at the artist picture, they do not match the voice. | E30: In Favor | F30: Opposed | G30: Opposed | H30: In Favor | I30: Opposed | K30: =IF(COUNTIF(D30:J30, "Opposed") >=3,"Failed", IF(COUNTIF(D30:J30, "In Favor") >=4, "Passed", "")) -> Failed | M30: =IFERROR(__xludf.DUMMYFUNCTION("""COMPUTED_VALUE"""),"Jake") -> Jake | N30: =IFERROR(__xludf.DUMMYFUNCTION("""COMPUTED_VALUE"""),"Winter Songs") -> Winter Songs | O30: =IFERROR(__xludf.DUMMYFUNCTION("""COMPUTED_VALUE"""),"Songs that give you that Winter feeling") -> Songs that give you that Winter feeling
A31: Weston | B31: Side projects | C31: When a band member creates a 2nd band or an artist creates an alias | D31: In Favor | E31: Opposed | F31: In Favor | G31: Opposed | H31: In Favor | J31: Opposed | K31: =IF(COUNTIF(D31:J31, "Opposed") >=3,"Failed", IF(COUNTIF(D31:J31, "In Favor") >=4, "Passed", "")) -> Failed | M31: =IFERROR(__xludf.DUMMYFUNCTION("""COMPUTED_VALUE"""),"Jake") -> Jake | N31: =IFERROR(__xludf.DUMMYFUNCTION("""COMPUTED_VALUE"""),"Bizarre Adventure") -> Bizarre Adventure | O31: =IFERROR(__xludf.DUMMYFUNCTION("""COMPUTED_VALUE"""),"Songs or Bands must share a name with a Stand, Character or Musical Reference from Jojo's Bizarre Adventure (No Part 8 or 9 References)") -> Songs or Bands must share a name with a Stand, Character or Musical Reference from Jojo's Bizarre Adventure (No Part 8 or 9 References)
A32: Jake | B32: Songs that make you want to drive 100 mph | C32: These are songs that make you wanna go fast! | D32: In Favor | E32: In Favor | F32: In Favor | H32: In Favor | I32: In Favor | K32: =IF(COUNTIF(D32:J32, "Opposed") >=3,"Failed", IF(COUNTIF(D32:J32, "In Favor") >=4, "Passed", "")) -> Passed | M32: =IFERROR(__xludf.DUMMYFUNCTION("""COMPUTED_VALUE"""),"Weston") -> Weston | N32: =IFERROR(__xludf.DUMMYFUNCTION("""COMPUTED_VALUE"""),"Carried") -> Carried | O32: =IFERROR(__xludf.DUMMYFUNCTION("""COMPUTED_VALUE"""),"Songs where the feature outshines the main artist") -> Songs where the feature outshines the main artist
A33: Logan | B33: Hammock Vibes | C33: Chill vibes of just relaxing | E33: In Favor | H33: In Favor | I33: In Favor | J33: In Favor | K33: =IF(COUNTIF(D33:J33, "Opposed") >=3,"Failed", IF(COUNTIF(D33:J33, "In Favor") >=4, "Passed", "")) -> Passed | M33: =IFERROR(__xludf.DUMMYFUNCTION("""COMPUTED_VALUE"""),"Weston") -> Weston | N33: =IFERROR(__xludf.DUMMYFUNCTION("""COMPUTED_VALUE"""),"Ayo?") -> Ayo? | O33: =IFERROR(__xludf.DUMMYFUNCTION("""COMPUTED_VALUE"""),"Songs that are completely normal but have a weird bar thrown in there that makes you go ayo pause") -> Songs that are completely normal but have a weird bar thrown in there that makes you go ayo pause
A34: Parker | B34: GeoGuessr | C34: 1-2 Games of Geoguessr and whatever countries you get right, artist has to be from/origin | D34: In Favor | F34: In Favor | G34: In Favor | H34: In Favor | I34: In Favor | J34: In Favor | K34: =IF(COUNTIF(D34:J34, "Opposed") >=3,"Failed", IF(COUNTIF(D34:J34, "In Favor") >=4, "Passed", "")) -> Passed | M34: =IFERROR(__xludf.DUMMYFUNCTION("""COMPUTED_VALUE"""),"Giacomo") -> Giacomo | N34: =IFERROR(__xludf.DUMMYFUNCTION("""COMPUTED_VALUE"""),"Easy Read") -> Easy Read | O34: =IFERROR(__xludf.DUMMYFUNCTION("""COMPUTED_VALUE"""),"Each person selects someone else, who the song is meant to impress, in secret (same person can be selected multiple times). First criteria for the win is the ranking your target gives the song, the standard group ranking will be the tiebraker.") -> Each person selects someone else, who the song is meant to impress, in secret (same person can be selected multiple times). First criteria for the win is the ranking your target gives the song, the standard group ranking will be the tiebraker. | P34: Yes | Q34: 46227 | R34: Ignorance | S34: TTAC
A35: Rosey | B35: Theme Graveyard | C35: A Theme is randomly selected out of the themes which were already done (Probably best to wait a bit on this one) | D35: In Favor | E35: Opposed | F35: In Favor | H35: In Favor | I35: Opposed | J35: In Favor | K35: =IF(COUNTIF(D35:J35, "Opposed") >=3,"Failed", IF(COUNTIF(D35:J35, "In Favor") >=4, "Passed", "")) -> Passed | M35: =IFERROR(__xludf.DUMMYFUNCTION("""COMPUTED_VALUE"""),"Parker") -> Parker | N35: =IFERROR(__xludf.DUMMYFUNCTION("""COMPUTED_VALUE"""),"Song Thats Named After a Person") -> Song Thats Named After a Person
A36: Rosey | B36: Good Head Songs | D36: In Favor | E36: In Favor | F36: In Favor | H36: In Favor | I36: In Favor | J36: In Favor | K36: =IF(COUNTIF(D36:J36, "Opposed") >=3,"Failed", IF(COUNTIF(D36:J36, "In Favor") >=4, "Passed", "")) -> Passed | M36: =IFERROR(__xludf.DUMMYFUNCTION("""COMPUTED_VALUE"""),"Giacomo") -> Giacomo | N36: =IFERROR(__xludf.DUMMYFUNCTION("""COMPUTED_VALUE"""),"Mutually Assured Destruction") -> Mutually Assured Destruction | O36: =IFERROR(__xludf.DUMMYFUNCTION("""COMPUTED_VALUE"""),"Everyone posts a nuke") -> Everyone posts a nuke
A37: TTAC | B37: Whips | C37: Song named after a car or a mode of transportation | D37: In Favor | E37: Opposed | F37: Opposed | G37: Opposed | H37: In Favor | I37: In Favor | J37: Opposed | K37: =IF(COUNTIF(D37:J37, "Opposed") >=3,"Failed", IF(COUNTIF(D37:J37, "In Favor") >=4, "Passed", "")) -> Failed | M37: =IFERROR(__xludf.DUMMYFUNCTION("""COMPUTED_VALUE"""),"TTAC") -> TTAC | N37: =IFERROR(__xludf.DUMMYFUNCTION("""COMPUTED_VALUE"""),"Sports Game Soundtrack") -> Sports Game Soundtrack | O37: =IFERROR(__xludf.DUMMYFUNCTION("""COMPUTED_VALUE"""),"A song that is featured on a sports game soundtrack, Fifa, madden, Tony Hawk, ect.") -> A song that is featured on a sports game soundtrack, Fifa, madden, Tony Hawk, ect. | P37: Yes | Q37: 46157 | R37: Stare At The Sun | S37: Weston
A38: Jake | B38: Vehicles | C38: Songs named after vehicles | D38: In Favor | E38: In Favor | F38: Opposed | G38: In Favor | H38: Opposed | I38: Opposed | J38: In Favor | K38: =IF(COUNTIF(D38:J38, "Opposed") >=3,"Failed", IF(COUNTIF(D38:J38, "In Favor") >=4, "Passed", "")) -> Failed | M38: =IFERROR(__xludf.DUMMYFUNCTION("""COMPUTED_VALUE"""),"Logan") -> Logan | N38: =IFERROR(__xludf.DUMMYFUNCTION("""COMPUTED_VALUE"""),"Two Hit Wonder?") -> Two Hit Wonder? | O38: =IFERROR(__xludf.DUMMYFUNCTION("""COMPUTED_VALUE"""),"song by an artist that's considered a one hit wonder but it can't be their known song") -> song by an artist that's considered a one hit wonder but it can't be their known song
A39: Jake | B39: Summer Songs | C39: Songs that remind you of Summer | D39: In Favor | E39: In Favor | F39: In Favor | G39: In Favor | H39: In Favor | I39: In Favor | K39: =IF(COUNTIF(D39:J39, "Opposed") >=3,"Failed", IF(COUNTIF(D39:J39, "In Favor") >=4, "Passed", "")) -> Passed | M39: =IFERROR(__xludf.DUMMYFUNCTION("""COMPUTED_VALUE"""),"TTAC") -> TTAC | N39: =IFERROR(__xludf.DUMMYFUNCTION("""COMPUTED_VALUE"""),"Live Music") -> Live Music | O39: =IFERROR(__xludf.DUMMYFUNCTION("""COMPUTED_VALUE"""),"Must have seen this song performed live at a concert by the artist") -> Must have seen this song performed live at a concert by the artist
A40: Jake | B40: Winter Songs | C40: Songs that give you that Winter feeling | D40: In Favor | E40: In Favor | F40: In Favor | G40: In Favor | H40: In Favor | I40: In Favor | K40: =IF(COUNTIF(D40:J40, "Opposed") >=3,"Failed", IF(COUNTIF(D40:J40, "In Favor") >=4, "Passed", "")) -> Passed | M40: =IFERROR(__xludf.DUMMYFUNCTION("""COMPUTED_VALUE"""),"Parker") -> Parker | N40: =IFERROR(__xludf.DUMMYFUNCTION("""COMPUTED_VALUE"""),"Straight Outta the Vagina") -> Straight Outta the Vagina | O40: =IFERROR(__xludf.DUMMYFUNCTION("""COMPUTED_VALUE"""),"Top 25 Charting Songs on the day you were born") -> Top 25 Charting Songs on the day you were born | P40: Yes | Q40: 46185 | R40: All The Small Things | S40: Flocco
A41: Jake | B41: TTAC Song | C41: Post a song that TTAC would post and get auto 7'd for | D41: In Favor | E41: Opposed | F41: In Favor | G41: Opposed | H41: Opposed | I41: Opposed | K41: =IF(COUNTIF(D41:J41, "Opposed") >=3,"Failed", IF(COUNTIF(D41:J41, "In Favor") >=4, "Passed", "")) -> Failed | M41: =IFERROR(__xludf.DUMMYFUNCTION("""COMPUTED_VALUE"""),"Rosey") -> Rosey | N41: =IFERROR(__xludf.DUMMYFUNCTION("""COMPUTED_VALUE"""),"2000s") -> 2000s
A42: Jake | B42: Bizarre Adventure | C42: Songs or Bands must share a name with a Stand, Character or Musical Reference from Jojo's Bizarre Adventure (No Part 8 or 9 References) | D42: In Favor | E42: In Favor | F42: Opposed | G42: In Favor | H42: In Favor | I42: In Favor | K42: =IF(COUNTIF(D42:J42, "Opposed") >=3,"Failed", IF(COUNTIF(D42:J42, "In Favor") >=4, "Passed", "")) -> Passed | M42: =IFERROR(__xludf.DUMMYFUNCTION("""COMPUTED_VALUE"""),"Rosey") -> Rosey | N42: =IFERROR(__xludf.DUMMYFUNCTION("""COMPUTED_VALUE"""),"Songs we blasting dropping into WW3") -> Songs we blasting dropping into WW3
A43: Weston | B43: Carried | C43: Songs where the feature outshines the main artist | D43: In Favor | E43: In Favor | F43: In Favor | H43: In Favor | K43: =IF(COUNTIF(D43:J43, "Opposed") >=3,"Failed", IF(COUNTIF(D43:J43, "In Favor") >=4, "Passed", "")) -> Passed | M43: =IFERROR(__xludf.DUMMYFUNCTION("""COMPUTED_VALUE"""),"Giacomo") -> Giacomo | N43: =IFERROR(__xludf.DUMMYFUNCTION("""COMPUTED_VALUE"""),"Ragebait TTAC Day") -> Ragebait TTAC Day | O43: =IFERROR(__xludf.DUMMYFUNCTION("""COMPUTED_VALUE"""),"""What's this newfangled horse-hockey?""") -> "What's this newfangled horse-hockey?" | P43: Yes | Q43: 46129 | R43: Meat | S43: Parker
A44: Jake | B44: Hidden Messages | C44: Songs that contain a hidden message via something like morse code or needing to play in reverse | D44: Opposed | E44: Opposed | F44: In Favor | H44: In Favor | I44: Opposed | K44: =IF(COUNTIF(D44:J44, "Opposed") >=3,"Failed", IF(COUNTIF(D44:J44, "In Favor") >=4, "Passed", "")) -> Failed | M44: =IFERROR(__xludf.DUMMYFUNCTION("""COMPUTED_VALUE"""),"Jake / Flocco") -> Jake / Flocco | N44: =IFERROR(__xludf.DUMMYFUNCTION("""COMPUTED_VALUE"""),"Copy cat") -> Copy cat | O44: =IFERROR(__xludf.DUMMYFUNCTION("""COMPUTED_VALUE"""),"Cover that's better than the original song") -> Cover that's better than the original song | P44: Yes | Q44: 46269
A45: Weston | B45: Ayo? | C45: Songs that are completely normal but have a weird bar thrown in there that makes you go ayo pause | D45: In Favor | E45: In Favor | F45: In Favor | H45: In Favor | K45: =IF(COUNTIF(D45:J45, "Opposed") >=3,"Failed", IF(COUNTIF(D45:J45, "In Favor") >=4, "Passed", "")) -> Passed | M45: =IFERROR(__xludf.DUMMYFUNCTION("""COMPUTED_VALUE"""),"Parker") -> Parker | N45: =IFERROR(__xludf.DUMMYFUNCTION("""COMPUTED_VALUE"""),"Walkout Song ") -> Walkout Song | O45: =IFERROR(__xludf.DUMMYFUNCTION("""COMPUTED_VALUE"""),"An Athlete/Team Who Walks out to this song. (Baseball Player, MMA Fighter, Super Bowl Walkout Song") -> An Athlete/Team Who Walks out to this song. (Baseball Player, MMA Fighter, Super Bowl Walkout Song
A46: Giacomo | B46: Easy Read | C46: Each person selects someone else, who the song is meant to impress, in secret (same person can be selected multiple times). First criteria for the win is the ranking your target gives the song, the standard group ranking will be the tiebraker. | D46: In Favor | E46: In Favor | H46: In Favor | I46: In Favor | K46: =IF(COUNTIF(D46:J46, "Opposed") >=3,"Failed", IF(COUNTIF(D46:J46, "In Favor") >=4, "Passed", "")) -> Passed | M46: =IFERROR(__xludf.DUMMYFUNCTION("""COMPUTED_VALUE"""),"Giacomo") -> Giacomo | N46: =IFERROR(__xludf.DUMMYFUNCTION("""COMPUTED_VALUE"""),"Obamna") -> Obamna | O46: =IFERROR(__xludf.DUMMYFUNCTION("""COMPUTED_VALUE"""),"Pick a song from any Obama summer playlist") -> Pick a song from any Obama summer playlist
A47: Logan | B47: Feature Flop | C47: Song where the feature ruins the song | E47: Opposed | F47: Opposed | G47: Opposed | H47: In Favor | I47: In Favor | J47: In Favor | K47: =IF(COUNTIF(D47:J47, "Opposed") >=3,"Failed", IF(COUNTIF(D47:J47, "In Favor") >=4, "Passed", "")) -> Failed | M47: =IFERROR(__xludf.DUMMYFUNCTION("""COMPUTED_VALUE"""),"Jake / Flocco") -> Jake / Flocco | N47: =IFERROR(__xludf.DUMMYFUNCTION("""COMPUTED_VALUE"""),"Same same same") -> Same same same | O47: =IFERROR(__xludf.DUMMYFUNCTION("""COMPUTED_VALUE"""),"Band, album, and song title all share the same name") -> Band, album, and song title all share the same name
A48: Parker | B48: Song Thats Named After a Person | D48: In Favor | F48: In Favor | H48: In Favor | I48: In Favor | J48: Needs Explanation | K48: =IF(COUNTIF(D48:J48, "Opposed") >=3,"Failed", IF(COUNTIF(D48:J48, "In Favor") >=4, "Passed", "")) -> Passed | M48: =IFERROR(__xludf.DUMMYFUNCTION("""COMPUTED_VALUE"""),"Weston") -> Weston | N48: =IFERROR(__xludf.DUMMYFUNCTION("""COMPUTED_VALUE"""),"Löded Diper Setlist") -> Löded Diper Setlist | O48: =IFERROR(__xludf.DUMMYFUNCTION("""COMPUTED_VALUE"""),"Pick a song that Rodrick and the band would cover") -> Pick a song that Rodrick and the band would cover
A49: Giacomo | B49: Mutually Assured Destruction | C49: Everyone posts a nuke | D49: In Favor | E49: In Favor | G49: In Favor | H49: In Favor | I49: In Favor | K49: =IF(COUNTIF(D49:J49, "Opposed") >=3,"Failed", IF(COUNTIF(D49:J49, "In Favor") >=4, "Passed", "")) -> Passed | M49: =IFERROR(__xludf.DUMMYFUNCTION("""COMPUTED_VALUE"""),"Jake / Flocco") -> Jake / Flocco | N49: =IFERROR(__xludf.DUMMYFUNCTION("""COMPUTED_VALUE"""),"That's me!") -> That's me! | O49: =IFERROR(__xludf.DUMMYFUNCTION("""COMPUTED_VALUE"""),"The artist's name must match your own") -> The artist's name must match your own
A50: TTAC | B50: Hey, I know that Guy! | C50: Must know someone who is credited in the song, produce, wrote, is in the band, ect. Can be "friends of a friend" link too if you dont know anyone directly | D50: Opposed | E50: Opposed | F50: Opposed | G50: Opposed | H50: In Favor | I50: Opposed | J50: Opposed | K50: =IF(COUNTIF(D50:J50, "Opposed") >=3,"Failed", IF(COUNTIF(D50:J50, "In Favor") >=4, "Passed", "")) -> Failed
A51: Weston | B51: Tony Hawk Pro Skater 2025 | C51: Post a song you think would be in a modern THPS soundtrack (2016-now) | D51: In Favor | E51: Opposed | F51: Opposed | G51: Opposed | H51: In Favor | K51: =IF(COUNTIF(D51:J51, "Opposed") >=3,"Failed", IF(COUNTIF(D51:J51, "In Favor") >=4, "Passed", "")) -> Failed
A52: TTAC | B52: Sports Game Soundtrack | C52: A song that is featured on a sports game soundtrack, Fifa, madden, Tony Hawk, ect. | D52: In Favor | E52: In Favor | F52: In Favor | G52: In Favor | H52: In Favor | I52: In Favor | K52: =IF(COUNTIF(D52:J52, "Opposed") >=3,"Failed", IF(COUNTIF(D52:J52, "In Favor") >=4, "Passed", "")) -> Passed
A53: Logan | B53: Two Hit Wonder? | C53: song by an artist that's considered a one hit wonder but it can't be their known song | E53: In Favor | F53: In Favor | G53: In Favor | H53: In Favor | I53: In Favor | K53: =IF(COUNTIF(D53:J53, "Opposed") >=3,"Failed", IF(COUNTIF(D53:J53, "In Favor") >=4, "Passed", "")) -> Passed
A54: TTAC | B54: Live Music | C54: Must have seen this song performed live at a concert by the artist | D54: In Favor | E54: In Favor | F54: In Favor | G54: Opposed | H54: In Favor | I54: In Favor | J54: In Favor | K54: =IF(COUNTIF(D54:J54, "Opposed") >=3,"Failed", IF(COUNTIF(D54:J54, "In Favor") >=4, "Passed", "")) -> Passed
A55: Weston | B55: Pot of Greed | C55: Pot of Greed is a magic card (theme) that lets you draw 2 cards (songs) from the top of your deck (main playlist/ liked songs on shuffle). You may put one of the two drawn cards (songs) onto the field (group playlist) and end your turn | E55: Opposed | F55: In Favor | G55: Opposed | H55: Opposed | J55: In Favor | K55: =IF(COUNTIF(D55:J55, "Opposed") >=3,"Failed", IF(COUNTIF(D55:J55, "In Favor") >=4, "Passed", "")) -> Failed
A56: Parker | B56: Straight Outta the Vagina | C56: Top 25 Charting Songs on the day you were born | D56: In Favor | F56: In Favor | G56: In Favor | H56: In Favor | I56: In Favor | J56: In Favor | K56: =IF(COUNTIF(D56:J56, "Opposed") >=3,"Failed", IF(COUNTIF(D56:J56, "In Favor") >=4, "Passed", "")) -> Passed
A57: Jake | B57: Combo Breaker | C57: Choose a song that fits as many themes as possible | E57: Opposed | F57: Opposed | G57: Opposed | H57: Opposed | I57: Opposed | J57: Opposed | K57: =IF(COUNTIF(D57:J57, "Opposed") >=3,"Failed", IF(COUNTIF(D57:J57, "In Favor") >=4, "Passed", "")) -> Failed
A58: Rosey | B58: 2000s | D58: In Favor | E58: In Favor | F58: In Favor | H58: In Favor | I58: In Favor | J58: In Favor | K58: =IF(COUNTIF(D58:J58, "Opposed") >=3,"Failed", IF(COUNTIF(D58:J58, "In Favor") >=4, "Passed", "")) -> Passed
A59: Rosey | B59: Songs we blasting dropping into WW3 | D59: In Favor | E59: In Favor | F59: In Favor | H59: In Favor | I59: In Favor | J59: In Favor | K59: =IF(COUNTIF(D59:J59, "Opposed") >=3,"Failed", IF(COUNTIF(D59:J59, "In Favor") >=4, "Passed", "")) -> Passed
A60: Giacomo | B60: Ragebait TTAC Day | C60: "What's this newfangled horse-hockey?" | D60: In Favor | E60: In Favor | G60: In Favor | H60: In Favor | I60: In Favor | J60: Opposed | K60: =IF(COUNTIF(D60:J60, "Opposed") >=3,"Failed", IF(COUNTIF(D60:J60, "In Favor") >=4, "Passed", "")) -> Passed
A61: Jake / Flocco | B61: Copy cat | C61: Cover that's better than the original song | D61: In Favor | E61: In Favor | F61: In Favor | H61: In Favor | I61: In Favor | K61: =IF(COUNTIF(D61:J61, "Opposed") >=3,"Failed", IF(COUNTIF(D61:J61, "In Favor") >=4, "Passed", "")) -> Passed
A62: Parker | B62: Walkout Song | C62: An Athlete/Team Who Walks out to this song. (Baseball Player, MMA Fighter, Super Bowl Walkout Song | D62: In Favor | F62: In Favor | H62: In Favor | I62: In Favor | J62: In Favor | K62: =IF(COUNTIF(D62:J62, "Opposed") >=3,"Failed", IF(COUNTIF(D62:J62, "In Favor") >=4, "Passed", "")) -> Passed
A63: Giacomo | B63: Obamna | C63: Pick a song from any Obama summer playlist | D63: In Favor | E63: In Favor | H63: In Favor | I63: In Favor | J63: In Favor | K63: =IF(COUNTIF(D63:J63, "Opposed") >=3,"Failed", IF(COUNTIF(D63:J63, "In Favor") >=4, "Passed", "")) -> Passed
A64: Jake / Flocco | B64: Same same same | C64: Band, album, and song title all share the same name | D64: In Favor | E64: In Favor | F64: Opposed | H64: In Favor | I64: In Favor | K64: =IF(COUNTIF(D64:J64, "Opposed") >=3,"Failed", IF(COUNTIF(D64:J64, "In Favor") >=4, "Passed", "")) -> Passed
A65: TTAC | B65: Mid Off | C65: Most Mid "4" OAT | D65: Opposed | E65: Opposed | F65: Opposed | H65: In Favor | I65: In Favor | J65: In Favor
A66: TTAC | B66: Shit Off | C66: TTAC type shit, 7s only | D66: In Favor | E66: Opposed | F66: Opposed | H66: In Favor | I66: In Favor | J66: Opposed | K66: =IF(COUNTIF(D66:J66, "Opposed") >=3,"Failed", IF(COUNTIF(D66:J66, "In Favor") >=4, "Passed", "")) -> Failed
A67: Jake / Flocco | B67: Dinner and a show | C67: Best music video wins | D67: Opposed | F67: Opposed | J67: In favor
A68: Parker | B68: Odd Collab | C68: A feature/producer collab that is the polar opposite of eachother/wouldnt expect a collab | D68: In Favor | F68: In Favor | H68: In Favor | I68: In Favor | J68: Opposed
A69: Weston | B69: Ohhhhh yeah | C69: Pick a song that we've definitely heard but probably forgot about | D69: In Favor | F69: In Favor | H69: In Favor | J69: In Favor
A70: Giacomo | B70: Evil Easy Read | C70: Same rules as Easy Read, but looking for a low rating from target | D70: In Favor | H70: In Favor | I70: In Favor | J70: Opposed | K70: =IF(COUNTIF(D70:J70, "Opposed") >=3,"Failed", IF(COUNTIF(D70:J70, "In Favor") >=4, "Passed", ""))
A71: Weston | B71: Löded Diper Setlist | C71: Pick a song that Rodrick and the band would cover | D71: Opposed | E71: In Favor | F71: In Favor | H71: In Favor | J71: In Favor | K71: =IF(COUNTIF(D71:J71, "Opposed") >=3,"Failed", IF(COUNTIF(D71:J71, "In Favor") >=4, "Passed", "")) -> Passed
A72: Jake / Flocco | B72: That's me! | C72: The artist's name must match your own | D72: In Favor | E72: In Favor | F72: Opposed | H72: In Favor | I72: In Favor | K72: =IF(COUNTIF(D72:J72, "Opposed") >=3,"Failed", IF(COUNTIF(D72:J72, "In Favor") >=4, "Passed", "")) -> Passed
A73: Giacomo | B73: Gaslight, Girlboss, Slay | C73: Songs about cheating, gaslighting, adultery, lying, promiscuity, etc. | I73: In Favor | K73: =IF(COUNTIF(D73:J73, "Opposed") >=3,"Failed", IF(COUNTIF(D73:J73, "In Favor") >=4, "Passed", ""))
K74: =IF(COUNTIF(D74:J74, "Opposed") >=3,"Failed", IF(COUNTIF(D74:J74, "In Favor") >=4, "Passed", ""))
K75: =IF(COUNTIF(D75:J75, "Opposed") >=3,"Failed", IF(COUNTIF(D75:J75, "In Favor") >=4, "Passed", ""))
K76: =IF(COUNTIF(D76:J76, "Opposed") >=3,"Failed", IF(COUNTIF(D76:J76, "In Favor") >=4, "Passed", ""))
K77: =IF(COUNTIF(D77:J77, "Opposed") >=3,"Failed", IF(COUNTIF(D77:J77, "In Favor") >=4, "Passed", ""))

Sheet 2026 Song of the Month
A1: January | V1: Seeding | W1: Date | X1: Poster | Y1: Average | Z1: STDEV | AA1: Peer Rank | AB1: Song | AC1: Artist
A2: Description | B2: L | C2: P | D2: G | E2: R | F2: T | G2: W | H2: F | I2: Song 1 | J2: Score 1 | K2: Winner | L2: Score 2 | M2: Song 2 | N2: F | O2: W | P2: T | Q2: R | R2: G | S2: P | T2: L | V2: 8 | W2: =IFERROR(__xludf.DUMMYFUNCTION("FILTER(Rankings!D:J, Rankings!D:D >= DATE(2026,1,1), Rankings!D:D < DATE(2026,2,1), Rankings!U:U = TRUE)"),46024.0) -> 46024 | X2: =IFERROR(__xludf.DUMMYFUNCTION("""COMPUTED_VALUE"""),"TTAC") -> TTAC | Y2: =IFERROR(__xludf.DUMMYFUNCTION("""COMPUTED_VALUE"""),2.6666666666666665) -> 2.6666667 | Z2: =IFERROR(__xludf.DUMMYFUNCTION("""COMPUTED_VALUE"""),1.247219128924647) -> 1.2472191 | AA2: =IFERROR(__xludf.DUMMYFUNCTION("""COMPUTED_VALUE"""),3.0) -> 3 | AB2: =IFERROR(__xludf.DUMMYFUNCTION("""COMPUTED_VALUE"""),"How to Get By") -> How to Get By | AC2: =IFERROR(__xludf.DUMMYFUNCTION("""COMPUTED_VALUE"""),"The Electric Sons") -> The Electric Sons
A3: Seed 1 vs 2 | B3: x | C3: x | D3: x | E3: X | I3: =K5 -> Please Be Rude | J3: =COUNTIF(B3:H3,"x") -> 4 | K3: =IF(J3>=4,I3,IF(L3>=4,M3,"TBD")) -> Please Be Rude | L3: =COUNTIF(N3:T3,"x") -> 3 | M3: =K4 -> So Cold | N3: X | O3: X | P3: X | V3: 5 | W3: =IFERROR(__xludf.DUMMYFUNCTION("""COMPUTED_VALUE"""),46027.0) -> 46027 | X3: =IFERROR(__xludf.DUMMYFUNCTION("""COMPUTED_VALUE"""),"TTAC") -> TTAC | Y3: =IFERROR(__xludf.DUMMYFUNCTION("""COMPUTED_VALUE"""),2.3333333333333335) -> 2.3333333 | Z3: =IFERROR(__xludf.DUMMYFUNCTION("""COMPUTED_VALUE"""),1.3743685418725535) -> 1.3743685 | AA3: =IFERROR(__xludf.DUMMYFUNCTION("""COMPUTED_VALUE"""),2.4) -> 2.4 | AB3: =IFERROR(__xludf.DUMMYFUNCTION("""COMPUTED_VALUE"""),"Stranger Than") -> Stranger Than | AC3: =IFERROR(__xludf.DUMMYFUNCTION("""COMPUTED_VALUE"""),"Coyote Theory") -> Coyote Theory
A4: Seed 2 vs 3 | B4: x | E4: X | G4: X | H4: X | I4: =K8 -> So Cold | J4: =COUNTIF(B4:H4,"x") -> 4 | K4: =IF(J4>=4,I4,IF(L4>=4,M4,"TBD")) -> So Cold | L4: =COUNTIF(N4:T4,"x") -> 3 | M4: =K7 -> Add Up My Love | P4: X | R4: x | S4: x | V4: 2 | W4: =IFERROR(__xludf.DUMMYFUNCTION("""COMPUTED_VALUE"""),46029.0) -> 46029 | X4: =IFERROR(__xludf.DUMMYFUNCTION("""COMPUTED_VALUE"""),"Logan") -> Logan | Y4: =IFERROR(__xludf.DUMMYFUNCTION("""COMPUTED_VALUE"""),1.6666666666666667) -> 1.6666667 | Z4: =IFERROR(__xludf.DUMMYFUNCTION("""COMPUTED_VALUE"""),0.7453559924999298) -> 0.74535599 | AA4: =IFERROR(__xludf.DUMMYFUNCTION("""COMPUTED_VALUE"""),1.8) -> 1.8 | AB4: =IFERROR(__xludf.DUMMYFUNCTION("""COMPUTED_VALUE"""),"Feel It (From ""Incincible""") -> Feel It (From "Incincible" | AC4: =IFERROR(__xludf.DUMMYFUNCTION("""COMPUTED_VALUE"""),"d4vd") -> d4vd
A5: Seed 1 vs 4 | C5: x | D5: x | E5: X | F5: X | G5: X | H5: X | I5: =K9 -> Please Be Rude | J5: =COUNTIF(B5:H5,"x") -> 6 | K5: =IF(J5>=4,I5,IF(L5>=4,M5,"TBD")) -> Please Be Rude | L5: =COUNTIF(N5:T5,"x") -> 1 | M5: =K6 -> BELLAKEO | T5: x | V5: 3 | W5: =IFERROR(__xludf.DUMMYFUNCTION("""COMPUTED_VALUE"""),46031.0) -> 46031 | X5: =IFERROR(__xludf.DUMMYFUNCTION("""COMPUTED_VALUE"""),"Rosey") -> Rosey | Y5: =IFERROR(__xludf.DUMMYFUNCTION("""COMPUTED_VALUE"""),1.8333333333333333) -> 1.8333333 | Z5: =IFERROR(__xludf.DUMMYFUNCTION("""COMPUTED_VALUE"""),1.0671873729054748) -> 1.0671874 | AA5: =IFERROR(__xludf.DUMMYFUNCTION("""COMPUTED_VALUE"""),2.0) -> 2 | AB5: =IFERROR(__xludf.DUMMYFUNCTION("""COMPUTED_VALUE"""),"Who Dat Girl (feat. Akon)") -> Who Dat Girl (feat. Akon) | AC5: =IFERROR(__xludf.DUMMYFUNCTION("""COMPUTED_VALUE"""),"Flo Rida, Akon") -> Flo Rida, Akon
A6: Seed 4 vs 5 | E6: X | F6: X | H6: X | I6: =K14 -> Time | J6: =COUNTIF(B6:H6,"x") -> 3 | K6: =IF(J6>=4,I6,IF(L6>=4,M6,"TBD")) -> BELLAKEO | L6: =COUNTIF(N6:T6,"x") -> 4 | M6: =K13 -> BELLAKEO | O6: X | R6: x | S6: x | T6: x | V6: 12 | W6: =IFERROR(__xludf.DUMMYFUNCTION("""COMPUTED_VALUE"""),46034.0) -> 46034 | X6: =IFERROR(__xludf.DUMMYFUNCTION("""COMPUTED_VALUE"""),"Parker") -> Parker | Y6: =IFERROR(__xludf.DUMMYFUNCTION("""COMPUTED_VALUE"""),3.0) -> 3 | Z6: =IFERROR(__xludf.DUMMYFUNCTION("""COMPUTED_VALUE"""),1.7320508075688772) -> 1.7320508 | AA6: =IFERROR(__xludf.DUMMYFUNCTION("""COMPUTED_VALUE"""),3.4) -> 3.4 | AB6: =IFERROR(__xludf.DUMMYFUNCTION("""COMPUTED_VALUE"""),"BELLAKEO") -> BELLAKEO | AC6: =IFERROR(__xludf.DUMMYFUNCTION("""COMPUTED_VALUE"""),"Peso Pluma, Anitta") -> Peso Pluma, Anitta
A7: Seed 3 vs 6 | B7: x | H7: X | I7: Who Dat Girl | J7: =COUNTIF(B7:H7,"x") -> 2 | K7: =IF(J7>=4,I7,IF(L7>=4,M7,"TBD")) -> Add Up My Love | L7: =COUNTIF(N7:T7,"x") -> 4 | M7: =K12 -> Add Up My Love | O7: X | P7: X | R7: x | S7: x | V7: 9 | W7: =IFERROR(__xludf.DUMMYFUNCTION("""COMPUTED_VALUE"""),46036.0) -> 46036 | X7: =IFERROR(__xludf.DUMMYFUNCTION("""COMPUTED_VALUE"""),"Logan") -> Logan | Y7: =IFERROR(__xludf.DUMMYFUNCTION("""COMPUTED_VALUE"""),2.6666666666666665) -> 2.6666667 | Z7: =IFERROR(__xludf.DUMMYFUNCTION("""COMPUTED_VALUE"""),1.247219128924647) -> 1.2472191 | AA7: =IFERROR(__xludf.DUMMYFUNCTION("""COMPUTED_VALUE"""),3.0) -> 3 | AB7: =IFERROR(__xludf.DUMMYFUNCTION("""COMPUTED_VALUE"""),"Demons (feat. Denzel Curry)") -> Demons (feat. Denzel Curry) | AC7: =IFERROR(__xludf.DUMMYFUNCTION("""COMPUTED_VALUE"""),"A$AP Ferg, Denzel Curry") -> A$AP Ferg, Denzel Curry
A8: Seed 2 vs 7 | B8: x | E8: X | G8: X | I8: Feel It | J8: =COUNTIF(B8:H8,"x") -> 3 | K8: =IF(J8>=4,I8,IF(L8>=4,M8,"TBD")) -> So Cold | L8: =COUNTIF(N8:T8,"x") -> 4 | M8: =K11 -> So Cold | N8: X | P8: X | R8: x | S8: x | V8: 10 | W8: =IFERROR(__xludf.DUMMYFUNCTION("""COMPUTED_VALUE"""),46038.0) -> 46038 | X8: =IFERROR(__xludf.DUMMYFUNCTION("""COMPUTED_VALUE"""),"Parker") -> Parker | Y8: =IFERROR(__xludf.DUMMYFUNCTION("""COMPUTED_VALUE"""),2.6666666666666665) -> 2.6666667 | Z8: =IFERROR(__xludf.DUMMYFUNCTION("""COMPUTED_VALUE"""),1.7950549357115013) -> 1.7950549 | AA8: =IFERROR(__xludf.DUMMYFUNCTION("""COMPUTED_VALUE"""),3.0) -> 3 | AB8: =IFERROR(__xludf.DUMMYFUNCTION("""COMPUTED_VALUE"""),"COQUETA") -> COQUETA | AC8: =IFERROR(__xludf.DUMMYFUNCTION("""COMPUTED_VALUE"""),"Fuerzo Regida, Grupo Frontera") -> Fuerzo Regida, Grupo Frontera
A9: Seed 1 vs 8 | C9: x | D9: x | F9: X | G9: X | I9: Please Be Rude | J9: =COUNTIF(B9:H9,"x") -> 4 | K9: =IF(J9>=4,I9,IF(L9>=4,M9,"TBD")) -> Please Be Rude | L9: =COUNTIF(N9:T9,"x") -> 2 | M9: =K10 -> Demons | N9: X | T9: x | V9: 1 | W9: =IFERROR(__xludf.DUMMYFUNCTION("""COMPUTED_VALUE"""),46041.0) -> 46041 | X9: =IFERROR(__xludf.DUMMYFUNCTION("""COMPUTED_VALUE"""),"Rosey") -> Rosey | Y9: =IFERROR(__xludf.DUMMYFUNCTION("""COMPUTED_VALUE"""),1.3333333333333333) -> 1.3333333 | Z9: =IFERROR(__xludf.DUMMYFUNCTION("""COMPUTED_VALUE"""),0.7453559924999299) -> 0.74535599 | AA9: =IFERROR(__xludf.DUMMYFUNCTION("""COMPUTED_VALUE"""),1.4) -> 1.4 | AB9: =IFERROR(__xludf.DUMMYFUNCTION("""COMPUTED_VALUE"""),"Please Be Rude") -> Please Be Rude | AC9: =IFERROR(__xludf.DUMMYFUNCTION("""COMPUTED_VALUE"""),"Gigi Perez") -> Gigi Perez
A10: Seed 8 vs 9 | F10: X | I10: How to Get By | J10: =COUNTIF(B10:H10,"x") -> 1 | K10: =IF(J10>=4,I10,IF(L10>=4,M10,"TBD")) -> Demons | L10: =COUNTIF(N10:T10,"x") -> 6 | M10: Demons | N10: X | O10: X | Q10: X | R10: x | S10: x | T10: x | V10: 6 | W10: =IFERROR(__xludf.DUMMYFUNCTION("""COMPUTED_VALUE"""),46043.0) -> 46043 | X10: =IFERROR(__xludf.DUMMYFUNCTION("""COMPUTED_VALUE"""),"Weston") -> Weston | Y10: =IFERROR(__xludf.DUMMYFUNCTION("""COMPUTED_VALUE"""),2.3333333333333335) -> 2.3333333 | Z10: =IFERROR(__xludf.DUMMYFUNCTION("""COMPUTED_VALUE"""),1.7950549357115015) -> 1.7950549 | AA10: =IFERROR(__xludf.DUMMYFUNCTION("""COMPUTED_VALUE"""),2.6) -> 2.6 | AB10: =IFERROR(__xludf.DUMMYFUNCTION("""COMPUTED_VALUE"""),"The Difference") -> The Difference | AC10: =IFERROR(__xludf.DUMMYFUNCTION("""COMPUTED_VALUE"""),"Flume, Toro y Moi") -> Flume, Toro y Moi
A11: Seed 7 vs 10 | B11: x | E11: X | F11: X | G11: X | H11: X | I11: So Cold | J11: =COUNTIF(B11:H11,"x") -> 5 | K11: =IF(J11>=4,I11,IF(L11>=4,M11,"TBD")) -> So Cold | L11: =COUNTIF(N11:T11,"x") -> 2 | M11: COQUETA | R11: x | S11: x | V11: 4 | W11: =IFERROR(__xludf.DUMMYFUNCTION("""COMPUTED_VALUE"""),46045.0) -> 46045 | X11: =IFERROR(__xludf.DUMMYFUNCTION("""COMPUTED_VALUE"""),"Rosey") -> Rosey | Y11: =IFERROR(__xludf.DUMMYFUNCTION("""COMPUTED_VALUE"""),2.0) -> 2 | Z11: =IFERROR(__xludf.DUMMYFUNCTION("""COMPUTED_VALUE"""),0.5773502691896257) -> 0.57735027 | AA11: =IFERROR(__xludf.DUMMYFUNCTION("""COMPUTED_VALUE"""),2.0) -> 2 | AB11: =IFERROR(__xludf.DUMMYFUNCTION("""COMPUTED_VALUE"""),"Time") -> Time | AC11: =IFERROR(__xludf.DUMMYFUNCTION("""COMPUTED_VALUE"""),"Hans Zimmer") -> Hans Zimmer
A12: Seed 6 vs 11 | B12: x | G12: X | I12: The Difference | J12: =COUNTIF(B12:H12,"x") -> 2 | K12: =IF(J12>=4,I12,IF(L12>=4,M12,"TBD")) -> Add Up My Love | L12: =COUNTIF(N12:T12,"x") -> 5 | M12: Add Up My Love | N12: X | P12: X | Q12: X | R12: x | S12: x | V12: 7 | W12: =IFERROR(__xludf.DUMMYFUNCTION("""COMPUTED_VALUE"""),46048.0) -> 46048 | X12: =IFERROR(__xludf.DUMMYFUNCTION("""COMPUTED_VALUE"""),"Flocco") -> Flocco | Y12: =IFERROR(__xludf.DUMMYFUNCTION("""COMPUTED_VALUE"""),2.4285714285714284) -> 2.4285714 | Z12: =IFERROR(__xludf.DUMMYFUNCTION("""COMPUTED_VALUE"""),1.6781914463529615) -> 1.6781914 | AA12: =IFERROR(__xludf.DUMMYFUNCTION("""COMPUTED_VALUE"""),2.6666666666666665) -> 2.6666667 | AB12: =IFERROR(__xludf.DUMMYFUNCTION("""COMPUTED_VALUE"""),"So Cold") -> So Cold | AC12: =IFERROR(__xludf.DUMMYFUNCTION("""COMPUTED_VALUE"""),"Balu Brigada") -> Balu Brigada
A13: Seed 5 vs 12 | F13: X | H13: X | I13: Stranger Than | J13: =COUNTIF(B13:H13,"x") -> 2 | K13: =IF(J13>=4,I13,IF(L13>=4,M13,"TBD")) -> BELLAKEO | L13: =COUNTIF(N13:T13,"x") -> 5 | M13: BELLAKEO | O13: X | Q13: X | R13: x | S13: x | T13: x | V13: 11 | W13: =IFERROR(__xludf.DUMMYFUNCTION("""COMPUTED_VALUE"""),46050.0) -> 46050 | X13: =IFERROR(__xludf.DUMMYFUNCTION("""COMPUTED_VALUE"""),"Parker") -> Parker | Y13: =IFERROR(__xludf.DUMMYFUNCTION("""COMPUTED_VALUE"""),2.857142857142857) -> 2.8571429 | Z13: =IFERROR(__xludf.DUMMYFUNCTION("""COMPUTED_VALUE"""),2.2314999074019015) -> 2.2314999 | AA13: =IFERROR(__xludf.DUMMYFUNCTION("""COMPUTED_VALUE"""),3.1666666666666665) -> 3.1666667 | AB13: =IFERROR(__xludf.DUMMYFUNCTION("""COMPUTED_VALUE"""),"Add Up My Love") -> Add Up My Love | AC13: =IFERROR(__xludf.DUMMYFUNCTION("""COMPUTED_VALUE"""),"Clairo") -> Clairo
A14: Seed 4 vs 13 | B14: x | C14: x | D14: x | E14: X | I14: Time | J14: =COUNTIF(B14:H14,"x") -> 4 | K14: =IF(J14>=4,I14,IF(L14>=4,M14,"TBD")) -> Time | L14: =COUNTIF(N14:T14,"x") -> 3 | M14: keep it in the dark | N14: X | O14: X | P14: X | V14: 13 | W14: =IFERROR(__xludf.DUMMYFUNCTION("""COMPUTED_VALUE"""),46052.0) -> 46052 | X14: =IFERROR(__xludf.DUMMYFUNCTION("""COMPUTED_VALUE"""),"Flocco") -> Flocco | Y14: =IFERROR(__xludf.DUMMYFUNCTION("""COMPUTED_VALUE"""),3.2857142857142856) -> 3.2857143 | Z14: =IFERROR(__xludf.DUMMYFUNCTION("""COMPUTED_VALUE"""),1.6659862556700857) -> 1.6659863 | AA14: =IFERROR(__xludf.DUMMYFUNCTION("""COMPUTED_VALUE"""),3.6666666666666665) -> 3.6666667 | AB14: =IFERROR(__xludf.DUMMYFUNCTION("""COMPUTED_VALUE"""),"keep it in the dark") -> keep it in the dark | AC14: =IFERROR(__xludf.DUMMYFUNCTION("""COMPUTED_VALUE"""),"Capital Soirée") -> Capital Soirée
A18: February | V18: Seeding | W18: Date | X18: Poster | Y18: Average | Z18: STDEV | AA18: Peer Rank | AB18: Song | AC18: Artist
A19: Description | B19: L | C19: P | D19: G | E19: R | F19: T | G19: W | H19: F | I19: Song 1 | J19: Score 1 | K19: Winner | L19: Score 2 | M19: Song 2 | N19: F | O19: W | P19: T | Q19: R | R19: G | S19: P | T19: L | V19: 4 | W19: =IFERROR(__xludf.DUMMYFUNCTION("FILTER(Rankings!D:J, Rankings!D:D >= DATE(2026,2,1), Rankings!D:D < DATE(2026,3,1), Rankings!U:U = TRUE)"),46055.0) -> 46055 | X19: =IFERROR(__xludf.DUMMYFUNCTION("""COMPUTED_VALUE"""),"Parker") -> Parker | Y19: =IFERROR(__xludf.DUMMYFUNCTION("""COMPUTED_VALUE"""),2.142857142857143) -> 2.1428571 | Z19: =IFERROR(__xludf.DUMMYFUNCTION("""COMPUTED_VALUE"""),1.551825784457174) -> 1.5518258 | AA19: =IFERROR(__xludf.DUMMYFUNCTION("""COMPUTED_VALUE"""),2.3333333333333335) -> 2.3333333 | AB19: =IFERROR(__xludf.DUMMYFUNCTION("""COMPUTED_VALUE"""),"DREAMING") -> DREAMING | AC19: =IFERROR(__xludf.DUMMYFUNCTION("""COMPUTED_VALUE"""),"Turnstile") -> Turnstile
A20: Seed 1 vs 2 | C20: x | E20: X | I20: =K22 -> COMO CAPO | J20: =COUNTIF(B20:H20,"x") -> 2 | K20: =IF(J20>=4,I20,IF(L20>=4,M20,"TBD")) -> Soup | L20: =COUNTIF(N20:T20,"x") -> 5 | M20: =K21 -> Soup | N20: X | O20: X | P20: X | R20: x | T20: x | V20: 2 | W20: =IFERROR(__xludf.DUMMYFUNCTION("""COMPUTED_VALUE"""),46057.0) -> 46057 | X20: =IFERROR(__xludf.DUMMYFUNCTION("""COMPUTED_VALUE"""),"Weston") -> Weston | Y20: =IFERROR(__xludf.DUMMYFUNCTION("""COMPUTED_VALUE"""),1.8571428571428572) -> 1.8571429 | Z20: =IFERROR(__xludf.DUMMYFUNCTION("""COMPUTED_VALUE"""),1.355261854357877) -> 1.3552619 | AA20: =IFERROR(__xludf.DUMMYFUNCTION("""COMPUTED_VALUE"""),2.0) -> 2 | AB20: =IFERROR(__xludf.DUMMYFUNCTION("""COMPUTED_VALUE"""),"Soup") -> Soup | AC20: =IFERROR(__xludf.DUMMYFUNCTION("""COMPUTED_VALUE"""),"Remi Wolf") -> Remi Wolf
A21: Seed 2 vs 3 | C21: x | E21: X | F21: X | G21: x | H21: X | I21: =K25 -> Soup | J21: =COUNTIF(B21:H21,"x") -> 5 | K21: =IF(J21>=4,I21,IF(L21>=4,M21,"TBD")) -> Soup | L21: =COUNTIF(N21:T21,"x") -> 2 | M21: =K24 -> A Couple Minutes | R21: x | T21: x | V21: 11 | W21: =IFERROR(__xludf.DUMMYFUNCTION("""COMPUTED_VALUE"""),46059.0) -> 46059 | X21: =IFERROR(__xludf.DUMMYFUNCTION("""COMPUTED_VALUE"""),"Weston") -> Weston | Y21: =IFERROR(__xludf.DUMMYFUNCTION("""COMPUTED_VALUE"""),2.7142857142857144) -> 2.7142857 | Z21: =IFERROR(__xludf.DUMMYFUNCTION("""COMPUTED_VALUE"""),1.577908716741037) -> 1.5779087 | AA21: =IFERROR(__xludf.DUMMYFUNCTION("""COMPUTED_VALUE"""),3.0) -> 3 | AB21: =IFERROR(__xludf.DUMMYFUNCTION("""COMPUTED_VALUE"""),"I2I") -> I2I | AC21: =IFERROR(__xludf.DUMMYFUNCTION("""COMPUTED_VALUE"""),"Tevin Campbell") -> Tevin Campbell
A22: Seed 1 vs 4 | B22: x | H22: X | I22: =K26 -> Mutt | J22: =COUNTIF(B22:H22,"x") -> 2 | K22: =IF(J22>=4,I22,IF(L22>=4,M22,"TBD")) -> COMO CAPO | L22: =COUNTIF(N22:T22,"x") -> 5 | M22: =K23 -> COMO CAPO | O22: x | P22: X | Q22: X | R22: x | S22: x | V22: 5 | W22: =IFERROR(__xludf.DUMMYFUNCTION("""COMPUTED_VALUE"""),46062.0) -> 46062 | X22: =IFERROR(__xludf.DUMMYFUNCTION("""COMPUTED_VALUE"""),"Rosey") -> Rosey | Y22: =IFERROR(__xludf.DUMMYFUNCTION("""COMPUTED_VALUE"""),2.2857142857142856) -> 2.2857143 | Z22: =IFERROR(__xludf.DUMMYFUNCTION("""COMPUTED_VALUE"""),1.8294640678379566) -> 1.8294641 | AA22: =IFERROR(__xludf.DUMMYFUNCTION("""COMPUTED_VALUE"""),2.5) -> 2.5 | AB22: =IFERROR(__xludf.DUMMYFUNCTION("""COMPUTED_VALUE"""),"COMO CAPO") -> COMO CAPO | AC22: =IFERROR(__xludf.DUMMYFUNCTION("""COMPUTED_VALUE"""),"Clave Especial, Fuerza Regida") -> Clave Especial, Fuerza Regida
A23: Seed 4 vs 5 | B23: x | I23: DREAMING | J23: =COUNTIF(B23:H23,"x") -> 1 | K23: =IF(J23>=4,I23,IF(L23>=4,M23,"TBD")) -> COMO CAPO | L23: =COUNTIF(N23:T23,"x") -> 5 | M23: =K30 -> COMO CAPO | N23: X | O23: X | P23: X | R23: x | S23: x | V23: 3 | W23: =IFERROR(__xludf.DUMMYFUNCTION("""COMPUTED_VALUE"""),46064.0) -> 46064 | X23: =IFERROR(__xludf.DUMMYFUNCTION("""COMPUTED_VALUE"""),"Giacomo") -> Giacomo | Y23: =IFERROR(__xludf.DUMMYFUNCTION("""COMPUTED_VALUE"""),2.0) -> 2 | Z23: =IFERROR(__xludf.DUMMYFUNCTION("""COMPUTED_VALUE"""),0.9258200997725514) -> 0.9258201 | AA23: =IFERROR(__xludf.DUMMYFUNCTION("""COMPUTED_VALUE"""),2.1666666666666665) -> 2.1666667 | AB23: =IFERROR(__xludf.DUMMYFUNCTION("""COMPUTED_VALUE"""),"A Couple Minutes") -> A Couple Minutes | AC23: =IFERROR(__xludf.DUMMYFUNCTION("""COMPUTED_VALUE"""),"Olivia Dean") -> Olivia Dean
A24: Seed 3 vs 6 | B24: x | C24: x | D24: x | E24: X | H24: X | I24: A Couple Minutes | J24: =COUNTIF(B24:H24,"x") -> 5 | K24: =IF(J24>=4,I24,IF(L24>=4,M24,"TBD")) -> A Couple Minutes | L24: =COUNTIF(N24:T24,"x") -> 3 | M24: =K29 -> Disco Man | O24: x | P24: X | Q24: X | V24: 7 | W24: =IFERROR(__xludf.DUMMYFUNCTION("""COMPUTED_VALUE"""),46066.0) -> 46066 | X24: =IFERROR(__xludf.DUMMYFUNCTION("""COMPUTED_VALUE"""),"Logan") -> Logan | Y24: =IFERROR(__xludf.DUMMYFUNCTION("""COMPUTED_VALUE"""),2.4285714285714284) -> 2.4285714 | Z24: =IFERROR(__xludf.DUMMYFUNCTION("""COMPUTED_VALUE"""),1.178030178747903) -> 1.1780302 | AA24: =IFERROR(__xludf.DUMMYFUNCTION("""COMPUTED_VALUE"""),2.6666666666666665) -> 2.6666667 | AB24: =IFERROR(__xludf.DUMMYFUNCTION("""COMPUTED_VALUE"""),"Masterpiece") -> Masterpiece | AC24: =IFERROR(__xludf.DUMMYFUNCTION("""COMPUTED_VALUE"""),"Barney Fletcher") -> Barney Fletcher
A25: Seed 2 vs 7 | C25: x | D25: x | E25: X | F25: X | G25: X | I25: Soup | J25: =COUNTIF(B25:H25,"x") -> 5 | K25: =IF(J25>=4,I25,IF(L25>=4,M25,"TBD")) -> Soup | L25: =COUNTIF(N25:T25,"x") -> 1 | M25: =K28 -> Masterpiece | T25: x | V25: 8 | W25: =IFERROR(__xludf.DUMMYFUNCTION("""COMPUTED_VALUE"""),46069.0) -> 46069 | X25: =IFERROR(__xludf.DUMMYFUNCTION("""COMPUTED_VALUE"""),"Weston") -> Weston | Y25: =IFERROR(__xludf.DUMMYFUNCTION("""COMPUTED_VALUE"""),2.4285714285714284) -> 2.4285714 | Z25: =IFERROR(__xludf.DUMMYFUNCTION("""COMPUTED_VALUE"""),1.8405855323893037) -> 1.8405855 | AA25: =IFERROR(__xludf.DUMMYFUNCTION("""COMPUTED_VALUE"""),2.6666666666666665) -> 2.6666667 | AB25: =IFERROR(__xludf.DUMMYFUNCTION("""COMPUTED_VALUE"""),"I Wish") -> I Wish | AC25: =IFERROR(__xludf.DUMMYFUNCTION("""COMPUTED_VALUE"""),"Stevie Wonder") -> Stevie Wonder
A26: Seed 1 vs 8 | B26: x | D26: x | E26: X | F26: X | H26: X | I26: Mutt | J26: =COUNTIF(B26:H26,"x") -> 5 | K26: =IF(J26>=4,I26,IF(L26>=4,M26,"TBD")) -> Mutt | L26: =COUNTIF(N26:T26,"x") -> 1 | M26: =K27 -> Y LLORO | S26: x | V26: 12 | W26: =IFERROR(__xludf.DUMMYFUNCTION("""COMPUTED_VALUE"""),46071.0) -> 46071 | X26: =IFERROR(__xludf.DUMMYFUNCTION("""COMPUTED_VALUE"""),"Weston") -> Weston | Y26: =IFERROR(__xludf.DUMMYFUNCTION("""COMPUTED_VALUE"""),2.857142857142857) -> 2.8571429 | Z26: =IFERROR(__xludf.DUMMYFUNCTION("""COMPUTED_VALUE"""),2.099562636671296) -> 2.0995626 | AA26: =IFERROR(__xludf.DUMMYFUNCTION("""COMPUTED_VALUE"""),3.0) -> 3 | AB26: =IFERROR(__xludf.DUMMYFUNCTION("""COMPUTED_VALUE"""),"Cocoon") -> Cocoon | AC26: =IFERROR(__xludf.DUMMYFUNCTION("""COMPUTED_VALUE"""),"Catfish and the Bottlemen") -> Catfish and the Bottlemen
A27: Seed 8 vs 9 | B27: x | D27: x | G27: X | I27: I Wish | J27: =COUNTIF(B27:H27,"x") -> 3 | K27: =IF(J27>=4,I27,IF(L27>=4,M27,"TBD")) -> Y LLORO | L27: =COUNTIF(N27:T27,"x") -> 4 | M27: Y LLORO | N27: X | P27: X | Q27: X | S27: x | V27: 9 | W27: =IFERROR(__xludf.DUMMYFUNCTION("""COMPUTED_VALUE"""),46073.0) -> 46073 | X27: =IFERROR(__xludf.DUMMYFUNCTION("""COMPUTED_VALUE"""),"Parker") -> Parker | Y27: =IFERROR(__xludf.DUMMYFUNCTION("""COMPUTED_VALUE"""),2.4285714285714284) -> 2.4285714 | Z27: =IFERROR(__xludf.DUMMYFUNCTION("""COMPUTED_VALUE"""),1.9166296949998196) -> 1.9166297 | AA27: =IFERROR(__xludf.DUMMYFUNCTION("""COMPUTED_VALUE"""),2.6666666666666665) -> 2.6666667 | AB27: =IFERROR(__xludf.DUMMYFUNCTION("""COMPUTED_VALUE"""),"Y LLORO") -> Y LLORO | AC27: =IFERROR(__xludf.DUMMYFUNCTION("""COMPUTED_VALUE"""),"Junior H") -> Junior H
A28: Seed 7 vs 10 | B28: x | C28: x | D28: x | E28: X | F28: X | I28: Masterpiece | J28: =COUNTIF(B28:H28,"x") -> 5 | K28: =IF(J28>=4,I28,IF(L28>=4,M28,"TBD")) -> Masterpiece | L28: =COUNTIF(N28:T28,"x") -> 2 | M28: Skin & Bones | N28: X | O28: X | V28: 6 | W28: =IFERROR(__xludf.DUMMYFUNCTION("""COMPUTED_VALUE"""),46076.0) -> 46076 | X28: =IFERROR(__xludf.DUMMYFUNCTION("""COMPUTED_VALUE"""),"TTAC") -> TTAC | Y28: =IFERROR(__xludf.DUMMYFUNCTION("""COMPUTED_VALUE"""),2.4285714285714284) -> 2.4285714 | Z28: =IFERROR(__xludf.DUMMYFUNCTION("""COMPUTED_VALUE"""),0.9035079029052512) -> 0.9035079 | AA28: =IFERROR(__xludf.DUMMYFUNCTION("""COMPUTED_VALUE"""),2.6666666666666665) -> 2.6666667 | AB28: =IFERROR(__xludf.DUMMYFUNCTION("""COMPUTED_VALUE"""),"Disco Man") -> Disco Man | AC28: =IFERROR(__xludf.DUMMYFUNCTION("""COMPUTED_VALUE"""),"Remi Wolf") -> Remi Wolf
A29: Seed 6 vs 11 | B29: x | C29: x | F29: X | G29: X | H29: X | I29: Disco Man | J29: =COUNTIF(B29:H29,"x") -> 5 | K29: =IF(J29>=4,I29,IF(L29>=4,M29,"TBD")) -> Disco Man | L29: =COUNTIF(N29:T29,"x") -> 1 | M29: I2I | R29: x | V29: 10 | W29: =IFERROR(__xludf.DUMMYFUNCTION("""COMPUTED_VALUE"""),46078.0) -> 46078 | X29: =IFERROR(__xludf.DUMMYFUNCTION("""COMPUTED_VALUE"""),"Parker") -> Parker | Y29: =IFERROR(__xludf.DUMMYFUNCTION("""COMPUTED_VALUE"""),2.7142857142857144) -> 2.7142857 | Z29: =IFERROR(__xludf.DUMMYFUNCTION("""COMPUTED_VALUE"""),1.2777531299998799) -> 1.2777531 | AA29: =IFERROR(__xludf.DUMMYFUNCTION("""COMPUTED_VALUE"""),2.8333333333333335) -> 2.8333333 | AB29: =IFERROR(__xludf.DUMMYFUNCTION("""COMPUTED_VALUE"""),"Skin & Bones") -> Skin & Bones | AC29: =IFERROR(__xludf.DUMMYFUNCTION("""COMPUTED_VALUE"""),"Silverstein") -> Silverstein
A30: Seed 5 vs 12 | C30: x | D30: x | F30: X | G30: X | H30: X | I30: COMO CAPO | J30: =COUNTIF(B30:H30,"x") -> 5 | K30: =IF(J30>=4,I30,IF(L30>=4,M30,"TBD")) -> COMO CAPO | L30: =COUNTIF(N30:T30,"x") -> 1 | M30: Cocoon | T30: x | V30: 1 | W30: =IFERROR(__xludf.DUMMYFUNCTION("""COMPUTED_VALUE"""),46080.0) -> 46080 | X30: =IFERROR(__xludf.DUMMYFUNCTION("""COMPUTED_VALUE"""),"Flocco") -> Flocco | Y30: =IFERROR(__xludf.DUMMYFUNCTION("""COMPUTED_VALUE"""),1.4285714285714286) -> 1.4285714 | Z30: =IFERROR(__xludf.DUMMYFUNCTION("""COMPUTED_VALUE"""),0.4948716593053935) -> 0.49487166 | AA30: =IFERROR(__xludf.DUMMYFUNCTION("""COMPUTED_VALUE"""),1.5) -> 1.5 | AB30: =IFERROR(__xludf.DUMMYFUNCTION("""COMPUTED_VALUE"""),"MUTT") -> MUTT | AC30: =IFERROR(__xludf.DUMMYFUNCTION("""COMPUTED_VALUE"""),"Leon Thomas") -> Leon Thomas
A34: March | V34: Seeding | W34: Date | X34: Poster | Y34: Average | Z34: STDEV | AA34: Peer Rank | AB34: Song | AC34: Artist
A35: Description | B35: L | C35: P | D35: G | E35: R | F35: T | G35: W | H35: F | I35: Song 1 | J35: Score 1 | K35: Winner | L35: Score 2 | M35: Song 2 | N35: F | O35: W | P35: T | Q35: R | R35: G | S35: P | T35: L | V35: 2 | W35: =IFERROR(__xludf.DUMMYFUNCTION("FILTER(Rankings!D:J, Rankings!D:D >= DATE(2026,3,1), Rankings!D:D < DATE(2026,4,1), Rankings!U:U = TRUE)"),46083.0) -> 46083 | X35: =IFERROR(__xludf.DUMMYFUNCTION("""COMPUTED_VALUE"""),"Rosey") -> Rosey | Y35: =IFERROR(__xludf.DUMMYFUNCTION("""COMPUTED_VALUE"""),2.142857142857143) -> 2.1428571 | Z35: =IFERROR(__xludf.DUMMYFUNCTION("""COMPUTED_VALUE"""),1.355261854357877) -> 1.3552619 | AA35: =IFERROR(__xludf.DUMMYFUNCTION("""COMPUTED_VALUE"""),2.3333333333333335) -> 2.3333333 | AB35: =IFERROR(__xludf.DUMMYFUNCTION("""COMPUTED_VALUE"""),"BAILE INoLVIDABLE") -> BAILE INoLVIDABLE | AC35: =IFERROR(__xludf.DUMMYFUNCTION("""COMPUTED_VALUE"""),"Bad Bunny") -> Bad Bunny
A36: Seed 1 vs 2 | F36: X | I36: =K38 -> Silver Springs | J36: =COUNTIF(B36:H36,"x") -> 1 | K36: =IF(J36>=4,I36,IF(L36>=4,M36,"TBD")) -> BAILE INoLVIDABLE | L36: =COUNTIF(N36:T36,"x") -> 5 | M36: =K37 -> BAILE INoLVIDABLE | O36: x | Q36: x | R36: x | S36: x | T36: x | V36: 10 | W36: =IFERROR(__xludf.DUMMYFUNCTION("""COMPUTED_VALUE"""),46085.0) -> 46085 | X36: =IFERROR(__xludf.DUMMYFUNCTION("""COMPUTED_VALUE"""),"Rosey") -> Rosey | Y36: =IFERROR(__xludf.DUMMYFUNCTION("""COMPUTED_VALUE"""),2.7142857142857144) -> 2.7142857 | Z36: =IFERROR(__xludf.DUMMYFUNCTION("""COMPUTED_VALUE"""),2.1189138534559038) -> 2.1189139 | AA36: =IFERROR(__xludf.DUMMYFUNCTION("""COMPUTED_VALUE"""),2.8333333333333335) -> 2.8333333 | AB36: =IFERROR(__xludf.DUMMYFUNCTION("""COMPUTED_VALUE"""),"Seasons (Waiting on You)") -> Seasons (Waiting on You) | AC36: =IFERROR(__xludf.DUMMYFUNCTION("""COMPUTED_VALUE"""),"Future Islands") -> Future Islands
A37: Seed 2 vs 3 | B37: x | C37: x | D37: x | E37: X | F37: X | G37: x | I37: =K41 -> BAILE INoLVIDABLE | J37: =COUNTIF(B37:H37,"x") -> 6 | K37: =IF(J37>=4,I37,IF(L37>=4,M37,"TBD")) -> BAILE INoLVIDABLE | L37: =COUNTIF(N37:T37,"x") -> 0 | M37: =K40 -> Clockwork | V37: 1 | W37: =IFERROR(__xludf.DUMMYFUNCTION("""COMPUTED_VALUE"""),46087.0) -> 46087 | X37: =IFERROR(__xludf.DUMMYFUNCTION("""COMPUTED_VALUE"""),"Logan") -> Logan | Y37: =IFERROR(__xludf.DUMMYFUNCTION("""COMPUTED_VALUE"""),1.8571428571428572) -> 1.8571429 | Z37: =IFERROR(__xludf.DUMMYFUNCTION("""COMPUTED_VALUE"""),1.1248582677159729) -> 1.1248583 | AA37: =IFERROR(__xludf.DUMMYFUNCTION("""COMPUTED_VALUE"""),1.6666666666666667) -> 1.6666667 | AB37: =IFERROR(__xludf.DUMMYFUNCTION("""COMPUTED_VALUE"""),"Best Part") -> Best Part | AC37: =IFERROR(__xludf.DUMMYFUNCTION("""COMPUTED_VALUE"""),"Daniel Ceasar, H.E.R.") -> Daniel Ceasar, H.E.R.
A38: Seed 1 vs 4 | B38: x | G38: x | I38: =K42 -> Shiva | J38: =COUNTIF(B38:H38,"x") -> 2 | K38: =IF(J38>=4,I38,IF(L38>=4,M38,"TBD")) -> Silver Springs | L38: =COUNTIF(N38:T38,"x") -> 4 | M38: =K39 -> Silver Springs | P38: X | Q38: X | R38: x | S38: x | V38: 3 | W38: =IFERROR(__xludf.DUMMYFUNCTION("""COMPUTED_VALUE"""),46090.0) -> 46090 | X38: =IFERROR(__xludf.DUMMYFUNCTION("""COMPUTED_VALUE"""),"Giacomo") -> Giacomo | Y38: =IFERROR(__xludf.DUMMYFUNCTION("""COMPUTED_VALUE"""),2.2857142857142856) -> 2.2857143 | Z38: =IFERROR(__xludf.DUMMYFUNCTION("""COMPUTED_VALUE"""),1.1605769149479943) -> 1.1605769 | AA38: =IFERROR(__xludf.DUMMYFUNCTION("""COMPUTED_VALUE"""),2.3333333333333335) -> 2.3333333 | AB38: =IFERROR(__xludf.DUMMYFUNCTION("""COMPUTED_VALUE"""),"No Simulation") -> No Simulation | AC38: =IFERROR(__xludf.DUMMYFUNCTION("""COMPUTED_VALUE"""),"Tinashe") -> Tinashe
A39: Seed 4 vs 5 | C39: x | E39: X | F39: X | H39: X | I39: =K47 -> Silver Springs | J39: =COUNTIF(B39:H39,"x") -> 4 | K39: =IF(J39>=4,I39,IF(L39>=4,M39,"TBD")) -> Silver Springs | L39: =COUNTIF(N39:T39,"x") -> 3 | M39: =K46 -> Layaway Luv | O39: X | R39: x | T39: x | V39: 4 | W39: =IFERROR(__xludf.DUMMYFUNCTION("""COMPUTED_VALUE"""),46092.0) -> 46092 | X39: =IFERROR(__xludf.DUMMYFUNCTION("""COMPUTED_VALUE"""),"Rosey") -> Rosey | Y39: =IFERROR(__xludf.DUMMYFUNCTION("""COMPUTED_VALUE"""),2.2857142857142856) -> 2.2857143 | Z39: =IFERROR(__xludf.DUMMYFUNCTION("""COMPUTED_VALUE"""),1.6659862556700857) -> 1.6659863 | AA39: =IFERROR(__xludf.DUMMYFUNCTION("""COMPUTED_VALUE"""),2.3333333333333335) -> 2.3333333 | AB39: =IFERROR(__xludf.DUMMYFUNCTION("""COMPUTED_VALUE"""),"Silver Springs") -> Silver Springs | AC39: =IFERROR(__xludf.DUMMYFUNCTION("""COMPUTED_VALUE"""),"Fleetwood Mac") -> Fleetwood Mac
A40: Seed 3 vs 6 | B40: x | D40: x | G40: x | I40: No Simulation | J40: =COUNTIF(B40:H40,"x") -> 3 | K40: =IF(J40>=4,I40,IF(L40>=4,M40,"TBD")) -> Clockwork | L40: =COUNTIF(N40:T40,"x") -> 4 | M40: =K45 -> Clockwork | N40: X | P40: X | Q40: X | S40: x | V40: 5 | W40: =IFERROR(__xludf.DUMMYFUNCTION("""COMPUTED_VALUE"""),46094.0) -> 46094 | X40: =IFERROR(__xludf.DUMMYFUNCTION("""COMPUTED_VALUE"""),"Flocco") -> Flocco | Y40: =IFERROR(__xludf.DUMMYFUNCTION("""COMPUTED_VALUE"""),2.2857142857142856) -> 2.2857143 | Z40: =IFERROR(__xludf.DUMMYFUNCTION("""COMPUTED_VALUE"""),1.1605769149479943) -> 1.1605769 | AA40: =IFERROR(__xludf.DUMMYFUNCTION("""COMPUTED_VALUE"""),2.5) -> 2.5 | AB40: =IFERROR(__xludf.DUMMYFUNCTION("""COMPUTED_VALUE"""),"Yellow") -> Yellow | AC40: =IFERROR(__xludf.DUMMYFUNCTION("""COMPUTED_VALUE"""),"Coldplay") -> Coldplay
A41: Seed 2 vs 7 | B41: x | C41: x | D41: x | E41: X | F41: X | G41: x | H41: X | I41: BAILE INoLVIDABLE | J41: =COUNTIF(B41:H41,"x") -> 7 | K41: =IF(J41>=4,I41,IF(L41>=4,M41,"TBD")) -> BAILE INoLVIDABLE | L41: =COUNTIF(N41:T41,"x") -> 0 | M41: =K44 -> Okayyy We Back | V41: 13 | W41: =IFERROR(__xludf.DUMMYFUNCTION("""COMPUTED_VALUE"""),46097.0) -> 46097 | X41: =IFERROR(__xludf.DUMMYFUNCTION("""COMPUTED_VALUE"""),"Parker") -> Parker | Y41: =IFERROR(__xludf.DUMMYFUNCTION("""COMPUTED_VALUE"""),3.142857142857143) -> 3.1428571 | Z41: =IFERROR(__xludf.DUMMYFUNCTION("""COMPUTED_VALUE"""),2.231499907401901) -> 2.2314999 | AA41: =IFERROR(__xludf.DUMMYFUNCTION("""COMPUTED_VALUE"""),3.3333333333333335) -> 3.3333333 | AB41: =IFERROR(__xludf.DUMMYFUNCTION("""COMPUTED_VALUE"""),"Metaverse") -> Metaverse | AC41: =IFERROR(__xludf.DUMMYFUNCTION("""COMPUTED_VALUE"""),"Cage The Elephant") -> Cage The Elephant
A42: Seed 1 vs 8 | B42: x | E42: X | H42: X | I42: Best Part | J42: =COUNTIF(B42:H42,"x") -> 3 | K42: =IF(J42>=4,I42,IF(L42>=4,M42,"TBD")) -> Shiva | L42: =COUNTIF(N42:T42,"x") -> 4 | M42: =K43 -> Shiva | O42: x | P42: X | R42: x | S42: x | V42: 7 | W42: =IFERROR(__xludf.DUMMYFUNCTION("""COMPUTED_VALUE"""),46099.0) -> 46099 | X42: =IFERROR(__xludf.DUMMYFUNCTION("""COMPUTED_VALUE"""),"Giacomo") -> Giacomo | Y42: =IFERROR(__xludf.DUMMYFUNCTION("""COMPUTED_VALUE"""),2.4285714285714284) -> 2.4285714 | Z42: =IFERROR(__xludf.DUMMYFUNCTION("""COMPUTED_VALUE"""),1.4982983545287878) -> 1.4982984 | AA42: =IFERROR(__xludf.DUMMYFUNCTION("""COMPUTED_VALUE"""),2.5) -> 2.5 | AB42: =IFERROR(__xludf.DUMMYFUNCTION("""COMPUTED_VALUE"""),"Okayyy We Back") -> Okayyy We Back | AC42: =IFERROR(__xludf.DUMMYFUNCTION("""COMPUTED_VALUE"""),"Andy Mineo, Mark Morrison") -> Andy Mineo, Mark Morrison
A43: Seed 8 vs 9 | B43: x | C43: x | D43: x | G43: X | I43: Shiva | J43: =COUNTIF(B43:H43,"x") -> 4 | K43: =IF(J43>=4,I43,IF(L43>=4,M43,"TBD")) -> Shiva | L43: =COUNTIF(N43:T43,"x") -> 3 | M43: Anna Sun | N43: X | P43: X | Q43: X | V43: 6 | W43: =IFERROR(__xludf.DUMMYFUNCTION("""COMPUTED_VALUE"""),46101.0) -> 46101 | X43: =IFERROR(__xludf.DUMMYFUNCTION("""COMPUTED_VALUE"""),"Rosey") -> Rosey | Y43: =IFERROR(__xludf.DUMMYFUNCTION("""COMPUTED_VALUE"""),2.2857142857142856) -> 2.2857143 | Z43: =IFERROR(__xludf.DUMMYFUNCTION("""COMPUTED_VALUE"""),1.749635530559413) -> 1.7496355 | AA43: =IFERROR(__xludf.DUMMYFUNCTION("""COMPUTED_VALUE"""),2.5) -> 2.5 | AB43: =IFERROR(__xludf.DUMMYFUNCTION("""COMPUTED_VALUE"""),"B.I.T.C.H.") -> B.I.T.C.H. | AC43: =IFERROR(__xludf.DUMMYFUNCTION("""COMPUTED_VALUE"""),"Megan Thee Stallion") -> Megan Thee Stallion
A44: Seed 7 vs 10 | B44: x | F44: X | G44: X | H44: X | I44: Okayyy We Back | J44: =COUNTIF(B44:H44,"x") -> 4 | K44: =IF(J44>=4,I44,IF(L44>=4,M44,"TBD")) -> Okayyy We Back | L44: =COUNTIF(N44:T44,"x") -> 3 | M44: Seasons (Waiting on You) | Q44: X | R44: x | S44: x | V44: 12 | W44: =IFERROR(__xludf.DUMMYFUNCTION("""COMPUTED_VALUE"""),46104.0) -> 46104 | X44: =IFERROR(__xludf.DUMMYFUNCTION("""COMPUTED_VALUE"""),"Giacomo") -> Giacomo | Y44: =IFERROR(__xludf.DUMMYFUNCTION("""COMPUTED_VALUE"""),3.0) -> 3 | Z44: =IFERROR(__xludf.DUMMYFUNCTION("""COMPUTED_VALUE"""),1.6035674514745464) -> 1.6035675 | AA44: =IFERROR(__xludf.DUMMYFUNCTION("""COMPUTED_VALUE"""),3.1666666666666665) -> 3.1666667 | AB44: =IFERROR(__xludf.DUMMYFUNCTION("""COMPUTED_VALUE"""),"Layaway Luv") -> Layaway Luv | AC44: =IFERROR(__xludf.DUMMYFUNCTION("""COMPUTED_VALUE"""),"Ariel") -> Ariel
A45: Seed 6 vs 11 | I45: B.I.T.C.H. | J45: =COUNTIF(B45:H45,"x") -> 0 | K45: =IF(J45>=4,I45,IF(L45>=4,M45,"TBD")) -> Clockwork | L45: =COUNTIF(N45:T45,"x") -> 7 | M45: Clockwork | N45: X | O45: X | P45: X | Q45: X | R45: x | S45: x | T45: x | V45: 11 | W45: =IFERROR(__xludf.DUMMYFUNCTION("""COMPUTED_VALUE"""),46106.0) -> 46106 | X45: =IFERROR(__xludf.DUMMYFUNCTION("""COMPUTED_VALUE"""),"Weston") -> Weston | Y45: =IFERROR(__xludf.DUMMYFUNCTION("""COMPUTED_VALUE"""),2.7142857142857144) -> 2.7142857 | Z45: =IFERROR(__xludf.DUMMYFUNCTION("""COMPUTED_VALUE"""),2.0503857277724746) -> 2.0503857 | AA45: =IFERROR(__xludf.DUMMYFUNCTION("""COMPUTED_VALUE"""),3.0) -> 3 | AB45: =IFERROR(__xludf.DUMMYFUNCTION("""COMPUTED_VALUE"""),"Clockwork") -> Clockwork | AC45: =IFERROR(__xludf.DUMMYFUNCTION("""COMPUTED_VALUE"""),"Autopilot Off") -> Autopilot Off
A46: Seed 5 vs 12 | F46: X | H46: X | I46: Yellow | J46: =COUNTIF(B46:H46,"x") -> 2 | K46: =IF(J46>=4,I46,IF(L46>=4,M46,"TBD")) -> Layaway Luv | L46: =COUNTIF(N46:T46,"x") -> 5 | M46: Layaway Luv | O46: X | Q46: X | R46: x | S46: x | T46: x | V46: 8 | W46: =IFERROR(__xludf.DUMMYFUNCTION("""COMPUTED_VALUE"""),46108.0) -> 46108 | X46: =IFERROR(__xludf.DUMMYFUNCTION("""COMPUTED_VALUE"""),"Weston") -> Weston | Y46: =IFERROR(__xludf.DUMMYFUNCTION("""COMPUTED_VALUE"""),2.4285714285714284) -> 2.4285714 | Z46: =IFERROR(__xludf.DUMMYFUNCTION("""COMPUTED_VALUE"""),1.178030178747903) -> 1.1780302 | AA46: =IFERROR(__xludf.DUMMYFUNCTION("""COMPUTED_VALUE"""),2.6666666666666665) -> 2.6666667 | AB46: =IFERROR(__xludf.DUMMYFUNCTION("""COMPUTED_VALUE"""),"Shiva") -> Shiva | AC46: =IFERROR(__xludf.DUMMYFUNCTION("""COMPUTED_VALUE"""),"Spillage Village, JID, Earthgang, Benji., Jurdan Bryant") -> Spillage Village, JID, Earthgang, Benji., Jurdan Bryant
A47: Seed 4 vs 13 | C47: x | D47: x | E47: X | F47: X | H47: X | I47: Silver Springs | J47: =COUNTIF(B47:H47,"x") -> 5 | K47: =IF(J47>=4,I47,IF(L47>=4,M47,"TBD")) -> Silver Springs | L47: =COUNTIF(N47:T47,"x") -> 2 | M47: Metaverse | O47: X | T47: x | V47: 9 | W47: =IFERROR(__xludf.DUMMYFUNCTION("""COMPUTED_VALUE"""),46111.0) -> 46111 | X47: =IFERROR(__xludf.DUMMYFUNCTION("""COMPUTED_VALUE"""),"Weston") -> Weston | Y47: =IFERROR(__xludf.DUMMYFUNCTION("""COMPUTED_VALUE"""),2.5714285714285716) -> 2.5714286 | Z47: =IFERROR(__xludf.DUMMYFUNCTION("""COMPUTED_VALUE"""),1.5907898179514348) -> 1.5907898 | AA47: =IFERROR(__xludf.DUMMYFUNCTION("""COMPUTED_VALUE"""),2.8333333333333335) -> 2.8333333 | AB47: =IFERROR(__xludf.DUMMYFUNCTION("""COMPUTED_VALUE"""),"Anna Sun") -> Anna Sun | AC47: =IFERROR(__xludf.DUMMYFUNCTION("""COMPUTED_VALUE"""),"WALK THE MOON") -> WALK THE MOON
A51: April | V51: Seeding | W51: Date | X51: Poster | Y51: Average | Z51: STDEV | AA51: Peer Rank | AB51: Song | AC51: Artist | AD51: Score
A52: Description | B52: L | C52: P | D52: G | E52: R | F52: T | G52: W | H52: F | I52: Song 1 | J52: Score 1 | K52: Winner | L52: Score 2 | M52: Song 2 | N52: F | O52: W | P52: T | Q52: R | R52: G | S52: P | T52: L | V52: =RANK(AD52,AD$52:AD$64) -> 9 | W52: =IFERROR(__xludf.DUMMYFUNCTION("FILTER(Rankings!D:J, Rankings!D:D >= DATE(2026,4,1), Rankings!D:D < DATE(2026,5,1), Rankings!U:U = TRUE)"),46113.0) -> 46113 | X52: =IFERROR(__xludf.DUMMYFUNCTION("""COMPUTED_VALUE"""),"TTAC") -> TTAC | Y52: =IFERROR(__xludf.DUMMYFUNCTION("""COMPUTED_VALUE"""),2.857142857142857) -> 2.8571429 | Z52: =IFERROR(__xludf.DUMMYFUNCTION("""COMPUTED_VALUE"""),1.9587584572574412) -> 1.9587585 | AA52: =IFERROR(__xludf.DUMMYFUNCTION("""COMPUTED_VALUE"""),3.1666666666666665) -> 3.1666667 | AB52: =IFERROR(__xludf.DUMMYFUNCTION("""COMPUTED_VALUE"""),"Save It For Later") -> Save It For Later | AC52: =IFERROR(__xludf.DUMMYFUNCTION("""COMPUTED_VALUE"""),"Eddie Vedder") -> Eddie Vedder | AD52: =IF(ISBLANK(W52), "", RANK(Y52, Y$52:Y$64) + RANK(AA52, AA$52:AA$64)/10 + RANK(Z52, Z$52:Z$64)/100) -> 5.42
A53: Seed 1 vs 2 | C53: x | D53: x | G53: X | H53: X | I53: =K55 -> Radio rio | J53: =COUNTIF(B53:H53,"x") -> 4 | K53: =IF(J53>=4,I53,IF(L53>=4,M53,"TBD")) -> Radio rio | L53: =COUNTIF(N53:T53,"x") -> 0 | M53: =K54 -> TBD | V53: =RANK(AD53,AD$52:AD$64) -> 2 | W53: =IFERROR(__xludf.DUMMYFUNCTION("""COMPUTED_VALUE"""),46115.0) -> 46115 | X53: =IFERROR(__xludf.DUMMYFUNCTION("""COMPUTED_VALUE"""),"Parker") -> Parker | Y53: =IFERROR(__xludf.DUMMYFUNCTION("""COMPUTED_VALUE"""),1.8571428571428572) -> 1.8571429 | Z53: =IFERROR(__xludf.DUMMYFUNCTION("""COMPUTED_VALUE"""),1.124858267715973) -> 1.1248583 | AA53: =IFERROR(__xludf.DUMMYFUNCTION("""COMPUTED_VALUE"""),2.0) -> 2 | AB53: =IFERROR(__xludf.DUMMYFUNCTION("""COMPUTED_VALUE"""),"Perfect Ten") -> Perfect Ten | AC53: =IFERROR(__xludf.DUMMYFUNCTION("""COMPUTED_VALUE"""),"Mustard, Nipsey Hussle") -> Mustard, Nipsey Hussle | AD53: =IF(ISBLANK(W53), "", RANK(Y53, Y$52:Y$64) + RANK(AA53, AA$52:AA$64)/10 + RANK(Z53, Z$52:Z$64)/100) + 0.01 -> 12.21
A54: Seed 2 vs 3 | C54: x | F54: X | H54: X | I54: =K58 -> Perfect Ten | J54: =COUNTIF(B54:H54,"x") -> 3 | K54: =IF(J54>=4,I54,IF(L54>=4,M54,"TBD")) -> TBD | L54: =COUNTIF(N54:T54,"x") -> 3 | M54: =K57 -> See You Later | O54: X | R54: x | T54: x | V54: =RANK(AD54,AD$52:AD$64) -> 3 | W54: =IFERROR(__xludf.DUMMYFUNCTION("""COMPUTED_VALUE"""),46118.0) -> 46118 | X54: =IFERROR(__xludf.DUMMYFUNCTION("""COMPUTED_VALUE"""),"Flocco") -> Flocco | Y54: =IFERROR(__xludf.DUMMYFUNCTION("""COMPUTED_VALUE"""),1.8571428571428572) -> 1.8571429 | Z54: =IFERROR(__xludf.DUMMYFUNCTION("""COMPUTED_VALUE"""),1.124858267715973) -> 1.1248583 | AA54: =IFERROR(__xludf.DUMMYFUNCTION("""COMPUTED_VALUE"""),2.0) -> 2 | AB54: =IFERROR(__xludf.DUMMYFUNCTION("""COMPUTED_VALUE"""),"How Will I Know") -> How Will I Know | AC54: =IFERROR(__xludf.DUMMYFUNCTION("""COMPUTED_VALUE""")," Whitney Houston") -> Whitney Houston | AD54: =IF(ISBLANK(W54), "", RANK(Y54, Y$52:Y$64) + RANK(AA54, AA$52:AA$64)/10 + RANK(Z54, Z$52:Z$64)/100) -> 12.2
A55: Seed 1 vs 4 | C55: x | D55: x | E55: X | G55: x | I55: =K59 -> Radio rio | J55: =COUNTIF(B55:H55,"x") -> 4 | K55: =IF(J55>=4,I55,IF(L55>=4,M55,"TBD")) -> Radio rio | L55: =COUNTIF(N55:T55,"x") -> 3 | M55: =K56 -> Roommates | N55: X | P55: X | T55: x | V55: =RANK(AD55,AD$52:AD$64) -> 4 | W55: =IFERROR(__xludf.DUMMYFUNCTION("""COMPUTED_VALUE"""),46120.0) -> 46120 | X55: =IFERROR(__xludf.DUMMYFUNCTION("""COMPUTED_VALUE"""),"Rosey") -> Rosey | Y55: =IFERROR(__xludf.DUMMYFUNCTION("""COMPUTED_VALUE"""),2.0) -> 2 | Z55: =IFERROR(__xludf.DUMMYFUNCTION("""COMPUTED_VALUE"""),1.0690449676496976) -> 1.069045 | AA55: =IFERROR(__xludf.DUMMYFUNCTION("""COMPUTED_VALUE"""),2.1666666666666665) -> 2.1666667 | AB55: =IFERROR(__xludf.DUMMYFUNCTION("""COMPUTED_VALUE"""),"Superstar (feat. Matthew Santos)") -> Superstar (feat. Matthew Santos) | AC55: =IFERROR(__xludf.DUMMYFUNCTION("""COMPUTED_VALUE"""),"Lupe Fiasco, Matthew Santos") -> Lupe Fiasco, Matthew Santos | AD55: =IF(ISBLANK(W55), "", RANK(Y55, Y$52:Y$64) + RANK(AA55, AA$52:AA$64)/10 + RANK(Z55, Z$52:Z$64)/100) -> 11.12
A56: Seed 4 vs 5 | F56: X | I56: =K64 -> Superstar (feat. Matthew Santos) | J56: =COUNTIF(B56:H56,"x") -> 1 | K56: =IF(J56>=4,I56,IF(L56>=4,M56,"TBD")) -> Roommates | L56: =COUNTIF(N56:T56,"x") -> 5 | M56: =K63 -> Roommates | N56: X | O56: X | R56: x | S56: x | T56: x | V56: =RANK(AD56,AD$52:AD$64) -> 1 | W56: =IFERROR(__xludf.DUMMYFUNCTION("""COMPUTED_VALUE"""),46122.0) -> 46122 | X56: =IFERROR(__xludf.DUMMYFUNCTION("""COMPUTED_VALUE"""),"Flocco") -> Flocco | Y56: =IFERROR(__xludf.DUMMYFUNCTION("""COMPUTED_VALUE"""),1.7142857142857142) -> 1.7142857 | Z56: =IFERROR(__xludf.DUMMYFUNCTION("""COMPUTED_VALUE"""),0.8806305718527109) -> 0.88063057 | AA56: =IFERROR(__xludf.DUMMYFUNCTION("""COMPUTED_VALUE"""),1.8333333333333333) -> 1.8333333 | AB56: =IFERROR(__xludf.DUMMYFUNCTION("""COMPUTED_VALUE""")," Radio rio") -> Radio rio | AC56: =IFERROR(__xludf.DUMMYFUNCTION("""COMPUTED_VALUE""")," Masayoshi takanaka") -> Masayoshi takanaka | AD56: =IF(ISBLANK(W56), "", RANK(Y56, Y$52:Y$64) + RANK(AA56, AA$52:AA$64)/10 + RANK(Z56, Z$52:Z$64)/100) -> 14.43
A57: Seed 3 vs 6 | B57: x | F57: X | H57: X | I57: =IFERROR(__xludf.DUMMYFUNCTION("FILTER(AB$52:AB$64, V$52:V$64=INT(MID(A57,6,1)))"),"How Will I Know") -> How Will I Know | J57: =COUNTIF(B57:H57,"x") -> 3 | K57: =IF(J57>=4,I57,IF(L57>=4,M57,"TBD")) -> See You Later | L57: =COUNTIF(N57:T57,"x") -> 4 | M57: =K62 -> See You Later | O57: X | Q57: X | R57: x | S57: x | V57: =RANK(AD57,AD$52:AD$64) -> 10 | W57: =IFERROR(__xludf.DUMMYFUNCTION("""COMPUTED_VALUE"""),46125.0) -> 46125 | X57: =IFERROR(__xludf.DUMMYFUNCTION("""COMPUTED_VALUE"""),"Weston") -> Weston | Y57: =IFERROR(__xludf.DUMMYFUNCTION("""COMPUTED_VALUE"""),3.0) -> 3 | Z57: =IFERROR(__xludf.DUMMYFUNCTION("""COMPUTED_VALUE"""),1.927248223318863) -> 1.9272482 | AA57: =IFERROR(__xludf.DUMMYFUNCTION("""COMPUTED_VALUE"""),3.3333333333333335) -> 3.3333333 | AB57: =IFERROR(__xludf.DUMMYFUNCTION("""COMPUTED_VALUE"""),"Don't you lie") -> Don't you lie | AC57: =IFERROR(__xludf.DUMMYFUNCTION("""COMPUTED_VALUE"""),"Offset") -> Offset | AD57: =IF(ISBLANK(W57), "", RANK(Y57, Y$52:Y$64) + RANK(AA57, AA$52:AA$64)/10 + RANK(Z57, Z$52:Z$64)/100) -> 4.33
A58: Seed 2 vs 7 | B58: x | C58: x | D58: x | F58: X | G58: X | H58: X | I58: =IFERROR(__xludf.DUMMYFUNCTION("FILTER(AB$52:AB$64, V$52:V$64=INT(MID(A58,6,1)))"),"Perfect Ten") -> Perfect Ten | J58: =COUNTIF(B58:H58,"x") -> 6 | K58: =IF(J58>=4,I58,IF(L58>=4,M58,"TBD")) -> Perfect Ten | L58: =COUNTIF(N58:T58,"x") -> 0 | M58: =K61 -> Space | V58: =RANK(AD58,AD$52:AD$64) -> 7 | W58: =IFERROR(__xludf.DUMMYFUNCTION("""COMPUTED_VALUE"""),46127.0) -> 46127 | X58: =IFERROR(__xludf.DUMMYFUNCTION("""COMPUTED_VALUE"""),"Rosey") -> Rosey | Y58: =IFERROR(__xludf.DUMMYFUNCTION("""COMPUTED_VALUE"""),2.5714285714285716) -> 2.5714286 | Z58: =IFERROR(__xludf.DUMMYFUNCTION("""COMPUTED_VALUE"""),1.178030178747903) -> 1.1780302 | AA58: =IFERROR(__xludf.DUMMYFUNCTION("""COMPUTED_VALUE"""),2.6666666666666665) -> 2.6666667 | AB58: =IFERROR(__xludf.DUMMYFUNCTION("""COMPUTED_VALUE"""),"Space") -> Space | AC58: =IFERROR(__xludf.DUMMYFUNCTION("""COMPUTED_VALUE"""),"French Fuse") -> French Fuse | AD58: =IF(ISBLANK(W58), "", RANK(Y58, Y$52:Y$64) + RANK(AA58, AA$52:AA$64)/10 + RANK(Z58, Z$52:Z$64)/100) -> 7.79
A59: Seed 1 vs 8 | B59: x | C59: x | D59: x | G59: X | H59: x | I59: =IFERROR(__xludf.DUMMYFUNCTION("FILTER(AB$52:AB$64, V$52:V$64=INT(MID(A59,6,1)))")," Radio rio") -> Radio rio | J59: =COUNTIF(B59:H59,"x") -> 5 | K59: =IF(J59>=4,I59,IF(L59>=4,M59,"TBD")) -> Radio rio | L59: =COUNTIF(N59:T59,"x") -> 1 | M59: =K60 -> Bad dreams | P59: X | V59: =RANK(AD59,AD$52:AD$64) -> 12 | W59: =IFERROR(__xludf.DUMMYFUNCTION("""COMPUTED_VALUE"""),46129.0) -> 46129 | X59: =IFERROR(__xludf.DUMMYFUNCTION("""COMPUTED_VALUE"""),"Parker") -> Parker | Y59: =IFERROR(__xludf.DUMMYFUNCTION("""COMPUTED_VALUE"""),3.2857142857142856) -> 3.2857143 | Z59: =IFERROR(__xludf.DUMMYFUNCTION("""COMPUTED_VALUE"""),1.665986255670086) -> 1.6659863 | AA59: =IFERROR(__xludf.DUMMYFUNCTION("""COMPUTED_VALUE"""),3.1666666666666665) -> 3.1666667 | AB59: =IFERROR(__xludf.DUMMYFUNCTION("""COMPUTED_VALUE"""),"Meat") -> Meat | AC59: =IFERROR(__xludf.DUMMYFUNCTION("""COMPUTED_VALUE"""),"2Slimey") -> 2Slimey | AD59: =IF(ISBLANK(W59), "", RANK(Y59, Y$52:Y$64) + RANK(AA59, AA$52:AA$64)/10 + RANK(Z59, Z$52:Z$64)/100) -> 2.48
A60: Seed 8 vs 9 | B60: x | E60: X | F60: X | H60: X | I60: =IFERROR(__xludf.DUMMYFUNCTION("FILTER(AB$52:AB$64, V$52:V$64=INT(MID(A60,6,1)))")," Bad dreams") -> Bad dreams | J60: =COUNTIF(B60:H60,"x") -> 4 | K60: =IF(J60>=4,I60,IF(L60>=4,M60,"TBD")) -> Bad dreams | L60: =COUNTIF(N60:T60,"x") -> 3 | M60: =IFERROR(__xludf.DUMMYFUNCTION("FILTER(AB$52:AB$64, V$52:V$64=INT(RIGHT(A60,1)))"),"Save It For Later") -> Save It For Later | O60: X | R60: x | S60: x | V60: =RANK(AD60,AD$52:AD$64) -> 11 | W60: =IFERROR(__xludf.DUMMYFUNCTION("""COMPUTED_VALUE"""),46132.0) -> 46132 | X60: =IFERROR(__xludf.DUMMYFUNCTION("""COMPUTED_VALUE"""),"Giacomo") -> Giacomo | Y60: =IFERROR(__xludf.DUMMYFUNCTION("""COMPUTED_VALUE"""),3.142857142857143) -> 3.1428571 | Z60: =IFERROR(__xludf.DUMMYFUNCTION("""COMPUTED_VALUE"""),1.8070158058105026) -> 1.8070158 | AA60: =IFERROR(__xludf.DUMMYFUNCTION("""COMPUTED_VALUE"""),3.5) -> 3.5 | AB60: =IFERROR(__xludf.DUMMYFUNCTION("""COMPUTED_VALUE"""),"See You Later") -> See You Later | AC60: =IFERROR(__xludf.DUMMYFUNCTION("""COMPUTED_VALUE"""),"Terrace Martin, Kenyon Dixon") -> Terrace Martin, Kenyon Dixon | AD60: =IF(ISBLANK(W60), "", RANK(Y60, Y$52:Y$64) + RANK(AA60, AA$52:AA$64)/10 + RANK(Z60, Z$52:Z$64)/100) -> 3.25
A61: Seed 7 vs 10 | B61: x | C61: x | F61: X | H61: X | I61: =IFERROR(__xludf.DUMMYFUNCTION("FILTER(AB$52:AB$64, V$52:V$64=INT(MID(A61,6,1)))"),"Space") -> Space | J61: =COUNTIF(B61:H61,"x") -> 4 | K61: =IF(J61>=4,I61,IF(L61>=4,M61,"TBD")) -> Space | L61: =COUNTIF(N61:T61,"x") -> 2 | M61: =IFERROR(__xludf.DUMMYFUNCTION("FILTER(AB$52:AB$64, V$52:V$64=INT(RIGHT(A61,2)))"),"Don't you lie") -> Don't you lie | O61: X | R61: x | V61: =RANK(AD61,AD$52:AD$64) -> 8 | W61: =IFERROR(__xludf.DUMMYFUNCTION("""COMPUTED_VALUE"""),46134.0) -> 46134 | X61: =IFERROR(__xludf.DUMMYFUNCTION("""COMPUTED_VALUE"""),"Flocco") -> Flocco | Y61: =IFERROR(__xludf.DUMMYFUNCTION("""COMPUTED_VALUE"""),2.857142857142857) -> 2.8571429 | Z61: =IFERROR(__xludf.DUMMYFUNCTION("""COMPUTED_VALUE"""),1.8070158058105026) -> 1.8070158 | AA61: =IFERROR(__xludf.DUMMYFUNCTION("""COMPUTED_VALUE"""),3.1666666666666665) -> 3.1666667 | AB61: =IFERROR(__xludf.DUMMYFUNCTION("""COMPUTED_VALUE""")," Bad dreams") -> Bad dreams | AC61: =IFERROR(__xludf.DUMMYFUNCTION("""COMPUTED_VALUE""")," Teddy swims") -> Teddy swims | AD61: =IF(ISBLANK(W61), "", RANK(Y61, Y$52:Y$64) + RANK(AA61, AA$52:AA$64)/10 + RANK(Z61, Z$52:Z$64)/100) -> 5.45
A62: Seed 6 vs 11 | F62: X | G62: X | H62: X | I62: =IFERROR(__xludf.DUMMYFUNCTION("FILTER(AB$52:AB$64, V$52:V$64=INT(MID(A62,6,1)))"),"Dirty Cigarettes ") -> Dirty Cigarettes | J62: =COUNTIF(B62:H62,"x") -> 3 | K62: =IF(J62>=4,I62,IF(L62>=4,M62,"TBD")) -> See You Later | L62: =COUNTIF(N62:T62,"x") -> 4 | M62: =IFERROR(__xludf.DUMMYFUNCTION("FILTER(AB$52:AB$64, V$52:V$64=INT(RIGHT(A62,2)))"),"See You Later") -> See You Later | Q62: X | R62: x | S62: x | T62: x | V62: =RANK(AD62,AD$52:AD$64) -> 13 | W62: =IFERROR(__xludf.DUMMYFUNCTION("""COMPUTED_VALUE"""),46136.0) -> 46136 | X62: =IFERROR(__xludf.DUMMYFUNCTION("""COMPUTED_VALUE"""),"Parker") -> Parker | Y62: =IFERROR(__xludf.DUMMYFUNCTION("""COMPUTED_VALUE"""),3.5714285714285716) -> 3.5714286 | Z62: =IFERROR(__xludf.DUMMYFUNCTION("""COMPUTED_VALUE"""),1.9166296949998198) -> 1.9166297 | AA62: =IFERROR(__xludf.DUMMYFUNCTION("""COMPUTED_VALUE"""),4.0) -> 4 | AB62: =IFERROR(__xludf.DUMMYFUNCTION("""COMPUTED_VALUE"""),"Curame") -> Curame | AC62: =IFERROR(__xludf.DUMMYFUNCTION("""COMPUTED_VALUE"""),"Rauw Alejandro") -> Rauw Alejandro | AD62: =IF(ISBLANK(W62), "", RANK(Y62, Y$52:Y$64) + RANK(AA62, AA$52:AA$64)/10 + RANK(Z62, Z$52:Z$64)/100) -> 1.14
A63: Seed 5 vs 12 | B63: x | C63: x | D63: x | F63: X | G63: X | H63: X | I63: =IFERROR(__xludf.DUMMYFUNCTION("FILTER(AB$52:AB$64, V$52:V$64=INT(MID(A63,6,1)))")," Roommates") -> Roommates | J63: =COUNTIF(B63:H63,"x") -> 6 | K63: =IF(J63>=4,I63,IF(L63>=4,M63,"TBD")) -> Roommates | L63: =COUNTIF(N63:T63,"x") -> 0 | M63: =IFERROR(__xludf.DUMMYFUNCTION("FILTER(AB$52:AB$64, V$52:V$64=INT(RIGHT(A63,2)))"),"Meat") -> Meat | V63: =RANK(AD63,AD$52:AD$64) -> 6 | W63: =IFERROR(__xludf.DUMMYFUNCTION("""COMPUTED_VALUE"""),46139.0) -> 46139 | X63: =IFERROR(__xludf.DUMMYFUNCTION("""COMPUTED_VALUE"""),"Weston") -> Weston | Y63: =IFERROR(__xludf.DUMMYFUNCTION("""COMPUTED_VALUE"""),2.3333333333333335) -> 2.3333333 | Z63: =IFERROR(__xludf.DUMMYFUNCTION("""COMPUTED_VALUE"""),2.1343747458109497) -> 2.1343747 | AA63: =IFERROR(__xludf.DUMMYFUNCTION("""COMPUTED_VALUE"""),2.6) -> 2.6 | AB63: =IFERROR(__xludf.DUMMYFUNCTION("""COMPUTED_VALUE"""),"Dirty Cigarettes ") -> Dirty Cigarettes | AC63: =IFERROR(__xludf.DUMMYFUNCTION("""COMPUTED_VALUE"""),"Beach Slang") -> Beach Slang | AD63: =IF(ISBLANK(W63), "", RANK(Y63, Y$52:Y$64) + RANK(AA63, AA$52:AA$64)/10 + RANK(Z63, Z$52:Z$64)/100) -> 8.81
A64: Seed 4 vs 13 | B64: x | D64: x | F64: X | G64: X | H64: X | I64: =IFERROR(__xludf.DUMMYFUNCTION("FILTER(AB$52:AB$64, V$52:V$64=INT(MID(A64,6,1)))"),"Superstar (feat. Matthew Santos)") -> Superstar (feat. Matthew Santos) | J64: =COUNTIF(B64:H64,"x") -> 5 | K64: =IF(J64>=4,I64,IF(L64>=4,M64,"TBD")) -> Superstar (feat. Matthew Santos) | L64: =COUNTIF(N64:T64,"x") -> 1 | M64: =IFERROR(__xludf.DUMMYFUNCTION("FILTER(AB$52:AB$64, V$52:V$64=INT(RIGHT(A64,2)))"),"Curame") -> Curame | S64: x | V64: =RANK(AD64,AD$52:AD$64) -> 5 | W64: =IFERROR(__xludf.DUMMYFUNCTION("""COMPUTED_VALUE"""),46141.0) -> 46141 | X64: =IFERROR(__xludf.DUMMYFUNCTION("""COMPUTED_VALUE"""),"Flocco") -> Flocco | Y64: =IFERROR(__xludf.DUMMYFUNCTION("""COMPUTED_VALUE"""),2.1666666666666665) -> 2.1666667 | Z64: =IFERROR(__xludf.DUMMYFUNCTION("""COMPUTED_VALUE"""),1.7716909687891083) -> 1.771691 | AA64: =IFERROR(__xludf.DUMMYFUNCTION("""COMPUTED_VALUE"""),2.4) -> 2.4 | AB64: =IFERROR(__xludf.DUMMYFUNCTION("""COMPUTED_VALUE""")," Roommates") -> Roommates | AC64: =IFERROR(__xludf.DUMMYFUNCTION("""COMPUTED_VALUE""")," Malcolm Todd") -> Malcolm Todd | AD64: =IF(ISBLANK(W64), "", RANK(Y64, Y$52:Y$64) + RANK(AA64, AA$52:AA$64)/10 + RANK(Z64, Z$52:Z$64)/100) -> 9.97
A68: May | V68: Seeding | W68: Date | X68: Poster | Y68: Average | Z68: STDEV | AA68: Peer Rank | AB68: Song | AC68: Artist
A69: Description | B69: L | C69: P | D69: G | E69: R | F69: T | G69: W | H69: F | I69: Song 1 | J69: Score 1 | K69: Winner | L69: Score 2 | M69: Song 2 | N69: F | O69: W | P69: T | Q69: R | R69: G | S69: P | T69: L | V69: =RANK(AD69,AD$69:AD$81) -> 13 | W69: =IFERROR(__xludf.DUMMYFUNCTION("FILTER(Rankings!D:J, Rankings!D:D >= DATE(2026,5,1), Rankings!D:D < DATE(2026,6,1), Rankings!U:U = TRUE)"),46143.0) -> 46143 | X69: =IFERROR(__xludf.DUMMYFUNCTION("""COMPUTED_VALUE"""),"Flocco") -> Flocco | Y69: =IFERROR(__xludf.DUMMYFUNCTION("""COMPUTED_VALUE"""),2.8333333333333335) -> 2.8333333 | Z69: =IFERROR(__xludf.DUMMYFUNCTION("""COMPUTED_VALUE"""),1.6749792701868151) -> 1.6749793 | AA69: =IFERROR(__xludf.DUMMYFUNCTION("""COMPUTED_VALUE"""),3.2) -> 3.2 | AB69: =IFERROR(__xludf.DUMMYFUNCTION("""COMPUTED_VALUE"""),"Red Red Wine") -> Red Red Wine | AC69: =IFERROR(__xludf.DUMMYFUNCTION("""COMPUTED_VALUE""")," UB40") -> UB40 | AD69: =IF(ISBLANK(W69), "", RANK(Y69, Y$69:Y$81) + RANK(AA69, AA$69:AA$81)/10 + RANK(Z69, Z$69:Z$81)/100) -> 1.11
A70: Seed 1 vs 2 | I70: =K72 -> TBD | J70: =COUNTIF(B70:H70,"x") -> 0 | K70: =IF(J70>=4,I70,IF(L70>=4,M70,"TBD")) -> TBD | L70: =COUNTIF(N70:T70,"x") -> 0 | M70: =K71 -> TBD | V70: =RANK(AD70,AD$69:AD$81) -> 6 | W70: =IFERROR(__xludf.DUMMYFUNCTION("""COMPUTED_VALUE"""),46146.0) -> 46146 | X70: =IFERROR(__xludf.DUMMYFUNCTION("""COMPUTED_VALUE"""),"Weston") -> Weston | Y70: =IFERROR(__xludf.DUMMYFUNCTION("""COMPUTED_VALUE"""),2.0) -> 2 | Z70: =IFERROR(__xludf.DUMMYFUNCTION("""COMPUTED_VALUE"""),0.6324555320336759) -> 0.63245553 | AA70: =IFERROR(__xludf.DUMMYFUNCTION("""COMPUTED_VALUE"""),2.0) -> 2 | AB70: =IFERROR(__xludf.DUMMYFUNCTION("""COMPUTED_VALUE"""),"Out of Sight") -> Out of Sight | AC70: =IFERROR(__xludf.DUMMYFUNCTION("""COMPUTED_VALUE"""),"Hundredth") -> Hundredth | AD70: =IF(ISBLANK(W70), "", RANK(Y70, Y$69:Y$81) + RANK(AA70, AA$69:AA$81)/10 + RANK(Z70, Z$69:Z$81)/100) -> 6.9
A71: Seed 2 vs 3 | I71: =K75 -> She Knows Too Much | J71: =COUNTIF(B71:H71,"x") -> 0 | K71: =IF(J71>=4,I71,IF(L71>=4,M71,"TBD")) -> TBD | L71: =COUNTIF(N71:T71,"x") -> 0 | M71: =K74 -> TBD | V71: =RANK(AD71,AD$69:AD$81) -> 5 | W71: =IFERROR(__xludf.DUMMYFUNCTION("""COMPUTED_VALUE"""),46148.0) -> 46148 | X71: =IFERROR(__xludf.DUMMYFUNCTION("""COMPUTED_VALUE"""),"Parker") -> Parker | Y71: =IFERROR(__xludf.DUMMYFUNCTION("""COMPUTED_VALUE"""),1.6) -> 1.6 | Z71: =IFERROR(__xludf.DUMMYFUNCTION("""COMPUTED_VALUE"""),0.8) -> 0.8 | AA71: =IFERROR(__xludf.DUMMYFUNCTION("""COMPUTED_VALUE"""),1.75) -> 1.75 | AB71: =IFERROR(__xludf.DUMMYFUNCTION("""COMPUTED_VALUE"""),"Broken Bones") -> Broken Bones | AC71: =IFERROR(__xludf.DUMMYFUNCTION("""COMPUTED_VALUE"""),"Anti-Flag") -> Anti-Flag | AD71: =IF(ISBLANK(W71), "", RANK(Y71, Y$69:Y$81) + RANK(AA71, AA$69:AA$81)/10 + RANK(Z71, Z$69:Z$81)/100) -> 9.98
A72: Seed 1 vs 4 | I72: =K76 -> Good Bye Boogie Dance | J72: =COUNTIF(B72:H72,"x") -> 0 | K72: =IF(J72>=4,I72,IF(L72>=4,M72,"TBD")) -> TBD | L72: =COUNTIF(N72:T72,"x") -> 0 | M72: =K73 -> TBD | V72: =RANK(AD72,AD$69:AD$81) -> 1 | W72: =IFERROR(__xludf.DUMMYFUNCTION("""COMPUTED_VALUE"""),46150.0) -> 46150 | X72: =IFERROR(__xludf.DUMMYFUNCTION("""COMPUTED_VALUE"""),"Weston") -> Weston | Y72: =IFERROR(__xludf.DUMMYFUNCTION("""COMPUTED_VALUE"""),1.2) -> 1.2 | Z72: =IFERROR(__xludf.DUMMYFUNCTION("""COMPUTED_VALUE"""),0.4) -> 0.4 | AA72: =IFERROR(__xludf.DUMMYFUNCTION("""COMPUTED_VALUE"""),1.25) -> 1.25 | AB72: =IFERROR(__xludf.DUMMYFUNCTION("""COMPUTED_VALUE"""),"Good Bye Boogie Dance") -> Good Bye Boogie Dance | AC72: =IFERROR(__xludf.DUMMYFUNCTION("""COMPUTED_VALUE"""),"Anri") -> Anri | AD72: =IF(ISBLANK(W72), "", RANK(Y72, Y$69:Y$81) + RANK(AA72, AA$69:AA$81)/10 + RANK(Z72, Z$69:Z$81)/100) -> 14.43
A73: Seed 4 vs 5 | B73: x | D73: x | I73: =K81 -> Crash | J73: =COUNTIF(B73:H73,"x") -> 2 | K73: =IF(J73>=4,I73,IF(L73>=4,M73,"TBD")) -> TBD | L73: =COUNTIF(N73:T73,"x") -> 3 | M73: =K80 -> Broken Bones | O73: X | P73: X | S73: x | V73: =RANK(AD73,AD$69:AD$81) -> 9 | W73: =IFERROR(__xludf.DUMMYFUNCTION("""COMPUTED_VALUE"""),46153.0) -> 46153 | X73: =IFERROR(__xludf.DUMMYFUNCTION("""COMPUTED_VALUE"""),"Giacomo") -> Giacomo | Y73: =IFERROR(__xludf.DUMMYFUNCTION("""COMPUTED_VALUE"""),2.2) -> 2.2 | Z73: =IFERROR(__xludf.DUMMYFUNCTION("""COMPUTED_VALUE"""),1.469693845669907) -> 1.4696938 | AA73: =IFERROR(__xludf.DUMMYFUNCTION("""COMPUTED_VALUE"""),2.5) -> 2.5 | AB73: =IFERROR(__xludf.DUMMYFUNCTION("""COMPUTED_VALUE"""),"costly") -> costly | AC73: =IFERROR(__xludf.DUMMYFUNCTION("""COMPUTED_VALUE"""),"MARCO PLUS") -> MARCO PLUS | AD73: =IF(ISBLANK(W73), "", RANK(Y73, Y$69:Y$81) + RANK(AA73, AA$69:AA$81)/10 + RANK(Z73, Z$69:Z$81)/100) -> 5.53
A74: Seed 3 vs 6 | B74: x | C74: x | D74: x | I74: =IFERROR(__xludf.DUMMYFUNCTION("FILTER(AB$69:AB$81, V$69:V$81=INT(MID(A74,6,1)))"),"All I Really Want") -> All I Really Want | J74: =COUNTIF(B74:H74,"x") -> 3 | K74: =IF(J74>=4,I74,IF(L74>=4,M74,"TBD")) -> TBD | L74: =COUNTIF(N74:T74,"x") -> 2 | M74: =K79 -> Out of Sight | O74: X | P74: X | V74: =RANK(AD74,AD$69:AD$81) -> 2 | W74: =IFERROR(__xludf.DUMMYFUNCTION("""COMPUTED_VALUE"""),46155.0) -> 46155 | X74: =IFERROR(__xludf.DUMMYFUNCTION("""COMPUTED_VALUE"""),"Logan") -> Logan | Y74: =IFERROR(__xludf.DUMMYFUNCTION("""COMPUTED_VALUE"""),1.4) -> 1.4 | Z74: =IFERROR(__xludf.DUMMYFUNCTION("""COMPUTED_VALUE"""),0.4898979485566356) -> 0.48989795 | AA74: =IFERROR(__xludf.DUMMYFUNCTION("""COMPUTED_VALUE"""),1.5) -> 1.5 | AB74: =IFERROR(__xludf.DUMMYFUNCTION("""COMPUTED_VALUE"""),"2SIDED") -> 2SIDED | AC74: =IFERROR(__xludf.DUMMYFUNCTION("""COMPUTED_VALUE"""),"Arlo Parks") -> Arlo Parks | AD74: =IF(ISBLANK(W74), "", RANK(Y74, Y$69:Y$81) + RANK(AA74, AA$69:AA$81)/10 + RANK(Z74, Z$69:Z$81)/100) -> 13.32
A75: Seed 2 vs 7 | B75: x | G75: X | I75: =IFERROR(__xludf.DUMMYFUNCTION("FILTER(AB$69:AB$81, V$69:V$81=INT(MID(A75,6,1)))"),"2SIDED") -> 2SIDED | J75: =COUNTIF(B75:H75,"x") -> 2 | K75: =IF(J75>=4,I75,IF(L75>=4,M75,"TBD")) -> She Knows Too Much | L75: =COUNTIF(N75:T75,"x") -> 4 | M75: =K78 -> She Knows Too Much | N75: X | P75: X | R75: x | S75: x | V75: =RANK(AD75,AD$69:AD$81) -> 8 | W75: =IFERROR(__xludf.DUMMYFUNCTION("""COMPUTED_VALUE"""),46157.0) -> 46157 | X75: =IFERROR(__xludf.DUMMYFUNCTION("""COMPUTED_VALUE"""),"Weston") -> Weston | Y75: =IFERROR(__xludf.DUMMYFUNCTION("""COMPUTED_VALUE"""),2.0) -> 2 | Z75: =IFERROR(__xludf.DUMMYFUNCTION("""COMPUTED_VALUE"""),0.6324555320336759) -> 0.63245553 | AA75: =IFERROR(__xludf.DUMMYFUNCTION("""COMPUTED_VALUE"""),2.25) -> 2.25 | AB75: =IFERROR(__xludf.DUMMYFUNCTION("""COMPUTED_VALUE"""),"Stare At The Sun") -> Stare At The Sun | AC75: =IFERROR(__xludf.DUMMYFUNCTION("""COMPUTED_VALUE"""),"Thrice") -> Thrice | AD75: =IF(ISBLANK(W75), "", RANK(Y75, Y$69:Y$81) + RANK(AA75, AA$69:AA$81)/10 + RANK(Z75, Z$69:Z$81)/100) -> 6.7
A76: Seed 1 vs 8 | B76: x | E76: X | F76: x | G76: X | I76: =IFERROR(__xludf.DUMMYFUNCTION("FILTER(AB$69:AB$81, V$69:V$81=INT(MID(A76,6,1)))"),"Good Bye Boogie Dance") -> Good Bye Boogie Dance | J76: =COUNTIF(B76:H76,"x") -> 4 | K76: =IF(J76>=4,I76,IF(L76>=4,M76,"TBD")) -> Good Bye Boogie Dance | L76: =COUNTIF(N76:T76,"x") -> 3 | M76: =K77 -> costly | N76: X | R76: x | S76: x | V76: =RANK(AD76,AD$69:AD$81) -> 4 | W76: =IFERROR(__xludf.DUMMYFUNCTION("""COMPUTED_VALUE"""),46160.0) -> 46160 | X76: =IFERROR(__xludf.DUMMYFUNCTION("""COMPUTED_VALUE"""),"Giacomo") -> Giacomo | Y76: =IFERROR(__xludf.DUMMYFUNCTION("""COMPUTED_VALUE"""),1.5) -> 1.5 | Z76: =IFERROR(__xludf.DUMMYFUNCTION("""COMPUTED_VALUE"""),1.118033988749895) -> 1.118034 | AA76: =IFERROR(__xludf.DUMMYFUNCTION("""COMPUTED_VALUE"""),1.6) -> 1.6 | AB76: =IFERROR(__xludf.DUMMYFUNCTION("""COMPUTED_VALUE"""),"Crash") -> Crash | AC76: =IFERROR(__xludf.DUMMYFUNCTION("""COMPUTED_VALUE"""),"Saba, No ID, Raphael Saadiq, Kelly Rowland") -> Saba, No ID, Raphael Saadiq, Kelly Rowland | AD76: =IF(ISBLANK(W76), "", RANK(Y76, Y$69:Y$81) + RANK(AA76, AA$69:AA$81)/10 + RANK(Z76, Z$69:Z$81)/100) -> 11.06
A77: Seed 8 vs 9 | F77: X | G77: x | I77: =IFERROR(__xludf.DUMMYFUNCTION("FILTER(AB$69:AB$81, V$69:V$81=INT(MID(A77,6,1)))"),"Stare At The Sun") -> Stare At The Sun | J77: =COUNTIF(B77:H77,"x") -> 2 | K77: =IF(J77>=4,I77,IF(L77>=4,M77,"TBD")) -> costly | L77: =COUNTIF(N77:T77,"x") -> 4 | M77: =IFERROR(__xludf.DUMMYFUNCTION("FILTER(AB$69:AB$81, V$69:V$81=INT(RIGHT(A77,1)))"),"costly") -> costly | N77: X | R77: x | S77: x | T77: x | V77: =RANK(AD77,AD$69:AD$81) -> 12 | W77: =IFERROR(__xludf.DUMMYFUNCTION("""COMPUTED_VALUE"""),46162.0) -> 46162 | X77: =IFERROR(__xludf.DUMMYFUNCTION("""COMPUTED_VALUE"""),"Flocco") -> Flocco | Y77: =IFERROR(__xludf.DUMMYFUNCTION("""COMPUTED_VALUE"""),2.6666666666666665) -> 2.6666667 | Z77: =IFERROR(__xludf.DUMMYFUNCTION("""COMPUTED_VALUE"""),1.1055415967851332) -> 1.1055416 | AA77: =IFERROR(__xludf.DUMMYFUNCTION("""COMPUTED_VALUE"""),2.8) -> 2.8 | AB77: =IFERROR(__xludf.DUMMYFUNCTION("""COMPUTED_VALUE"""),"Movies") -> Movies | AC77: =IFERROR(__xludf.DUMMYFUNCTION("""COMPUTED_VALUE"""),"Alfie Templeman") -> Alfie Templeman | AD77: =IF(ISBLANK(W77), "", RANK(Y77, Y$69:Y$81) + RANK(AA77, AA$69:AA$81)/10 + RANK(Z77, Z$69:Z$81)/100) -> 2.27
A78: Seed 7 vs 10 | B78: x | H78: X | I78: =IFERROR(__xludf.DUMMYFUNCTION("FILTER(AB$69:AB$81, V$69:V$81=INT(MID(A78,6,1)))"),"Set my heart on fire") -> Set my heart on fire | J78: =COUNTIF(B78:H78,"x") -> 2 | K78: =IF(J78>=4,I78,IF(L78>=4,M78,"TBD")) -> She Knows Too Much | L78: =COUNTIF(N78:T78,"x") -> 4 | M78: =IFERROR(__xludf.DUMMYFUNCTION("FILTER(AB$69:AB$81, V$69:V$81=INT(RIGHT(A78,2)))"),"She Knows Too Much") -> She Knows Too Much | O78: x | P78: X | R78: x | S78: x | V78: =RANK(AD78,AD$69:AD$81) -> 3 | W78: =IFERROR(__xludf.DUMMYFUNCTION("""COMPUTED_VALUE"""),46164.0) -> 46164 | X78: =IFERROR(__xludf.DUMMYFUNCTION("""COMPUTED_VALUE"""),"Weston") -> Weston | Y78: =IFERROR(__xludf.DUMMYFUNCTION("""COMPUTED_VALUE"""),1.5) -> 1.5 | Z78: =IFERROR(__xludf.DUMMYFUNCTION("""COMPUTED_VALUE"""),0.7637626158259734) -> 0.76376262 | AA78: =IFERROR(__xludf.DUMMYFUNCTION("""COMPUTED_VALUE"""),1.6) -> 1.6 | AB78: =IFERROR(__xludf.DUMMYFUNCTION("""COMPUTED_VALUE"""),"All I Really Want") -> All I Really Want | AC78: =IFERROR(__xludf.DUMMYFUNCTION("""COMPUTED_VALUE"""),"Yes Boone") -> Yes Boone | AD78: =IF(ISBLANK(W78), "", RANK(Y78, Y$69:Y$81) + RANK(AA78, AA$69:AA$81)/10 + RANK(Z78, Z$69:Z$81)/100) -> 11.09
A79: Seed 6 vs 11 | E79: X | F79: X | G79: x | H79: X | I79: =IFERROR(__xludf.DUMMYFUNCTION("FILTER(AB$69:AB$81, V$69:V$81=INT(MID(A79,6,1)))"),"Out of Sight") -> Out of Sight | J79: =COUNTIF(B79:H79,"x") -> 4 | K79: =IF(J79>=4,I79,IF(L79>=4,M79,"TBD")) -> Out of Sight | L79: =COUNTIF(N79:T79,"x") -> 3 | M79: =IFERROR(__xludf.DUMMYFUNCTION("FILTER(AB$69:AB$81, V$69:V$81=INT(RIGHT(A79,2)))"),"Joga Pra Lua") -> Joga Pra Lua | R79: x | S79: x | T79: x | V79: =RANK(AD79,AD$69:AD$81) -> 10 | W79: =IFERROR(__xludf.DUMMYFUNCTION("""COMPUTED_VALUE"""),46167.0) -> 46167 | X79: =IFERROR(__xludf.DUMMYFUNCTION("""COMPUTED_VALUE"""),"Giacomo") -> Giacomo | Y79: =IFERROR(__xludf.DUMMYFUNCTION("""COMPUTED_VALUE"""),2.3333333333333335) -> 2.3333333 | Z79: =IFERROR(__xludf.DUMMYFUNCTION("""COMPUTED_VALUE"""),1.3743685418725535) -> 1.3743685 | AA79: =IFERROR(__xludf.DUMMYFUNCTION("""COMPUTED_VALUE"""),2.6) -> 2.6 | AB79: =IFERROR(__xludf.DUMMYFUNCTION("""COMPUTED_VALUE"""),"She Knows Too Much") -> She Knows Too Much | AC79: =IFERROR(__xludf.DUMMYFUNCTION("""COMPUTED_VALUE"""),"Thundercat, Mac Miller") -> Thundercat, Mac Miller | AD79: =IF(ISBLANK(W79), "", RANK(Y79, Y$69:Y$81) + RANK(AA79, AA$69:AA$81)/10 + RANK(Z79, Z$69:Z$81)/100) -> 4.45
A80: Seed 5 vs 12 | C80: x | E80: X | F80: X | G80: x | I80: =IFERROR(__xludf.DUMMYFUNCTION("FILTER(AB$69:AB$81, V$69:V$81=INT(MID(A80,6,1)))"),"Broken Bones") -> Broken Bones | J80: =COUNTIF(B80:H80,"x") -> 4 | K80: =IF(J80>=4,I80,IF(L80>=4,M80,"TBD")) -> Broken Bones | L80: =COUNTIF(N80:T80,"x") -> 3 | M80: =IFERROR(__xludf.DUMMYFUNCTION("FILTER(AB$69:AB$81, V$69:V$81=INT(RIGHT(A80,2)))"),"Movies") -> Movies | N80: X | R80: x | T80: x | V80: =RANK(AD80,AD$69:AD$81) -> 7 | W80: =IFERROR(__xludf.DUMMYFUNCTION("""COMPUTED_VALUE"""),46169.0) -> 46169 | X80: =IFERROR(__xludf.DUMMYFUNCTION("""COMPUTED_VALUE"""),"Flocco") -> Flocco | Y80: =IFERROR(__xludf.DUMMYFUNCTION("""COMPUTED_VALUE"""),2.0) -> 2 | Z80: =IFERROR(__xludf.DUMMYFUNCTION("""COMPUTED_VALUE"""),1.4142135623730951) -> 1.4142136 | AA80: =IFERROR(__xludf.DUMMYFUNCTION("""COMPUTED_VALUE"""),2.2) -> 2.2 | AB80: =IFERROR(__xludf.DUMMYFUNCTION("""COMPUTED_VALUE"""),"Set my heart on fire") -> Set my heart on fire | AC80: =IFERROR(__xludf.DUMMYFUNCTION("""COMPUTED_VALUE"""),"Majestic, the jammin kid, Celine Dion") -> Majestic, the jammin kid, Celine Dion | AD80: =IF(ISBLANK(W80), "", RANK(Y80, Y$69:Y$81) + RANK(AA80, AA$69:AA$81)/10 + RANK(Z80, Z$69:Z$81)/100) -> 6.74
A81: Seed 4 vs 13 | B81: x | C81: x | D81: x | F81: X | G81: x | I81: =IFERROR(__xludf.DUMMYFUNCTION("FILTER(AB$69:AB$81, V$69:V$81=INT(MID(A81,6,1)))"),"Crash") -> Crash | J81: =COUNTIF(B81:H81,"x") -> 5 | K81: =IF(J81>=4,I81,IF(L81>=4,M81,"TBD")) -> Crash | L81: =COUNTIF(N81:T81,"x") -> 1 | M81: =IFERROR(__xludf.DUMMYFUNCTION("FILTER(AB$69:AB$81, V$69:V$81=INT(RIGHT(A81,2)))"),"Red Red Wine") -> Red Red Wine | N81: X | V81: =RANK(AD81,AD$69:AD$81) -> 11 | W81: =IFERROR(__xludf.DUMMYFUNCTION("""COMPUTED_VALUE"""),46171.0) -> 46171 | X81: =IFERROR(__xludf.DUMMYFUNCTION("""COMPUTED_VALUE"""),"Parker") -> Parker | Y81: =IFERROR(__xludf.DUMMYFUNCTION("""COMPUTED_VALUE"""),2.5) -> 2.5 | Z81: =IFERROR(__xludf.DUMMYFUNCTION("""COMPUTED_VALUE"""),1.607275126832159) -> 1.6072751 | AA81: =IFERROR(__xludf.DUMMYFUNCTION("""COMPUTED_VALUE"""),2.8) -> 2.8 | AB81: =IFERROR(__xludf.DUMMYFUNCTION("""COMPUTED_VALUE"""),"Joga Pra Lua") -> Joga Pra Lua | AC81: =IFERROR(__xludf.DUMMYFUNCTION("""COMPUTED_VALUE"""),"Anitta, DENNIS, PEDRO SAMPAIO (Brazil)") -> Anitta, DENNIS, PEDRO SAMPAIO (Brazil) | AD81: =IF(ISBLANK(W81), "", RANK(Y81, Y$69:Y$81) + RANK(AA81, AA$69:AA$81)/10 + RANK(Z81, Z$69:Z$81)/100) -> 3.22
A85: June | V85: Seeding | W85: Date | X85: Poster | Y85: Average | Z85: STDEV | AA85: Peer Rank | AB85: Song | AC85: Artist | AD85: Score
A86: Description | B86: L | C86: P | D86: G | E86: R | F86: T | G86: W | H86: F | I86: Song 1 | J86: Score 1 | K86: Winner | L86: Score 2 | M86: Song 2 | N86: F | O86: W | P86: T | Q86: R | R86: G | S86: P | T86: L | V86: =RANK(AD86,AD$86:AD$98) -> 10 | W86: =IFERROR(__xludf.DUMMYFUNCTION("FILTER(Rankings!D:J, Rankings!D:D >= DATE(2026,6,1), Rankings!D:D < DATE(2026,7,1), Rankings!U:U = TRUE)"),46174.0) -> 46174 | X86: =IFERROR(__xludf.DUMMYFUNCTION("""COMPUTED_VALUE"""),"Logan") -> Logan | Y86: =IFERROR(__xludf.DUMMYFUNCTION("""COMPUTED_VALUE"""),2.3333333333333335) -> 2.3333333 | Z86: =IFERROR(__xludf.DUMMYFUNCTION("""COMPUTED_VALUE"""),1.1055415967851332) -> 1.1055416 | AA86: =IFERROR(__xludf.DUMMYFUNCTION("""COMPUTED_VALUE"""),2.6) -> 2.6 | AB86: =IFERROR(__xludf.DUMMYFUNCTION("""COMPUTED_VALUE"""),"over it") -> over it | AC86: =IFERROR(__xludf.DUMMYFUNCTION("""COMPUTED_VALUE"""),"joss lockwood") -> joss lockwood | AD86: =IF(ISBLANK(W86), "", RANK(Y86, Y$86:Y$98) + RANK(AA86, AA$86:AA$98)/10 + RANK(Z86, Z$86:Z$98)/100) -> 4.45
A87: Seed 1 vs 2 | I87: =K89 -> TBD | J87: =COUNTIF(B87:H87,"x") -> 0 | K87: =IF(J87>=4,I87,IF(L87>=4,M87,"TBD")) -> TBD | L87: =COUNTIF(N87:T87,"x") -> 0 | M87: =K88 -> TBD | V87: =RANK(AD87,AD$86:AD$98) -> 9 | W87: =IFERROR(__xludf.DUMMYFUNCTION("""COMPUTED_VALUE"""),46176.0) -> 46176 | X87: =IFERROR(__xludf.DUMMYFUNCTION("""COMPUTED_VALUE"""),"Parker") -> Parker | Y87: =IFERROR(__xludf.DUMMYFUNCTION("""COMPUTED_VALUE"""),2.0) -> 2 | Z87: =IFERROR(__xludf.DUMMYFUNCTION("""COMPUTED_VALUE"""),1.5275252316519468) -> 1.5275252 | AA87: =IFERROR(__xludf.DUMMYFUNCTION("""COMPUTED_VALUE"""),2.2) -> 2.2 | AB87: =IFERROR(__xludf.DUMMYFUNCTION("""COMPUTED_VALUE"""),"AGAIN") -> AGAIN | AC87: =IFERROR(__xludf.DUMMYFUNCTION("""COMPUTED_VALUE"""),"Feid, Sky Rompiendo, Majid Jordan") -> Feid, Sky Rompiendo, Majid Jordan | AD87: =IF(ISBLANK(W87), "", RANK(Y87, Y$86:Y$98) + RANK(AA87, AA$86:AA$98)/10 + RANK(Z87, Z$86:Z$98)/100) -> 5.53
A88: Seed 2 vs 3 | B88: x | D88: x | I88: =K92 -> over it | J88: =COUNTIF(B88:H88,"x") -> 2 | K88: =IF(J88>=4,I88,IF(L88>=4,M88,"TBD")) -> TBD | L88: =COUNTIF(N88:T88,"x") -> 3 | M88: =K91 -> No more regrets | O88: x | P88: X | S88: x | V88: =RANK(AD88,AD$86:AD$98) -> 6 | W88: =IFERROR(__xludf.DUMMYFUNCTION("""COMPUTED_VALUE"""),46178.0) -> 46178 | X88: =IFERROR(__xludf.DUMMYFUNCTION("""COMPUTED_VALUE"""),"Giacomo") -> Giacomo | Y88: =IFERROR(__xludf.DUMMYFUNCTION("""COMPUTED_VALUE"""),1.6666666666666667) -> 1.6666667 | Z88: =IFERROR(__xludf.DUMMYFUNCTION("""COMPUTED_VALUE"""),0.9428090415820634) -> 0.94280904 | AA88: =IFERROR(__xludf.DUMMYFUNCTION("""COMPUTED_VALUE"""),1.8) -> 1.8 | AB88: =IFERROR(__xludf.DUMMYFUNCTION("""COMPUTED_VALUE"""),"TRICERATOPS") -> TRICERATOPS | AC88: =IFERROR(__xludf.DUMMYFUNCTION("""COMPUTED_VALUE"""),"Action Bronson, Paul Wall, Lil Yachty") -> Action Bronson, Paul Wall, Lil Yachty | AD88: =IF(ISBLANK(W88), "", RANK(Y88, Y$86:Y$98) + RANK(AA88, AA$86:AA$98)/10 + RANK(Z88, Z$86:Z$98)/100) -> 8.66
A89: Seed 1 vs 4 | C89: x | G89: x | I89: =K93 -> AGAIN | J89: =COUNTIF(B89:H89,"x") -> 2 | K89: =IF(J89>=4,I89,IF(L89>=4,M89,"TBD")) -> TBD | L89: =COUNTIF(N89:T89,"x") -> 1 | M89: =K90 -> Oxygen | R89: x | V89: =RANK(AD89,AD$86:AD$98) -> 5 | W89: =IFERROR(__xludf.DUMMYFUNCTION("""COMPUTED_VALUE"""),46181.0) -> 46181 | X89: =IFERROR(__xludf.DUMMYFUNCTION("""COMPUTED_VALUE"""),"Logan") -> Logan | Y89: =IFERROR(__xludf.DUMMYFUNCTION("""COMPUTED_VALUE"""),1.6666666666666667) -> 1.6666667 | Z89: =IFERROR(__xludf.DUMMYFUNCTION("""COMPUTED_VALUE"""),0.7453559924999298) -> 0.74535599 | AA89: =IFERROR(__xludf.DUMMYFUNCTION("""COMPUTED_VALUE"""),1.6) -> 1.6 | AB89: =IFERROR(__xludf.DUMMYFUNCTION("""COMPUTED_VALUE"""),"Oxygen") -> Oxygen | AC89: =IFERROR(__xludf.DUMMYFUNCTION("""COMPUTED_VALUE"""),"Porch Light") -> Porch Light | AD89: =IF(ISBLANK(W89), "", RANK(Y89, Y$86:Y$98) + RANK(AA89, AA$86:AA$98)/10 + RANK(Z89, Z$86:Z$98)/100) -> 8.99
A90: Seed 4 vs 5 | G90: X | I90: =K98 -> Somedays | J90: =COUNTIF(B90:H90,"x") -> 1 | K90: =IF(J90>=4,I90,IF(L90>=4,M90,"TBD")) -> Oxygen | L90: =COUNTIF(N90:T90,"x") -> 4 | M90: =K97 -> Oxygen | P90: X | R90: x | S90: x | T90: x | V90: =RANK(AD90,AD$86:AD$98) -> 1 | W90: =IFERROR(__xludf.DUMMYFUNCTION("""COMPUTED_VALUE"""),46183.0) -> 46183 | X90: =IFERROR(__xludf.DUMMYFUNCTION("""COMPUTED_VALUE"""),"Parker") -> Parker | Y90: =IFERROR(__xludf.DUMMYFUNCTION("""COMPUTED_VALUE"""),1.3333333333333333) -> 1.3333333 | Z90: =IFERROR(__xludf.DUMMYFUNCTION("""COMPUTED_VALUE"""),0.4714045207910317) -> 0.47140452 | AA90: =IFERROR(__xludf.DUMMYFUNCTION("""COMPUTED_VALUE"""),1.4) -> 1.4 | AB90: =IFERROR(__xludf.DUMMYFUNCTION("""COMPUTED_VALUE"""),"Otra Atardecer") -> Otra Atardecer | AC90: =IFERROR(__xludf.DUMMYFUNCTION("""COMPUTED_VALUE"""),"Bad Bunny, The Marias") -> Bad Bunny, The Marias | AD90: =IF(ISBLANK(W90), "", RANK(Y90, Y$86:Y$98) + RANK(AA90, AA$86:AA$98)/10 + RANK(Z90, Z$86:Z$98)/100) -> 13.32
A91: Seed 3 vs 6 | B91: x | C91: x | D91: x | F91: X | G91: X | H91: X | I91: =IFERROR(__xludf.DUMMYFUNCTION("FILTER(AB$86:AB$98, V$86:V$98=INT(MID(A91,6,1)))"),"No more regrets") -> No more regrets | J91: =COUNTIF(B91:H91,"x") -> 6 | K91: =IF(J91>=4,I91,IF(L91>=4,M91,"TBD")) -> No more regrets | L91: =COUNTIF(N91:T91,"x") -> 0 | M91: =K96 -> Face My Fears - KINGDOM Orchestra Instrumental Version | V91: =RANK(AD91,AD$86:AD$98) -> 4 | W91: =IFERROR(__xludf.DUMMYFUNCTION("""COMPUTED_VALUE"""),46185.0) -> 46185 | X91: =IFERROR(__xludf.DUMMYFUNCTION("""COMPUTED_VALUE"""),"Flocco") -> Flocco | Y91: =IFERROR(__xludf.DUMMYFUNCTION("""COMPUTED_VALUE"""),1.6666666666666667) -> 1.6666667 | Z91: =IFERROR(__xludf.DUMMYFUNCTION("""COMPUTED_VALUE"""),0.4714045207910317) -> 0.47140452 | AA91: =IFERROR(__xludf.DUMMYFUNCTION("""COMPUTED_VALUE"""),1.6) -> 1.6 | AB91: =IFERROR(__xludf.DUMMYFUNCTION("""COMPUTED_VALUE"""),"All the small things") -> All the small things | AC91: =IFERROR(__xludf.DUMMYFUNCTION("""COMPUTED_VALUE"""),"Blink 182") -> Blink 182 | AD91: =IF(ISBLANK(W91), "", RANK(Y91, Y$86:Y$98) + RANK(AA91, AA$86:AA$98)/10 + RANK(Z91, Z$86:Z$98)/100) -> 9.02
A92: Seed 2 vs 7 | F92: X | G92: x | I92: =IFERROR(__xludf.DUMMYFUNCTION("FILTER(AB$86:AB$98, V$86:V$98=INT(MID(A92,6,1)))"),"Material Lover") -> Material Lover | J92: =COUNTIF(B92:H92,"x") -> 2 | K92: =IF(J92>=4,I92,IF(L92>=4,M92,"TBD")) -> over it | L92: =COUNTIF(N92:T92,"x") -> 4 | M92: =K95 -> over it | N92: X | R92: x | S92: x | T92: x | V92: =RANK(AD92,AD$86:AD$98) -> 12 | W92: =IFERROR(__xludf.DUMMYFUNCTION("""COMPUTED_VALUE"""),46188.0) -> 46188 | X92: =IFERROR(__xludf.DUMMYFUNCTION("""COMPUTED_VALUE"""),"TTAC") -> TTAC | Y92: =IFERROR(__xludf.DUMMYFUNCTION("""COMPUTED_VALUE"""),2.8333333333333335) -> 2.8333333 | Z92: =IFERROR(__xludf.DUMMYFUNCTION("""COMPUTED_VALUE"""),1.6749792701868151) -> 1.6749793 | AA92: =IFERROR(__xludf.DUMMYFUNCTION("""COMPUTED_VALUE"""),3.2) -> 3.2 | AB92: =IFERROR(__xludf.DUMMYFUNCTION("""COMPUTED_VALUE"""),"Dive Bar Named Nirvana") -> Dive Bar Named Nirvana | AC92: =IFERROR(__xludf.DUMMYFUNCTION("""COMPUTED_VALUE"""),"Dogpark") -> Dogpark | AD92: =IF(ISBLANK(W92), "", RANK(Y92, Y$86:Y$98) + RANK(AA92, AA$86:AA$98)/10 + RANK(Z92, Z$86:Z$98)/100) -> 1.12
